{
"meta":{"launch_mode":"Train","name":"experiment","iteration_count":1000,"learn_metrics":[{"best_value":"Min","name":"RMSE"}],"test_sets":[],"test_metrics":[],"learn_sets":["learn"]},
"iterations":[
{"learn":[15.78624361],"iteration":0,"passed_time":0.0358368189,"remaining_time":35.80098208},
{"learn":[15.33785363],"iteration":1,"passed_time":0.09174787437,"remaining_time":45.78218931},
{"learn":[14.89794361],"iteration":2,"passed_time":0.1320658445,"remaining_time":43.88988231},
{"learn":[14.47502665],"iteration":3,"passed_time":0.1813699525,"remaining_time":45.16111818},
{"learn":[14.06277387],"iteration":4,"passed_time":0.2425303319,"remaining_time":48.26353605},
{"learn":[13.66290317],"iteration":5,"passed_time":0.3046352146,"remaining_time":50.46790055},
{"learn":[13.27628624],"iteration":6,"passed_time":0.3799294543,"remaining_time":53.89570688},
{"learn":[12.8982501],"iteration":7,"passed_time":0.4080733542,"remaining_time":50.60109592},
{"learn":[12.52971997],"iteration":8,"passed_time":0.4782955929,"remaining_time":52.66565917},
{"learn":[12.17744636],"iteration":9,"passed_time":0.522600693,"remaining_time":51.7374686},
{"learn":[11.83167649],"iteration":10,"passed_time":0.5994351602,"remaining_time":53.89467031},
{"learn":[11.50198795],"iteration":11,"passed_time":0.6419998109,"remaining_time":52.85798443},
{"learn":[11.17732313],"iteration":12,"passed_time":0.7126074625,"remaining_time":54.10335119},
{"learn":[10.86780601],"iteration":13,"passed_time":0.7641212387,"remaining_time":53.81596724},
{"learn":[10.56545573],"iteration":14,"passed_time":0.8253602979,"remaining_time":54.19865956},
{"learn":[10.27263954],"iteration":15,"passed_time":0.8363946845,"remaining_time":51.43827309},
{"learn":[9.984922407],"iteration":16,"passed_time":0.8722504161,"remaining_time":50.43659759},
{"learn":[9.710550287],"iteration":17,"passed_time":0.8798494759,"remaining_time":48.00067696},
{"learn":[9.447782625],"iteration":18,"passed_time":0.9281331526,"remaining_time":47.92098014},
{"learn":[9.190814523],"iteration":19,"passed_time":1.006547175,"remaining_time":49.32081155},
{"learn":[8.941418376],"iteration":20,"passed_time":1.071095514,"remaining_time":49.93345277},
{"learn":[8.702459966],"iteration":21,"passed_time":1.118046105,"remaining_time":49.7022314},
{"learn":[8.465967818],"iteration":22,"passed_time":1.153627324,"remaining_time":49.00408241},
{"learn":[8.235962595],"iteration":23,"passed_time":1.219483352,"remaining_time":49.59232298},
{"learn":[8.01766616],"iteration":24,"passed_time":1.248768418,"remaining_time":48.70196831},
{"learn":[7.805253167],"iteration":25,"passed_time":1.282412284,"remaining_time":48.04113709},
{"learn":[7.60034041],"iteration":26,"passed_time":1.357616508,"remaining_time":48.92447639},
{"learn":[7.399171779],"iteration":27,"passed_time":1.405481119,"remaining_time":48.79027313},
{"learn":[7.20641802],"iteration":28,"passed_time":1.483370312,"remaining_time":49.6673301},
{"learn":[7.024434536],"iteration":29,"passed_time":1.582977562,"remaining_time":51.18294118},
{"learn":[6.846379562],"iteration":30,"passed_time":1.664473992,"remaining_time":52.02823543},
{"learn":[6.674323414],"iteration":31,"passed_time":1.703533945,"remaining_time":51.53190184},
{"learn":[6.504976109],"iteration":32,"passed_time":1.727439641,"remaining_time":50.61921614},
{"learn":[6.344638016],"iteration":33,"passed_time":1.763348632,"remaining_time":50.09984643},
{"learn":[6.189827517],"iteration":34,"passed_time":1.794758009,"remaining_time":49.48404225},
{"learn":[6.036884662],"iteration":35,"passed_time":1.875069895,"remaining_time":50.21020496},
{"learn":[5.888112061],"iteration":36,"passed_time":1.956697612,"remaining_time":50.92702162},
{"learn":[5.748788028],"iteration":37,"passed_time":1.97561329,"remaining_time":50.01421012},
{"learn":[5.61597722],"iteration":38,"passed_time":2.055726582,"remaining_time":50.65521142},
{"learn":[5.482464552],"iteration":39,"passed_time":2.126629739,"remaining_time":51.03911375},
{"learn":[5.351915479],"iteration":40,"passed_time":2.174404373,"remaining_time":50.85984862},
{"learn":[5.226191266],"iteration":41,"passed_time":2.226097392,"remaining_time":50.77622147},
{"learn":[5.104513208],"iteration":42,"passed_time":2.275156379,"remaining_time":50.63545708},
{"learn":[4.987597211],"iteration":43,"passed_time":2.327930016,"remaining_time":50.57957034},
{"learn":[4.875589934],"iteration":44,"passed_time":2.415478719,"remaining_time":51.26182614},
{"learn":[4.766866447],"iteration":45,"passed_time":2.483233111,"remaining_time":51.5000954},
{"learn":[4.661157929],"iteration":46,"passed_time":2.50103983,"remaining_time":50.71257358},
{"learn":[4.558121748],"iteration":47,"passed_time":2.580407375,"remaining_time":51.17807961},
{"learn":[4.463741556],"iteration":48,"passed_time":2.641680423,"remaining_time":51.27016494},
{"learn":[4.370308019],"iteration":49,"passed_time":2.721268222,"remaining_time":51.70409623},
{"learn":[4.284234948],"iteration":50,"passed_time":2.793546922,"remaining_time":51.98188293},
{"learn":[4.196853063],"iteration":51,"passed_time":2.841226015,"remaining_time":51.79773581},
{"learn":[4.111921965],"iteration":52,"passed_time":2.915941135,"remaining_time":52.10181614},
{"learn":[4.035543693],"iteration":53,"passed_time":2.957751135,"remaining_time":51.81541802},
{"learn":[3.962585215],"iteration":54,"passed_time":2.982343584,"remaining_time":51.24208521},
{"learn":[3.887379801],"iteration":55,"passed_time":3.02226558,"remaining_time":50.94676264},
{"learn":[3.814716208],"iteration":56,"passed_time":3.072745378,"remaining_time":50.83506827},
{"learn":[3.746220851],"iteration":57,"passed_time":3.145915564,"remaining_time":51.09400795},
{"learn":[3.678801768],"iteration":58,"passed_time":3.203416285,"remaining_time":51.09177499},
{"learn":[3.617269894],"iteration":59,"passed_time":3.2471229,"remaining_time":50.8715921},
{"learn":[3.56060683],"iteration":60,"passed_time":3.272223215,"remaining_time":50.37078032},
{"learn":[3.501518116],"iteration":61,"passed_time":3.298697105,"remaining_time":49.90609491},
{"learn":[3.444356036],"iteration":62,"passed_time":3.371058168,"remaining_time":50.13780164},
{"learn":[3.394914896],"iteration":63,"passed_time":3.42104658,"remaining_time":50.03280623},
{"learn":[3.343277821],"iteration":64,"passed_time":3.495144838,"remaining_time":50.27631421},
{"learn":[3.293059681],"iteration":65,"passed_time":3.568684327,"remaining_time":50.50229032},
{"learn":[3.245127258],"iteration":66,"passed_time":3.663585397,"remaining_time":51.01679367},
{"learn":[3.201352965],"iteration":67,"passed_time":3.760629871,"remaining_time":51.54275058},
{"learn":[3.161407853],"iteration":68,"passed_time":3.813032445,"remaining_time":51.44830734},
{"learn":[3.121433539],"iteration":69,"passed_time":3.843444547,"remaining_time":51.06290612},
{"learn":[3.080026467],"iteration":70,"passed_time":3.879390303,"remaining_time":50.75990974},
{"learn":[3.041160218],"iteration":71,"passed_time":3.934391412,"remaining_time":50.70993375},
{"learn":[3.002733489],"iteration":72,"passed_time":3.994870852,"remaining_time":50.72938739},
{"learn":[2.969738781],"iteration":73,"passed_time":4.031659888,"remaining_time":50.45023049},
{"learn":[2.934235109],"iteration":74,"passed_time":4.104440704,"remaining_time":50.62143535},
{"learn":[2.905899357],"iteration":75,"passed_time":4.158427487,"remaining_time":50.55772366},
{"learn":[2.874535964],"iteration":76,"passed_time":4.215523303,"remaining_time":50.53153258},
{"learn":[2.845115968],"iteration":77,"passed_time":4.284405153,"remaining_time":50.64386604},
{"learn":[2.814647214],"iteration":78,"passed_time":4.337119577,"remaining_time":50.56312823},
{"learn":[2.787019937],"iteration":79,"passed_time":4.404136032,"remaining_time":50.64756437},
{"learn":[2.76496037],"iteration":80,"passed_time":4.421692039,"remaining_time":50.16709856},
{"learn":[2.742054724],"iteration":81,"passed_time":4.465044159,"remaining_time":49.98671388},
{"learn":[2.717160107],"iteration":82,"passed_time":4.488004718,"remaining_time":49.58434128},
{"learn":[2.693739949],"iteration":83,"passed_time":4.580852321,"remaining_time":49.95310388},
{"learn":[2.673112552],"iteration":84,"passed_time":4.627973937,"remaining_time":49.81877826},
{"learn":[2.651520186],"iteration":85,"passed_time":4.730378475,"remaining_time":50.27402239},
{"learn":[2.630884912],"iteration":86,"passed_time":4.788815253,"remaining_time":50.25503823},
{"learn":[2.613092794],"iteration":87,"passed_time":4.839014396,"remaining_time":50.14978556},
{"learn":[2.593859495],"iteration":88,"passed_time":4.907540512,"remaining_time":50.23336412},
{"learn":[2.576642044],"iteration":89,"passed_time":4.978653984,"remaining_time":50.33972362},
{"learn":[2.558412169],"iteration":90,"passed_time":5.051573055,"remaining_time":50.46021876},
{"learn":[2.541035276],"iteration":91,"passed_time":5.125236105,"remaining_time":50.58385199},
{"learn":[2.526200886],"iteration":92,"passed_time":5.179617979,"remaining_time":50.515199},
{"learn":[2.511507238],"iteration":93,"passed_time":5.20906832,"remaining_time":50.20655211},
{"learn":[2.497020246],"iteration":94,"passed_time":5.284828876,"remaining_time":50.34494876},
{"learn":[2.48316795],"iteration":95,"passed_time":5.309336257,"remaining_time":49.99624975},
{"learn":[2.472536919],"iteration":96,"passed_time":5.386251624,"remaining_time":50.14211563},
{"learn":[2.460543455],"iteration":97,"passed_time":5.460223546,"remaining_time":50.25634325},
{"learn":[2.449305682],"iteration":98,"passed_time":5.507635392,"remaining_time":50.12504534},
{"learn":[2.437591265],"iteration":99,"passed_time":5.569952274,"remaining_time":50.12957047},
{"learn":[2.426029883],"iteration":100,"passed_time":5.635852459,"remaining_time":50.16466694},
{"learn":[2.415885251],"iteration":101,"passed_time":5.710046722,"remaining_time":50.27080349},
{"learn":[2.40909807],"iteration":102,"passed_time":5.726208452,"remaining_time":49.86804836},
{"learn":[2.398470548],"iteration":103,"passed_time":5.788785081,"remaining_time":49.87260992},
{"learn":[2.391495525],"iteration":104,"passed_time":5.809734407,"remaining_time":49.52106947},
{"learn":[2.384483699],"iteration":105,"passed_time":5.868843672,"remaining_time":49.49760607},
{"learn":[2.372717386],"iteration":106,"passed_time":5.914863656,"remaining_time":49.36423593},
{"learn":[2.362344223],"iteration":107,"passed_time":5.976607499,"remaining_time":49.36235082},
{"learn":[2.355006278],"iteration":108,"passed_time":6.042891635,"remaining_time":49.39648117},
{"learn":[2.347830908],"iteration":109,"passed_time":6.092662744,"remaining_time":49.29518039},
{"learn":[2.341007086],"iteration":110,"passed_time":6.131503136,"remaining_time":49.10726386},
{"learn":[2.336927707],"iteration":111,"passed_time":6.154905597,"remaining_time":48.79960866},
{"learn":[2.329685949],"iteration":112,"passed_time":6.223074095,"remaining_time":48.84837807},
{"learn":[2.323199808],"iteration":113,"passed_time":6.32041255,"remaining_time":49.1218028},
{"learn":[2.31790859],"iteration":114,"passed_time":6.378540272,"remaining_time":49.08702731},
{"learn":[2.314092421],"iteration":115,"passed_time":6.418935093,"remaining_time":48.91671226},
{"learn":[2.310153091],"iteration":116,"passed_time":6.474737435,"remaining_time":48.86489876},
{"learn":[2.304877793],"iteration":117,"passed_time":6.524800706,"remaining_time":48.77012053},
{"learn":[2.299105941],"iteration":118,"passed_time":6.623040193,"remaining_time":49.03275975},
{"learn":[2.294482196],"iteration":119,"passed_time":6.69862901,"remaining_time":49.12327941},
{"learn":[2.289513833],"iteration":120,"passed_time":6.774331854,"remaining_time":49.21188181},
{"learn":[2.284294743],"iteration":121,"passed_time":6.857696665,"remaining_time":49.35293173},
{"learn":[2.281581272],"iteration":122,"passed_time":6.894954096,"remaining_time":49.16158327},
{"learn":[2.276449733],"iteration":123,"passed_time":6.974677573,"remaining_time":49.27272221},
{"learn":[2.272001804],"iteration":124,"passed_time":7.052745432,"remaining_time":49.36921803},
{"learn":[2.268336587],"iteration":125,"passed_time":7.123319271,"remaining_time":49.41096066},
{"learn":[2.263987107],"iteration":126,"passed_time":7.163830541,"remaining_time":49.24428395},
{"learn":[2.260643282],"iteration":127,"passed_time":7.211657876,"remaining_time":49.12941928},
{"learn":[2.255451207],"iteration":128,"passed_time":7.27477517,"remaining_time":49.1188308},
{"learn":[2.250925467],"iteration":129,"passed_time":7.336290822,"remaining_time":49.0967155},
{"learn":[2.245738727],"iteration":130,"passed_time":7.377345046,"remaining_time":48.93826599},
{"learn":[2.240218376],"iteration":131,"passed_time":7.456604121,"remaining_time":49.03282104},
{"learn":[2.237995303],"iteration":132,"passed_time":7.532756085,"remaining_time":49.10450771},
{"learn":[2.235347367],"iteration":133,"passed_time":7.590919144,"remaining_time":49.05773118},
{"learn":[2.234191211],"iteration":134,"passed_time":7.609527756,"remaining_time":48.75734451},
{"learn":[2.230928566],"iteration":135,"passed_time":7.713131702,"remaining_time":49.00107199},
{"learn":[2.22779338],"iteration":136,"passed_time":7.792049015,"remaining_time":49.08422117},
{"learn":[2.224951195],"iteration":137,"passed_time":7.872470395,"remaining_time":49.17441652},
{"learn":[2.220766511],"iteration":138,"passed_time":7.971160659,"remaining_time":49.3753189},
{"learn":[2.215738703],"iteration":139,"passed_time":8.038005995,"remaining_time":49.37632254},
{"learn":[2.211183167],"iteration":140,"passed_time":8.132380454,"remaining_time":49.54407667},
{"learn":[2.207586765],"iteration":141,"passed_time":8.196925377,"remaining_time":49.52790122},
{"learn":[2.202650735],"iteration":142,"passed_time":8.243032495,"remaining_time":49.40055138},
{"learn":[2.199195033],"iteration":143,"passed_time":8.31804397,"remaining_time":49.44615026},
{"learn":[2.196819882],"iteration":144,"passed_time":8.360206082,"remaining_time":49.29638759},
{"learn":[2.193420733],"iteration":145,"passed_time":8.431261387,"remaining_time":49.31710428},
{"learn":[2.191895632],"iteration":146,"passed_time":8.474296633,"remaining_time":49.17397978},
{"learn":[2.189031865],"iteration":147,"passed_time":8.521582954,"remaining_time":49.05668025},
{"learn":[2.186509671],"iteration":148,"passed_time":8.593835866,"remaining_time":49.08291491},
{"learn":[2.183410738],"iteration":149,"passed_time":8.637027797,"remaining_time":48.94315751},
{"learn":[2.180515335],"iteration":150,"passed_time":8.704795056,"remaining_time":48.94285432},
{"learn":[2.178390353],"iteration":151,"passed_time":8.775192502,"remaining_time":48.95633711},
{"learn":[2.174926815],"iteration":152,"passed_time":8.889266659,"remaining_time":49.21051543},
{"learn":[2.172643784],"iteration":153,"passed_time":8.960933609,"remaining_time":49.22694697},
{"learn":[2.170846442],"iteration":154,"passed_time":9.066572718,"remaining_time":49.42744482},
{"learn":[2.169980324],"iteration":155,"passed_time":9.092089272,"remaining_time":49.19053427},
{"learn":[2.169517464],"iteration":156,"passed_time":9.110455296,"remaining_time":48.91792239},
{"learn":[2.168151976],"iteration":157,"passed_time":9.164820424,"remaining_time":48.84037213},
{"learn":[2.167627071],"iteration":158,"passed_time":9.192414464,"remaining_time":48.62151299},
{"learn":[2.165558047],"iteration":159,"passed_time":9.268642197,"remaining_time":48.66037153},
{"learn":[2.163988585],"iteration":160,"passed_time":9.318009623,"remaining_time":48.55782654},
{"learn":[2.162003087],"iteration":161,"passed_time":9.408880677,"remaining_time":48.67062967},
{"learn":[2.160899369],"iteration":162,"passed_time":9.435617582,"remaining_time":48.45160685},
{"learn":[2.159644509],"iteration":163,"passed_time":9.505626937,"remaining_time":48.45551292},
{"learn":[2.157741589],"iteration":164,"passed_time":9.555301241,"remaining_time":48.35561537},
{"learn":[2.155717104],"iteration":165,"passed_time":9.655186016,"remaining_time":48.50858516},
{"learn":[2.15390023],"iteration":166,"passed_time":9.689121865,"remaining_time":48.32957194},
{"learn":[2.152274713],"iteration":167,"passed_time":9.773251926,"remaining_time":48.40086668},
{"learn":[2.151106967],"iteration":168,"passed_time":9.873304521,"remaining_time":48.54861572},
{"learn":[2.148573674],"iteration":169,"passed_time":9.931013568,"remaining_time":48.4867133},
{"learn":[2.146752743],"iteration":170,"passed_time":10.00732184,"remaining_time":48.51502812},
{"learn":[2.144863304],"iteration":171,"passed_time":10.09038112,"remaining_time":48.57462538},
{"learn":[2.143836539],"iteration":172,"passed_time":10.20719157,"remaining_time":48.79391576},
{"learn":[2.141437614],"iteration":173,"passed_time":10.28600732,"remaining_time":48.82897727},
{"learn":[2.139883085],"iteration":174,"passed_time":10.36528792,"remaining_time":48.86492876},
{"learn":[2.138453176],"iteration":175,"passed_time":10.41985664,"remaining_time":48.78387425},
{"learn":[2.137568187],"iteration":176,"passed_time":10.453918,"remaining_time":48.60776563},
{"learn":[2.136313101],"iteration":177,"passed_time":10.53231891,"remaining_time":48.63801205},
{"learn":[2.134806688],"iteration":178,"passed_time":10.61948029,"remaining_time":48.70722522},
{"learn":[2.133984084],"iteration":179,"passed_time":10.65344594,"remaining_time":48.53236483},
{"learn":[2.132683157],"iteration":180,"passed_time":10.72543162,"remaining_time":48.53109668},
{"learn":[2.129782268],"iteration":181,"passed_time":10.80527749,"remaining_time":48.56437905},
{"learn":[2.127688336],"iteration":182,"passed_time":10.90765591,"remaining_time":48.69702121},
{"learn":[2.124616351],"iteration":183,"passed_time":10.9843429,"remaining_time":48.71317288},
{"learn":[2.123011131],"iteration":184,"passed_time":11.06510984,"remaining_time":48.74629471},
{"learn":[2.121987943],"iteration":185,"passed_time":11.1290463,"remaining_time":48.70453594},
{"learn":[2.119962524],"iteration":186,"passed_time":11.17291246,"remaining_time":48.57528252},
{"learn":[2.119496024],"iteration":187,"passed_time":11.25425078,"remaining_time":48.60878527},
{"learn":[2.113988109],"iteration":188,"passed_time":11.34880342,"remaining_time":48.69777552},
{"learn":[2.113490224],"iteration":189,"passed_time":11.41117782,"remaining_time":48.6476528},
{"learn":[2.112520996],"iteration":190,"passed_time":11.45593946,"remaining_time":48.52280119},
{"learn":[2.111339791],"iteration":191,"passed_time":11.51425018,"remaining_time":48.45580284},
{"learn":[2.110428283],"iteration":192,"passed_time":11.5866654,"remaining_time":48.44787037},
{"learn":[2.109323731],"iteration":193,"passed_time":11.63288968,"remaining_time":48.33045919},
{"learn":[2.107446503],"iteration":194,"passed_time":11.70865389,"remaining_time":48.33572505},
{"learn":[2.107047104],"iteration":195,"passed_time":11.76654403,"remaining_time":48.26684388},
{"learn":[2.106235638],"iteration":196,"passed_time":11.82722995,"remaining_time":48.20947029},
{"learn":[2.105290791],"iteration":197,"passed_time":11.89291275,"remaining_time":48.17230314},
{"learn":[2.104605914],"iteration":198,"passed_time":11.96594682,"remaining_time":48.16443921},
{"learn":[2.10409802],"iteration":199,"passed_time":12.02577446,"remaining_time":48.10309783},
{"learn":[2.103179765],"iteration":200,"passed_time":12.12161305,"remaining_time":48.18491955},
{"learn":[2.099076691],"iteration":201,"passed_time":12.1882407,"remaining_time":48.14958453},
{"learn":[2.098345125],"iteration":202,"passed_time":12.25849261,"remaining_time":48.1281705},
{"learn":[2.097871062],"iteration":203,"passed_time":12.30740879,"remaining_time":48.02302646},
{"learn":[2.097004938],"iteration":204,"passed_time":12.36897705,"remaining_time":47.96749638},
{"learn":[2.095956148],"iteration":205,"passed_time":12.40276518,"remaining_time":47.80483277},
{"learn":[2.094574295],"iteration":206,"passed_time":12.46590232,"remaining_time":47.75584803},
{"learn":[2.093474999],"iteration":207,"passed_time":12.52522956,"remaining_time":47.69222023},
{"learn":[2.092563161],"iteration":208,"passed_time":12.61098117,"remaining_time":47.72864165},
{"learn":[2.091461803],"iteration":209,"passed_time":12.70599686,"remaining_time":47.79875011},
{"learn":[2.09001633],"iteration":210,"passed_time":12.82178946,"remaining_time":47.94498522},
{"learn":[2.089876083],"iteration":211,"passed_time":12.87149701,"remaining_time":47.84311154},
{"learn":[2.087967005],"iteration":212,"passed_time":12.92157781,"remaining_time":47.74310674},
{"learn":[2.087495312],"iteration":213,"passed_time":13.00261768,"remaining_time":47.75727802},
{"learn":[2.08681634],"iteration":214,"passed_time":13.05504895,"remaining_time":47.66610896},
{"learn":[2.085920242],"iteration":215,"passed_time":13.10638916,"remaining_time":47.57133842},
{"learn":[2.085910979],"iteration":216,"passed_time":13.13910883,"remaining_time":47.40977977},
{"learn":[2.085856466],"iteration":217,"passed_time":13.17494132,"remaining_time":47.26056934},
{"learn":[2.085594325],"iteration":218,"passed_time":13.25096695,"remaining_time":47.25573144},
{"learn":[2.084305724],"iteration":219,"passed_time":13.32199789,"remaining_time":47.23253797},
{"learn":[2.08369574],"iteration":220,"passed_time":13.36562444,"remaining_time":47.11231419},
{"learn":[2.083129595],"iteration":221,"passed_time":13.38697277,"remaining_time":46.91470639},
{"learn":[2.082052744],"iteration":222,"passed_time":13.50436298,"remaining_time":47.05331854},
{"learn":[2.081290749],"iteration":223,"passed_time":13.59203347,"remaining_time":47.08668738},
{"learn":[2.080651544],"iteration":224,"passed_time":13.64222441,"remaining_time":46.98988407},
{"learn":[2.079878697],"iteration":225,"passed_time":13.75782738,"remaining_time":47.11751502},
{"learn":[2.079380425],"iteration":226,"passed_time":13.83659498,"remaining_time":47.11756793},
{"learn":[2.078851859],"iteration":227,"passed_time":13.90935927,"remaining_time":47.09660245},
{"learn":[2.078815428],"iteration":228,"passed_time":13.93974127,"remaining_time":46.93249134},
{"learn":[2.077016662],"iteration":229,"passed_time":13.99154359,"remaining_time":46.84125463},
{"learn":[2.076456172],"iteration":230,"passed_time":14.03887305,"remaining_time":46.73546917},
{"learn":[2.075589999],"iteration":231,"passed_time":14.09046818,"remaining_time":46.64430846},
{"learn":[2.07503502],"iteration":232,"passed_time":14.13861115,"remaining_time":46.54212339},
{"learn":[2.073924569],"iteration":233,"passed_time":14.20551235,"remaining_time":46.50180537},
{"learn":[2.07303445],"iteration":234,"passed_time":14.23093823,"remaining_time":46.32624571},
{"learn":[2.071745844],"iteration":235,"passed_time":14.29906236,"remaining_time":46.29018492},
{"learn":[2.071138973],"iteration":236,"passed_time":14.34104746,"remaining_time":46.16970131},
{"learn":[2.068482006],"iteration":237,"passed_time":14.41349403,"remaining_time":46.14740526},
{"learn":[2.067304315],"iteration":238,"passed_time":14.48089059,"remaining_time":46.10860979},
{"learn":[2.067263264],"iteration":239,"passed_time":14.5506375,"remaining_time":46.07701875},
{"learn":[2.066836874],"iteration":240,"passed_time":14.60106635,"remaining_time":45.98427121},
{"learn":[2.066493943],"iteration":241,"passed_time":14.6730187,"remaining_time":45.95928996},
{"learn":[2.065931416],"iteration":242,"passed_time":14.71905748,"remaining_time":45.85319553},
{"learn":[2.065191462],"iteration":243,"passed_time":14.82325166,"remaining_time":45.92777975},
{"learn":[2.064223237],"iteration":244,"passed_time":14.86282743,"remaining_time":45.80177432},
{"learn":[2.062525022],"iteration":245,"passed_time":14.94804825,"remaining_time":45.81637553},
{"learn":[2.062414435],"iteration":246,"passed_time":14.98870868,"remaining_time":45.69432242},
{"learn":[2.06211888],"iteration":247,"passed_time":15.07474295,"remaining_time":45.71051089},
{"learn":[2.061449437],"iteration":248,"passed_time":15.13227523,"remaining_time":45.63991445},
{"learn":[2.061303997],"iteration":249,"passed_time":15.1575758,"remaining_time":45.4727274},
{"learn":[2.060358379],"iteration":250,"passed_time":15.21947668,"remaining_time":45.41588857},
{"learn":[2.059780824],"iteration":251,"passed_time":15.25788936,"remaining_time":45.28929063},
{"learn":[2.058288652],"iteration":252,"passed_time":15.33846185,"remaining_time":45.28786956},
{"learn":[2.057740133],"iteration":253,"passed_time":15.39300727,"remaining_time":45.20938355},
{"learn":[2.056805045],"iteration":254,"passed_time":15.4324093,"remaining_time":45.08684286},
{"learn":[2.056330009],"iteration":255,"passed_time":15.48081938,"remaining_time":44.99113133},
{"learn":[2.056276604],"iteration":256,"passed_time":15.51572409,"remaining_time":44.85674318},
{"learn":[2.054801417],"iteration":257,"passed_time":15.57362207,"remaining_time":44.78925418},
{"learn":[2.053718173],"iteration":258,"passed_time":15.63637206,"remaining_time":44.73572082},
{"learn":[2.052679824],"iteration":259,"passed_time":15.68790937,"remaining_time":44.6502036},
{"learn":[2.048595856],"iteration":260,"passed_time":15.77102207,"remaining_time":44.65434986},
{"learn":[2.046944516],"iteration":261,"passed_time":15.83559457,"remaining_time":44.60560607},
{"learn":[2.046004591],"iteration":262,"passed_time":15.89675641,"remaining_time":44.54718432},
{"learn":[2.044222144],"iteration":263,"passed_time":15.94151394,"remaining_time":44.44300856},
{"learn":[2.043453041],"iteration":264,"passed_time":15.99412073,"remaining_time":44.36105184},
{"learn":[2.042539302],"iteration":265,"passed_time":16.04350406,"remaining_time":44.27042098},
{"learn":[2.042329425],"iteration":266,"passed_time":16.08362526,"remaining_time":44.15467159},
{"learn":[2.041792519],"iteration":267,"passed_time":16.17187102,"remaining_time":44.1709313},
{"learn":[2.041610642],"iteration":268,"passed_time":16.2171199,"remaining_time":44.06957116},
{"learn":[2.041102792],"iteration":269,"passed_time":16.27087927,"remaining_time":43.99163655},
{"learn":[2.040164412],"iteration":270,"passed_time":16.33254345,"remaining_time":43.93514455},
{"learn":[2.039546471],"iteration":271,"passed_time":16.38128153,"remaining_time":43.84401821},
{"learn":[2.039162984],"iteration":272,"passed_time":16.45241836,"remaining_time":43.81285035},
{"learn":[2.038206559],"iteration":273,"passed_time":16.49491908,"remaining_time":43.70551551},
{"learn":[2.038039862],"iteration":274,"passed_time":16.58416133,"remaining_time":43.72187987},
{"learn":[2.03708144],"iteration":275,"passed_time":16.6304822,"remaining_time":43.62488808},
{"learn":[2.036694736],"iteration":276,"passed_time":16.68223283,"remaining_time":43.54243443},
{"learn":[2.031692601],"iteration":277,"passed_time":16.78957902,"remaining_time":43.60459012},
{"learn":[2.031419904],"iteration":278,"passed_time":16.87308118,"remaining_time":43.6039123},
{"learn":[2.031124795],"iteration":279,"passed_time":16.93290462,"remaining_time":43.54175473},
{"learn":[2.03108194],"iteration":280,"passed_time":16.95893884,"remaining_time":43.39315669},
{"learn":[2.030462834],"iteration":281,"passed_time":17.05293805,"remaining_time":43.41847348},
{"learn":[2.029886906],"iteration":282,"passed_time":17.09501545,"remaining_time":43.31139958},
{"learn":[2.028473903],"iteration":283,"passed_time":17.19033874,"remaining_time":43.33902302},
{"learn":[2.028282314],"iteration":284,"passed_time":17.24147933,"remaining_time":43.25493938},
{"learn":[2.027597634],"iteration":285,"passed_time":17.29296027,"remaining_time":43.17193578},
{"learn":[2.026607876],"iteration":286,"passed_time":17.38924633,"remaining_time":43.20046215},
{"learn":[2.025861165],"iteration":287,"passed_time":17.46669053,"remaining_time":43.18154048},
{"learn":[2.025654411],"iteration":288,"passed_time":17.5297405,"remaining_time":43.12680102},
{"learn":[2.025164215],"iteration":289,"passed_time":17.58074027,"remaining_time":43.04250203},
{"learn":[2.024209909],"iteration":290,"passed_time":17.62597927,"remaining_time":42.94439623},
{"learn":[2.022422719],"iteration":291,"passed_time":17.69027998,"remaining_time":42.89287064},
{"learn":[2.021249154],"iteration":292,"passed_time":17.75122038,"remaining_time":42.83314952},
{"learn":[2.019180101],"iteration":293,"passed_time":17.82754981,"remaining_time":42.81037472},
{"learn":[2.018895773],"iteration":294,"passed_time":17.88931737,"remaining_time":42.75243643},
{"learn":[2.018401409],"iteration":295,"passed_time":17.9328538,"remaining_time":42.65111174},
{"learn":[2.017540366],"iteration":296,"passed_time":18.01522785,"remaining_time":42.64210499},
{"learn":[2.016235849],"iteration":297,"passed_time":18.11437319,"remaining_time":42.67211403},
{"learn":[2.015486251],"iteration":298,"passed_time":18.1778061,"remaining_time":42.61753203},
{"learn":[2.014023594],"iteration":299,"passed_time":18.21955916,"remaining_time":42.51230471},
{"learn":[2.013423338],"iteration":300,"passed_time":18.31561119,"remaining_time":42.53359543},
{"learn":[2.013148224],"iteration":301,"passed_time":18.36261481,"remaining_time":42.44074549},
{"learn":[2.012515817],"iteration":302,"passed_time":18.45660829,"remaining_time":42.45629036},
{"learn":[2.012515763],"iteration":303,"passed_time":18.47358681,"remaining_time":42.29479085},
{"learn":[2.012404648],"iteration":304,"passed_time":18.53379994,"remaining_time":42.23275724},
{"learn":[2.01169841],"iteration":305,"passed_time":18.59873758,"remaining_time":42.18145058},
{"learn":[2.011336862],"iteration":306,"passed_time":18.65786504,"remaining_time":42.11693966},
{"learn":[2.011212174],"iteration":307,"passed_time":18.73616202,"remaining_time":42.09553285},
{"learn":[2.00997565],"iteration":308,"passed_time":18.78632355,"remaining_time":42.01084004},
{"learn":[2.00927274],"iteration":309,"passed_time":18.85760716,"remaining_time":41.97338368},
{"learn":[2.00802101],"iteration":310,"passed_time":18.91557082,"remaining_time":41.90620031},
{"learn":[2.00680901],"iteration":311,"passed_time":19.00307669,"remaining_time":41.90422039},
{"learn":[2.006608026],"iteration":312,"passed_time":19.06544248,"remaining_time":41.84651432},
{"learn":[2.006128517],"iteration":313,"passed_time":19.10867356,"remaining_time":41.74697473},
{"learn":[2.005141897],"iteration":314,"passed_time":19.18700637,"remaining_time":41.72412497},
{"learn":[2.004266204],"iteration":315,"passed_time":19.2475356,"remaining_time":41.66238719},
{"learn":[2.00360666],"iteration":316,"passed_time":19.34119147,"remaining_time":41.67203082},
{"learn":[2.003419669],"iteration":317,"passed_time":19.4065677,"remaining_time":41.62037475},
{"learn":[2.002864213],"iteration":318,"passed_time":19.46827875,"remaining_time":41.56080825},
{"learn":[1.998959115],"iteration":319,"passed_time":19.56143924,"remaining_time":41.56805839},
{"learn":[1.997808021],"iteration":320,"passed_time":19.64125842,"remaining_time":41.54646251},
{"learn":[1.993196963],"iteration":321,"passed_time":19.70307099,"remaining_time":41.48659047},
{"learn":[1.992310394],"iteration":322,"passed_time":19.77429226,"remaining_time":41.44642681},
{"learn":[1.991680655],"iteration":323,"passed_time":19.84347779,"remaining_time":41.40182403},
{"learn":[1.986776221],"iteration":324,"passed_time":19.91998694,"remaining_time":41.37228056},
{"learn":[1.985962615],"iteration":325,"passed_time":19.99931564,"remaining_time":41.34827836},
{"learn":[1.985750712],"iteration":326,"passed_time":20.08418762,"remaining_time":41.33534639},
{"learn":[1.984673437],"iteration":327,"passed_time":20.12567841,"remaining_time":41.23309723},
{"learn":[1.98431386],"iteration":328,"passed_time":20.22029719,"remaining_time":41.23957269},
{"learn":[1.983044987],"iteration":329,"passed_time":20.29894575,"remaining_time":41.21301107},
{"learn":[1.982337299],"iteration":330,"passed_time":20.38471633,"remaining_time":41.20052939},
{"learn":[1.981378738],"iteration":331,"passed_time":20.4783402,"remaining_time":41.2034074},
{"learn":[1.981048917],"iteration":332,"passed_time":20.54470343,"remaining_time":41.15110266},
{"learn":[1.98059431],"iteration":333,"passed_time":20.62173768,"remaining_time":41.1199919},
{"learn":[1.980226776],"iteration":334,"passed_time":20.70006749,"remaining_time":41.09117874},
{"learn":[1.979522352],"iteration":335,"passed_time":20.7633568,"remaining_time":41.03234796},
{"learn":[1.975983583],"iteration":336,"passed_time":20.81786833,"remaining_time":40.95622166},
{"learn":[1.974991198],"iteration":337,"passed_time":20.88159748,"remaining_time":40.89827671},
{"learn":[1.974711512],"iteration":338,"passed_time":20.9632557,"remaining_time":40.87525668},
{"learn":[1.969375682],"iteration":339,"passed_time":21.07722967,"remaining_time":40.9146223},
{"learn":[1.968830698],"iteration":340,"passed_time":21.13662525,"remaining_time":40.84761301},
{"learn":[1.967981378],"iteration":341,"passed_time":21.20158579,"remaining_time":40.79135513},
{"learn":[1.966856939],"iteration":342,"passed_time":21.25945082,"remaining_time":40.72145536},
{"learn":[1.965935565],"iteration":343,"passed_time":21.31897836,"remaining_time":40.65479594},
{"learn":[1.965600806],"iteration":344,"passed_time":21.3717186,"remaining_time":40.57529184},
{"learn":[1.965270602],"iteration":345,"passed_time":21.43963218,"remaining_time":40.52462267},
{"learn":[1.9622378],"iteration":346,"passed_time":21.51863049,"remaining_time":40.49471386},
{"learn":[1.961953837],"iteration":347,"passed_time":21.59448407,"remaining_time":40.45863107},
{"learn":[1.961096523],"iteration":348,"passed_time":21.65853646,"remaining_time":40.40030727},
{"learn":[1.959574353],"iteration":349,"passed_time":21.73489069,"remaining_time":40.364797},
{"learn":[1.959311083],"iteration":350,"passed_time":21.80472548,"remaining_time":40.31699953},
{"learn":[1.959182591],"iteration":351,"passed_time":21.89098782,"remaining_time":40.29931848},
{"learn":[1.957914701],"iteration":352,"passed_time":21.97425632,"remaining_time":40.27576158},
{"learn":[1.9575988],"iteration":353,"passed_time":22.05483387,"remaining_time":40.24695672},
{"learn":[1.956804285],"iteration":354,"passed_time":22.11768467,"remaining_time":40.18565243},
{"learn":[1.956217859],"iteration":355,"passed_time":22.19350812,"remaining_time":40.14780682},
{"learn":[1.955853845],"iteration":356,"passed_time":22.25911732,"remaining_time":40.09135135},
{"learn":[1.954908283],"iteration":357,"passed_time":22.37472031,"remaining_time":40.12449844},
{"learn":[1.954631234],"iteration":358,"passed_time":22.45485878,"remaining_time":40.09349437},
{"learn":[1.953734297],"iteration":359,"passed_time":22.53373825,"remaining_time":40.05997911},
{"learn":[1.95283869],"iteration":360,"passed_time":22.61119459,"remaining_time":40.02369346},
{"learn":[1.952413275],"iteration":361,"passed_time":22.67941407,"remaining_time":39.97090103},
{"learn":[1.951967367],"iteration":362,"passed_time":22.75526041,"remaining_time":39.93140738},
{"learn":[1.951640212],"iteration":363,"passed_time":22.79780945,"remaining_time":39.8335352},
{"learn":[1.95120055],"iteration":364,"passed_time":22.87223908,"remaining_time":39.79142963},
{"learn":[1.948232079],"iteration":365,"passed_time":22.95139741,"remaining_time":39.75733868},
{"learn":[1.947862566],"iteration":366,"passed_time":23.03116713,"remaining_time":39.72405665},
{"learn":[1.947622476],"iteration":367,"passed_time":23.09745155,"remaining_time":39.66736244},
{"learn":[1.947071508],"iteration":368,"passed_time":23.1731785,"remaining_time":39.62676323},
{"learn":[1.946893305],"iteration":369,"passed_time":23.25524118,"remaining_time":39.596762},
{"learn":[1.945733976],"iteration":370,"passed_time":23.31289966,"remaining_time":39.52510482},
{"learn":[1.944986386],"iteration":371,"passed_time":23.374816,"remaining_time":39.46071089},
{"learn":[1.944053828],"iteration":372,"passed_time":23.44960711,"remaining_time":39.41797228},
{"learn":[1.943886918],"iteration":373,"passed_time":23.51387943,"remaining_time":39.35745594},
{"learn":[1.942988635],"iteration":374,"passed_time":23.55389068,"remaining_time":39.25648446},
{"learn":[1.942110083],"iteration":375,"passed_time":23.63199745,"remaining_time":39.2190596},
{"learn":[1.93792936],"iteration":376,"passed_time":23.74856817,"remaining_time":39.24498135},
{"learn":[1.937439331],"iteration":377,"passed_time":23.83514936,"remaining_time":39.22080133},
{"learn":[1.937387996],"iteration":378,"passed_time":23.9290886,"remaining_time":39.20834833},
{"learn":[1.937214536],"iteration":379,"passed_time":23.99362193,"remaining_time":39.14748841},
{"learn":[1.936771748],"iteration":380,"passed_time":24.09399559,"remaining_time":39.14483798},
{"learn":[1.936345638],"iteration":381,"passed_time":24.17236122,"remaining_time":39.1060713},
{"learn":[1.935648461],"iteration":382,"passed_time":24.24800533,"remaining_time":39.06271355},
{"learn":[1.934937614],"iteration":383,"passed_time":24.31151903,"remaining_time":38.99972844},
{"learn":[1.932827753],"iteration":384,"passed_time":24.3918014,"remaining_time":38.96352691},
{"learn":[1.931852954],"iteration":385,"passed_time":24.46831331,"remaining_time":38.92109942},
{"learn":[1.931709793],"iteration":386,"passed_time":24.54714124,"remaining_time":38.88216429},
{"learn":[1.927984958],"iteration":387,"passed_time":24.62749864,"remaining_time":38.845436},
{"learn":[1.927302618],"iteration":388,"passed_time":24.69364576,"remaining_time":38.7861634},
{"learn":[1.926280643],"iteration":389,"passed_time":24.78950895,"remaining_time":38.77333452},
{"learn":[1.925947948],"iteration":390,"passed_time":24.8880617,"remaining_time":38.76427002},
{"learn":[1.925276457],"iteration":391,"passed_time":24.96741176,"remaining_time":38.72496519},
{"learn":[1.925040562],"iteration":392,"passed_time":25.02988534,"remaining_time":38.65939034},
{"learn":[1.924197959],"iteration":393,"passed_time":25.10493083,"remaining_time":38.61316772},
{"learn":[1.923797227],"iteration":394,"passed_time":25.1688369,"remaining_time":38.54973753},
{"learn":[1.923370621],"iteration":395,"passed_time":25.21322685,"remaining_time":38.45653792},
{"learn":[1.923140362],"iteration":396,"passed_time":25.29237894,"remaining_time":38.41638414},
{"learn":[1.922857799],"iteration":397,"passed_time":25.37553122,"remaining_time":38.38208492},
{"learn":[1.922778144],"iteration":398,"passed_time":25.46577292,"remaining_time":38.35821937},
{"learn":[1.921837525],"iteration":399,"passed_time":25.52827573,"remaining_time":38.2924136},
{"learn":[1.918031895],"iteration":400,"passed_time":25.60000153,"remaining_time":38.24040129},
{"learn":[1.915462201],"iteration":401,"passed_time":25.68751694,"remaining_time":38.21177894},
{"learn":[1.914728317],"iteration":402,"passed_time":25.76098519,"remaining_time":38.16205499},
{"learn":[1.914452607],"iteration":403,"passed_time":25.83873271,"remaining_time":38.11852647},
{"learn":[1.914190252],"iteration":404,"passed_time":25.87869361,"remaining_time":38.0193153},
{"learn":[1.913401596],"iteration":405,"passed_time":25.9733488,"remaining_time":38.00041672},
{"learn":[1.912682665],"iteration":406,"passed_time":26.03742184,"remaining_time":37.93658759},
{"learn":[1.909353067],"iteration":407,"passed_time":26.11689105,"remaining_time":37.89509682},
{"learn":[1.908475436],"iteration":408,"passed_time":26.19747297,"remaining_time":37.85502818},
{"learn":[1.908233669],"iteration":409,"passed_time":26.27278409,"remaining_time":37.80717711},
{"learn":[1.90802952],"iteration":410,"passed_time":26.33636984,"remaining_time":37.74238889},
{"learn":[1.907551906],"iteration":411,"passed_time":26.41228474,"remaining_time":37.69520249},
{"learn":[1.906697762],"iteration":412,"passed_time":26.47516943,"remaining_time":37.62935704},
{"learn":[1.905564764],"iteration":413,"passed_time":26.53944503,"remaining_time":37.56549466},
{"learn":[1.905426576],"iteration":414,"passed_time":26.61651259,"remaining_time":37.51966232},
{"learn":[1.904986141],"iteration":415,"passed_time":26.65608349,"remaining_time":37.42104028},
{"learn":[1.902144289],"iteration":416,"passed_time":26.75546606,"remaining_time":37.40632305},
{"learn":[1.901738905],"iteration":417,"passed_time":26.83151139,"remaining_time":37.35870724},
{"learn":[1.901419256],"iteration":418,"passed_time":26.899788,"remaining_time":37.30018336},
{"learn":[1.900899934],"iteration":419,"passed_time":26.99186457,"remaining_time":37.27447965},
{"learn":[1.900118421],"iteration":420,"passed_time":27.05240153,"remaining_time":37.20508429},
{"learn":[1.899642295],"iteration":421,"passed_time":27.11375923,"remaining_time":37.13685505},
{"learn":[1.899411105],"iteration":422,"passed_time":27.1486217,"remaining_time":37.03251707},
{"learn":[1.898846305],"iteration":423,"passed_time":27.23028115,"remaining_time":36.99208006},
{"learn":[1.898648692],"iteration":424,"passed_time":27.31042423,"remaining_time":36.94939749},
{"learn":[1.89856682],"iteration":425,"passed_time":27.37408066,"remaining_time":36.88432465},
{"learn":[1.897879954],"iteration":426,"passed_time":27.46987553,"remaining_time":36.86238566},
{"learn":[1.896890355],"iteration":427,"passed_time":27.56898731,"remaining_time":36.84453444},
{"learn":[1.896621841],"iteration":428,"passed_time":27.63317399,"remaining_time":36.77981899},
{"learn":[1.895536949],"iteration":429,"passed_time":27.70744212,"remaining_time":36.72846979},
{"learn":[1.895325855],"iteration":430,"passed_time":27.78947884,"remaining_time":36.68727021},
{"learn":[1.894797765],"iteration":431,"passed_time":27.8885863,"remaining_time":36.66832643},
{"learn":[1.894667682],"iteration":432,"passed_time":27.95597879,"remaining_time":36.60748262},
{"learn":[1.894252796],"iteration":433,"passed_time":28.04741241,"remaining_time":36.5779618},
{"learn":[1.894121838],"iteration":434,"passed_time":28.12718873,"remaining_time":36.53301525},
{"learn":[1.893671715],"iteration":435,"passed_time":28.19058894,"remaining_time":36.46672515},
{"learn":[1.89171183],"iteration":436,"passed_time":28.23371603,"remaining_time":36.37432981},
{"learn":[1.891215267],"iteration":437,"passed_time":28.32621957,"remaining_time":36.3455146},
{"learn":[1.890472462],"iteration":438,"passed_time":28.40624754,"remaining_time":36.30046667},
{"learn":[1.888514325],"iteration":439,"passed_time":28.47128356,"remaining_time":36.23617907},
{"learn":[1.887953418],"iteration":440,"passed_time":28.54150213,"remaining_time":36.17845734},
{"learn":[1.88753576],"iteration":441,"passed_time":28.62616589,"remaining_time":36.13891531},
{"learn":[1.886728363],"iteration":442,"passed_time":28.68832859,"remaining_time":36.07087815},
{"learn":[1.886357596],"iteration":443,"passed_time":28.73269127,"remaining_time":35.98057736},
{"learn":[1.886191826],"iteration":444,"passed_time":28.80913909,"remaining_time":35.93049932},
{"learn":[1.884019425],"iteration":445,"passed_time":28.88738541,"remaining_time":35.88253703},
{"learn":[1.883723718],"iteration":446,"passed_time":28.94746954,"remaining_time":35.81197015},
{"learn":[1.883212361],"iteration":447,"passed_time":29.0246521,"remaining_time":35.76251776},
{"learn":[1.882332425],"iteration":448,"passed_time":29.0877493,"remaining_time":35.69565671},
{"learn":[1.882239132],"iteration":449,"passed_time":29.14787151,"remaining_time":35.62517629},
{"learn":[1.881034085],"iteration":450,"passed_time":29.19095958,"remaining_time":35.53400623},
{"learn":[1.880569871],"iteration":451,"passed_time":29.28928295,"remaining_time":35.51001561},
{"learn":[1.880052881],"iteration":452,"passed_time":29.37258479,"remaining_time":35.46755823},
{"learn":[1.879965334],"iteration":453,"passed_time":29.45352887,"remaining_time":35.42208538},
{"learn":[1.879561158],"iteration":454,"passed_time":29.51571179,"remaining_time":35.35398445},
{"learn":[1.879286597],"iteration":455,"passed_time":29.55746924,"remaining_time":35.26154225},
{"learn":[1.879169473],"iteration":456,"passed_time":29.65266963,"remaining_time":35.23282191},
{"learn":[1.879110495],"iteration":457,"passed_time":29.75250822,"remaining_time":35.20930013},
{"learn":[1.878720156],"iteration":458,"passed_time":29.85314368,"remaining_time":35.18638503},
{"learn":[1.878466191],"iteration":459,"passed_time":29.93628109,"remaining_time":35.14259084},
{"learn":[1.877772632],"iteration":460,"passed_time":30.0243255,"remaining_time":35.10436322},
{"learn":[1.87756778],"iteration":461,"passed_time":30.07990656,"remaining_time":35.02811629},
{"learn":[1.877435732],"iteration":462,"passed_time":30.17127957,"remaining_time":34.99347112},
{"learn":[1.876784727],"iteration":463,"passed_time":30.25053046,"remaining_time":34.94457829},
{"learn":[1.87647912],"iteration":464,"passed_time":30.33511132,"remaining_time":34.90168721},
{"learn":[1.876190387],"iteration":465,"passed_time":30.41043102,"remaining_time":34.84800465},
{"learn":[1.87593407],"iteration":466,"passed_time":30.49270264,"remaining_time":34.80216383},
{"learn":[1.87505748],"iteration":467,"passed_time":30.52505794,"remaining_time":34.69942484},
{"learn":[1.874378298],"iteration":468,"passed_time":30.59334732,"remaining_time":34.63767042},
{"learn":[1.874079712],"iteration":469,"passed_time":30.65278715,"remaining_time":34.56590891},
{"learn":[1.873761984],"iteration":470,"passed_time":30.68558223,"remaining_time":34.46427388},
{"learn":[1.873409088],"iteration":471,"passed_time":30.75162037,"remaining_time":34.4001177},
{"learn":[1.872799156],"iteration":472,"passed_time":30.8492117,"remaining_time":34.37110902},
{"learn":[1.870791235],"iteration":473,"passed_time":30.9133763,"remaining_time":34.30471716},
{"learn":[1.870566874],"iteration":474,"passed_time":30.99266013,"remaining_time":34.25504541},
{"learn":[1.870424106],"iteration":475,"passed_time":31.05989077,"remaining_time":34.19198059},
{"learn":[1.87031961],"iteration":476,"passed_time":31.13340189,"remaining_time":34.13578446},
{"learn":[1.869882606],"iteration":477,"passed_time":31.23013501,"remaining_time":34.10487547},
{"learn":[1.869482974],"iteration":478,"passed_time":31.29192312,"remaining_time":34.03568256},
{"learn":[1.869122969],"iteration":479,"passed_time":31.37265717,"remaining_time":33.98704526},
{"learn":[1.868732573],"iteration":480,"passed_time":31.45230476,"remaining_time":33.93710222},
{"learn":[1.867811089],"iteration":481,"passed_time":31.4958214,"remaining_time":33.8482064},
{"learn":[1.866732877],"iteration":482,"passed_time":31.58653167,"remaining_time":33.81001423},
{"learn":[1.866499938],"iteration":483,"passed_time":31.66597391,"remaining_time":33.75959202},
{"learn":[1.866082756],"iteration":484,"passed_time":31.73034115,"remaining_time":33.69304266},
{"learn":[1.864640201],"iteration":485,"passed_time":31.77063646,"remaining_time":33.60104349},
{"learn":[1.863508038],"iteration":486,"passed_time":31.86532396,"remaining_time":33.56655275},
{"learn":[1.863405955],"iteration":487,"passed_time":31.94520331,"remaining_time":33.51627889},
{"learn":[1.861989311],"iteration":488,"passed_time":32.00849023,"remaining_time":33.448545},
{"learn":[1.861776291],"iteration":489,"passed_time":32.07789655,"remaining_time":33.38719845},
{"learn":[1.861688566],"iteration":490,"passed_time":32.13033834,"remaining_time":33.30823262},
{"learn":[1.861128445],"iteration":491,"passed_time":32.22396798,"remaining_time":33.2719019},
{"learn":[1.860832379],"iteration":492,"passed_time":32.28676285,"remaining_time":33.20362833},
{"learn":[1.860744396],"iteration":493,"passed_time":32.32913259,"remaining_time":33.11445565},
{"learn":[1.860333674],"iteration":494,"passed_time":32.40381753,"remaining_time":33.0584401},
{"learn":[1.860174937],"iteration":495,"passed_time":32.465486,"remaining_time":32.98912287},
{"learn":[1.859615223],"iteration":496,"passed_time":32.50747636,"remaining_time":32.89992075},
{"learn":[1.859372411],"iteration":497,"passed_time":32.60381218,"remaining_time":32.86569019},
{"learn":[1.859224754],"iteration":498,"passed_time":32.68399162,"remaining_time":32.81498959},
{"learn":[1.85886026],"iteration":499,"passed_time":32.76770892,"remaining_time":32.76770892},
{"learn":[1.857793115],"iteration":500,"passed_time":32.84269288,"remaining_time":32.71158432},
{"learn":[1.857700115],"iteration":501,"passed_time":32.89056197,"remaining_time":32.62848578},
{"learn":[1.857402045],"iteration":502,"passed_time":32.96515618,"remaining_time":32.57193364},
{"learn":[1.856009217],"iteration":503,"passed_time":33.02615561,"remaining_time":32.50193092},
{"learn":[1.855696793],"iteration":504,"passed_time":33.08976916,"remaining_time":32.4345262},
{"learn":[1.855420683],"iteration":505,"passed_time":33.13391977,"remaining_time":32.34813511},
{"learn":[1.85509416],"iteration":506,"passed_time":33.24082488,"remaining_time":32.32293228},
{"learn":[1.855032539],"iteration":507,"passed_time":33.30736332,"remaining_time":32.25831251},
{"learn":[1.854427483],"iteration":508,"passed_time":33.40015486,"remaining_time":32.21900989},
{"learn":[1.854326337],"iteration":509,"passed_time":33.46481249,"remaining_time":32.1524669},
{"learn":[1.854164078],"iteration":510,"passed_time":33.54176025,"remaining_time":32.0976923},
{"learn":[1.853553147],"iteration":511,"passed_time":33.63982249,"remaining_time":32.06295581},
{"learn":[1.853347071],"iteration":512,"passed_time":33.71862236,"remaining_time":32.00968633},
{"learn":[1.852757071],"iteration":513,"passed_time":33.78207651,"remaining_time":31.94180775},
{"learn":[1.852370312],"iteration":514,"passed_time":33.82420328,"remaining_time":31.85386134},
{"learn":[1.851983634],"iteration":515,"passed_time":33.90195408,"remaining_time":31.79950732},
{"learn":[1.851892825],"iteration":516,"passed_time":33.94570557,"remaining_time":31.7132994},
{"learn":[1.851064035],"iteration":517,"passed_time":34.03837215,"remaining_time":31.672771},
{"learn":[1.850917715],"iteration":518,"passed_time":34.10104359,"remaining_time":31.60424271},
{"learn":[1.849902732],"iteration":519,"passed_time":34.19724209,"remaining_time":31.56668501},
{"learn":[1.849859848],"iteration":520,"passed_time":34.27987879,"remaining_time":31.51643367},
{"learn":[1.849023537],"iteration":521,"passed_time":34.32346782,"remaining_time":31.43030195},
{"learn":[1.84851681],"iteration":522,"passed_time":34.39974706,"remaining_time":31.37414789},
{"learn":[1.847301887],"iteration":523,"passed_time":34.45864917,"remaining_time":31.30213169},
{"learn":[1.846739163],"iteration":524,"passed_time":34.53667998,"remaining_time":31.24747236},
{"learn":[1.846692991],"iteration":525,"passed_time":34.60255366,"remaining_time":31.18176889},
{"learn":[1.846506489],"iteration":526,"passed_time":34.69911018,"remaining_time":31.14360363},
{"learn":[1.846195332],"iteration":527,"passed_time":34.77627028,"remaining_time":31.08787798},
{"learn":[1.845985036],"iteration":528,"passed_time":34.85545506,"remaining_time":31.03387397},
{"learn":[1.845819227],"iteration":529,"passed_time":34.92123637,"remaining_time":30.96788886},
{"learn":[1.845578931],"iteration":530,"passed_time":34.99804388,"remaining_time":30.91164328},
{"learn":[1.845443597],"iteration":531,"passed_time":35.04012659,"remaining_time":30.82477301},
{"learn":[1.845307964],"iteration":532,"passed_time":35.15604316,"remaining_time":30.80276201},
{"learn":[1.845246144],"iteration":533,"passed_time":35.21773982,"remaining_time":30.73308381},
{"learn":[1.845115462],"iteration":534,"passed_time":35.26029909,"remaining_time":30.64680201},
{"learn":[1.844984451],"iteration":535,"passed_time":35.35318484,"remaining_time":30.60424956},
{"learn":[1.844358263],"iteration":536,"passed_time":35.41762664,"remaining_time":30.53698536},
{"learn":[1.844210791],"iteration":537,"passed_time":35.47726068,"remaining_time":30.46560304},
{"learn":[1.844106504],"iteration":538,"passed_time":35.51545775,"remaining_time":30.37592954},
{"learn":[1.843691046],"iteration":539,"passed_time":35.57482731,"remaining_time":30.30448252},
{"learn":[1.843489818],"iteration":540,"passed_time":35.63376,"remaining_time":30.2327095},
{"learn":[1.843282065],"iteration":541,"passed_time":35.71078304,"remaining_time":30.17627054},
{"learn":[1.843042265],"iteration":542,"passed_time":35.81149371,"remaining_time":30.13969176},
{"learn":[1.842448713],"iteration":543,"passed_time":35.89119096,"remaining_time":30.08526301},
{"learn":[1.842298201],"iteration":544,"passed_time":35.95715789,"remaining_time":30.01927861},
{"learn":[1.84185787],"iteration":545,"passed_time":36.01364004,"remaining_time":29.94540765},
{"learn":[1.840846666],"iteration":546,"passed_time":36.05729988,"remaining_time":29.86098144},
{"learn":[1.840695261],"iteration":547,"passed_time":36.13240243,"remaining_time":29.8026385},
{"learn":[1.840247476],"iteration":548,"passed_time":36.22255364,"remaining_time":29.75659689},
{"learn":[1.840027585],"iteration":549,"passed_time":36.29596304,"remaining_time":29.69669704},
{"learn":[1.839518828],"iteration":550,"passed_time":36.37419624,"remaining_time":29.64067897},
{"learn":[1.839272656],"iteration":551,"passed_time":36.46923931,"remaining_time":29.59822321},
{"learn":[1.839187028],"iteration":552,"passed_time":36.55332959,"remaining_time":29.54672392},
{"learn":[1.839084565],"iteration":553,"passed_time":36.59385754,"remaining_time":29.46003693},
{"learn":[1.83887121],"iteration":554,"passed_time":36.67202629,"remaining_time":29.40369676},
{"learn":[1.83846993],"iteration":555,"passed_time":36.75374779,"remaining_time":29.35011514},
{"learn":[1.838387136],"iteration":556,"passed_time":36.8476434,"remaining_time":29.30611495},
{"learn":[1.838305594],"iteration":557,"passed_time":36.91153243,"remaining_time":29.23816726},
{"learn":[1.837451875],"iteration":558,"passed_time":36.98677273,"remaining_time":29.17918922},
{"learn":[1.837090814],"iteration":559,"passed_time":37.05051005,"remaining_time":29.11111504},
{"learn":[1.836428634],"iteration":560,"passed_time":37.1472208,"remaining_time":29.06885906},
{"learn":[1.835817475],"iteration":561,"passed_time":37.2461662,"remaining_time":29.02815088},
{"learn":[1.835649657],"iteration":562,"passed_time":37.31022311,"remaining_time":28.96015541},
{"learn":[1.835137908],"iteration":563,"passed_time":37.35208552,"remaining_time":28.87501647},
{"learn":[1.83433882],"iteration":564,"passed_time":37.43069558,"remaining_time":28.81832314},
{"learn":[1.83380745],"iteration":565,"passed_time":37.50788955,"remaining_time":28.76046655},
{"learn":[1.833742455],"iteration":566,"passed_time":37.56527224,"remaining_time":28.68741249},
{"learn":[1.83366785],"iteration":567,"passed_time":37.60598638,"remaining_time":28.60173612},
{"learn":[1.833209426],"iteration":568,"passed_time":37.66865269,"remaining_time":28.53284589},
{"learn":[1.832957567],"iteration":569,"passed_time":37.70966569,"remaining_time":28.44764254},
{"learn":[1.832477441],"iteration":570,"passed_time":37.78975894,"remaining_time":28.39195549},
{"learn":[1.832140671],"iteration":571,"passed_time":37.85007615,"remaining_time":28.32138565},
{"learn":[1.832076407],"iteration":572,"passed_time":37.88992281,"remaining_time":28.23559693},
{"learn":[1.832021405],"iteration":573,"passed_time":37.96663352,"remaining_time":28.17732732},
{"learn":[1.831740934],"iteration":574,"passed_time":37.99743419,"remaining_time":28.08506005},
{"learn":[1.831351505],"iteration":575,"passed_time":38.08241302,"remaining_time":28.03288736},
{"learn":[1.830639073],"iteration":576,"passed_time":38.14776927,"remaining_time":27.9662156},
{"learn":[1.830165331],"iteration":577,"passed_time":38.22687725,"remaining_time":27.90958858},
{"learn":[1.827539394],"iteration":578,"passed_time":38.27336432,"remaining_time":27.82916473},
{"learn":[1.827500858],"iteration":579,"passed_time":38.34473133,"remaining_time":27.76687441},
{"learn":[1.827250424],"iteration":580,"passed_time":38.38895208,"remaining_time":27.68497577},
{"learn":[1.827180859],"iteration":581,"passed_time":38.46635036,"remaining_time":27.62703514},
{"learn":[1.826451632],"iteration":582,"passed_time":38.50641131,"remaining_time":27.54232164},
{"learn":[1.826289951],"iteration":583,"passed_time":38.58343899,"remaining_time":27.48409353},
{"learn":[1.826159927],"iteration":584,"passed_time":38.62562109,"remaining_time":27.40108162},
{"learn":[1.82600062],"iteration":585,"passed_time":38.70022649,"remaining_time":27.34111564},
{"learn":[1.825874805],"iteration":586,"passed_time":38.76247838,"remaining_time":27.27240813},
{"learn":[1.825660966],"iteration":587,"passed_time":38.82073188,"remaining_time":27.20092098},
{"learn":[1.825507515],"iteration":588,"passed_time":38.88674346,"remaining_time":27.1348923},
{"learn":[1.825369266],"iteration":589,"passed_time":38.92713427,"remaining_time":27.05105941},
{"learn":[1.825217714],"iteration":590,"passed_time":39.0195086,"remaining_time":27.00334859},
{"learn":[1.823906237],"iteration":591,"passed_time":39.08444835,"remaining_time":26.93657927},
{"learn":[1.823237967],"iteration":592,"passed_time":39.17896988,"remaining_time":26.89011929},
{"learn":[1.822947737],"iteration":593,"passed_time":39.24283358,"remaining_time":26.82254282},
{"learn":[1.822468249],"iteration":594,"passed_time":39.31977365,"remaining_time":26.76387954},
{"learn":[1.821540737],"iteration":595,"passed_time":39.39703944,"remaining_time":26.70537573},
{"learn":[1.821380143],"iteration":596,"passed_time":39.46251709,"remaining_time":26.63885157},
{"learn":[1.820982787],"iteration":597,"passed_time":39.54311655,"remaining_time":26.58249641},
{"learn":[1.820872881],"iteration":598,"passed_time":39.62113133,"remaining_time":26.52432999},
{"learn":[1.820441707],"iteration":599,"passed_time":39.66108127,"remaining_time":26.44072085},
{"learn":[1.81936583],"iteration":600,"passed_time":39.75625191,"remaining_time":26.39391766},
{"learn":[1.818915525],"iteration":601,"passed_time":39.83593462,"remaining_time":26.33671425},
{"learn":[1.818732323],"iteration":602,"passed_time":39.93631284,"remaining_time":26.29306169},
{"learn":[1.818498349],"iteration":603,"passed_time":40.00282772,"remaining_time":26.2270195},
{"learn":[1.818224703],"iteration":604,"passed_time":40.03963156,"remaining_time":26.14157763},
{"learn":[1.818121711],"iteration":605,"passed_time":40.11899151,"remaining_time":26.08396477},
{"learn":[1.817921509],"iteration":606,"passed_time":40.15980726,"remaining_time":26.00132496},
{"learn":[1.817581629],"iteration":607,"passed_time":40.21870923,"remaining_time":25.93048358},
{"learn":[1.817319231],"iteration":608,"passed_time":40.29462397,"remaining_time":25.87060423},
{"learn":[1.816692715],"iteration":609,"passed_time":40.37570364,"remaining_time":25.81397446},
{"learn":[1.816545164],"iteration":610,"passed_time":40.49519843,"remaining_time":25.78172207},
{"learn":[1.815417701],"iteration":611,"passed_time":40.57316993,"remaining_time":25.72285937},
{"learn":[1.815175501],"iteration":612,"passed_time":40.63713501,"remaining_time":25.65509176},
{"learn":[1.814999505],"iteration":613,"passed_time":40.71336747,"remaining_time":25.59504861},
{"learn":[1.81493567],"iteration":614,"passed_time":40.77757673,"remaining_time":25.52742608},
{"learn":[1.81469414],"iteration":615,"passed_time":40.87237149,"remaining_time":25.47888093},
{"learn":[1.813828433],"iteration":616,"passed_time":40.95457764,"remaining_time":25.42237153},
{"learn":[1.81322652],"iteration":617,"passed_time":41.01500307,"remaining_time":25.35231581},
{"learn":[1.812965073],"iteration":618,"passed_time":41.04896924,"remaining_time":25.2660053},
{"learn":[1.812899667],"iteration":619,"passed_time":41.11486108,"remaining_time":25.19943099},
{"learn":[1.812250968],"iteration":620,"passed_time":41.15608103,"remaining_time":25.11780147},
{"learn":[1.812063599],"iteration":621,"passed_time":41.23328525,"remaining_time":25.05817014},
{"learn":[1.811682869],"iteration":622,"passed_time":41.28205197,"remaining_time":24.98127383},
{"learn":[1.811548738],"iteration":623,"passed_time":41.35461076,"remaining_time":24.91880392},
{"learn":[1.81153125],"iteration":624,"passed_time":41.39551639,"remaining_time":24.83730983},
{"learn":[1.811404716],"iteration":625,"passed_time":41.47139245,"remaining_time":24.7768383},
{"learn":[1.811249898],"iteration":626,"passed_time":41.51674727,"remaining_time":24.69816065},
{"learn":[1.811122318],"iteration":627,"passed_time":41.59335497,"remaining_time":24.63810199},
{"learn":[1.810302247],"iteration":628,"passed_time":41.63412066,"remaining_time":24.55685018},
{"learn":[1.809847251],"iteration":629,"passed_time":41.72838719,"remaining_time":24.50714803},
{"learn":[1.809794126],"iteration":630,"passed_time":41.81811639,"remaining_time":24.45465127},
{"learn":[1.809519201],"iteration":631,"passed_time":41.89167905,"remaining_time":24.39262324},
{"learn":[1.80928457],"iteration":632,"passed_time":41.95460119,"remaining_time":24.32438963},
{"learn":[1.809089652],"iteration":633,"passed_time":42.0473843,"remaining_time":24.27341113},
{"learn":[1.809082364],"iteration":634,"passed_time":42.11138004,"remaining_time":24.20575388},
{"learn":[1.808854849],"iteration":635,"passed_time":42.15221882,"remaining_time":24.1248548},
{"learn":[1.808600458],"iteration":636,"passed_time":42.22926315,"remaining_time":24.06471354},
{"learn":[1.808508306],"iteration":637,"passed_time":42.30667373,"remaining_time":24.0047271},
{"learn":[1.807436781],"iteration":638,"passed_time":42.39446363,"remaining_time":23.95054988},
{"learn":[1.807346418],"iteration":639,"passed_time":42.48833965,"remaining_time":23.89969105},
{"learn":[1.806007757],"iteration":640,"passed_time":42.54776196,"remaining_time":23.82940178},
{"learn":[1.805682421],"iteration":641,"passed_time":42.62529713,"remaining_time":23.76924668},
{"learn":[1.805573314],"iteration":642,"passed_time":42.69016381,"remaining_time":23.70200386},
{"learn":[1.805526269],"iteration":643,"passed_time":42.74805297,"remaining_time":23.63091127},
{"learn":[1.804817438],"iteration":644,"passed_time":42.82525885,"remaining_time":23.57049131},
{"learn":[1.804675885],"iteration":645,"passed_time":42.89066735,"remaining_time":23.50355455},
{"learn":[1.804491367],"iteration":646,"passed_time":42.97426838,"remaining_time":23.44654828},
{"learn":[1.804068126],"iteration":647,"passed_time":43.05378463,"remaining_time":23.38724103},
{"learn":[1.803544305],"iteration":648,"passed_time":43.1153571,"remaining_time":23.31816694},
{"learn":[1.802903236],"iteration":649,"passed_time":43.19263016,"remaining_time":23.25757008},
{"learn":[1.8027319],"iteration":650,"passed_time":43.25793193,"remaining_time":23.19050421},
{"learn":[1.802652223],"iteration":651,"passed_time":43.33843008,"remaining_time":23.13155471},
{"learn":[1.802414886],"iteration":652,"passed_time":43.37961806,"remaining_time":23.05165003},
{"learn":[1.802265536],"iteration":653,"passed_time":43.4615389,"remaining_time":22.99341355},
{"learn":[1.80210961],"iteration":654,"passed_time":43.5368657,"remaining_time":22.93163155},
{"learn":[1.801591081],"iteration":655,"passed_time":43.57520966,"remaining_time":22.85041482},
{"learn":[1.801490014],"iteration":656,"passed_time":43.65454705,"remaining_time":22.79073004},
{"learn":[1.801271475],"iteration":657,"passed_time":43.71322962,"remaining_time":22.72025004},
{"learn":[1.801216361],"iteration":658,"passed_time":43.75660225,"remaining_time":22.64188371},
{"learn":[1.800753706],"iteration":659,"passed_time":43.83500961,"remaining_time":22.58167162},
{"learn":[1.800701103],"iteration":660,"passed_time":43.89985645,"remaining_time":22.51444983},
{"learn":[1.800480655],"iteration":661,"passed_time":43.96142221,"remaining_time":22.44555998},
{"learn":[1.800233988],"iteration":662,"passed_time":44.03445132,"remaining_time":22.382519},
{"learn":[1.800010345],"iteration":663,"passed_time":44.12507009,"remaining_time":22.32834872},
{"learn":[1.7999586],"iteration":664,"passed_time":44.21994724,"remaining_time":22.27621402},
{"learn":[1.799543361],"iteration":665,"passed_time":44.29865692,"remaining_time":22.21584296},
{"learn":[1.799389134],"iteration":666,"passed_time":44.34180401,"remaining_time":22.13766227},
{"learn":[1.798826972],"iteration":667,"passed_time":44.40231947,"remaining_time":22.06821866},
{"learn":[1.798769018],"iteration":668,"passed_time":44.4877322,"remaining_time":22.01112012},
{"learn":[1.798023245],"iteration":669,"passed_time":44.52779822,"remaining_time":21.93160211},
{"learn":[1.797949627],"iteration":670,"passed_time":44.59027073,"remaining_time":21.86318789},
{"learn":[1.797898548],"iteration":671,"passed_time":44.66998937,"remaining_time":21.8032091},
{"learn":[1.797697298],"iteration":672,"passed_time":44.72978745,"remaining_time":21.73349256},
{"learn":[1.797630187],"iteration":673,"passed_time":44.80636007,"remaining_time":21.67191896},
{"learn":[1.797235427],"iteration":674,"passed_time":44.85422603,"remaining_time":21.5964792},
{"learn":[1.796818007],"iteration":675,"passed_time":44.89095326,"remaining_time":21.51578233},
{"learn":[1.796182468],"iteration":676,"passed_time":44.9852351,"remaining_time":21.46267495},
{"learn":[1.795445347],"iteration":677,"passed_time":45.05091547,"remaining_time":21.39586251},
{"learn":[1.795205535],"iteration":678,"passed_time":45.12858364,"remaining_time":21.33472069},
{"learn":[1.795136492],"iteration":679,"passed_time":45.2058485,"remaining_time":21.27334047},
{"learn":[1.793321738],"iteration":680,"passed_time":45.28505334,"remaining_time":21.21282234},
{"learn":[1.793164206],"iteration":681,"passed_time":45.34771803,"remaining_time":21.14453714},
{"learn":[1.792963699],"iteration":682,"passed_time":45.40763498,"remaining_time":21.0749931},
{"learn":[1.792777891],"iteration":683,"passed_time":45.48266256,"remaining_time":21.01245814},
{"learn":[1.792756857],"iteration":684,"passed_time":45.55746822,"remaining_time":20.94978466},
{"learn":[1.792499523],"iteration":685,"passed_time":45.62439552,"remaining_time":20.88346967},
{"learn":[1.792444206],"iteration":686,"passed_time":45.69387576,"remaining_time":20.81831603},
{"learn":[1.792410438],"iteration":687,"passed_time":45.76182719,"remaining_time":20.75245652},
{"learn":[1.792051996],"iteration":688,"passed_time":45.82195207,"remaining_time":20.68305819},
{"learn":[1.79199514],"iteration":689,"passed_time":45.89040664,"remaining_time":20.61742907},
{"learn":[1.791665287],"iteration":690,"passed_time":45.96490343,"remaining_time":20.55449372},
{"learn":[1.791499668],"iteration":691,"passed_time":46.02426236,"remaining_time":20.48478729},
{"learn":[1.791191328],"iteration":692,"passed_time":46.09561825,"remaining_time":20.4204254},
{"learn":[1.791028968],"iteration":693,"passed_time":46.1473954,"remaining_time":20.34741065},
{"learn":[1.790963247],"iteration":694,"passed_time":46.18831988,"remaining_time":20.26969434},
{"learn":[1.790923905],"iteration":695,"passed_time":46.27936438,"remaining_time":20.21397525},
{"learn":[1.788072319],"iteration":696,"passed_time":46.35964866,"remaining_time":20.15347711},
{"learn":[1.788037945],"iteration":697,"passed_time":46.42412769,"remaining_time":20.0860839},
{"learn":[1.787967495],"iteration":698,"passed_time":46.46918495,"remaining_time":20.01033572},
{"learn":[1.787739485],"iteration":699,"passed_time":46.54856215,"remaining_time":19.94938378},
{"learn":[1.786997581],"iteration":700,"passed_time":46.62096846,"remaining_time":19.88540595},
{"learn":[1.786262844],"iteration":701,"passed_time":46.66027298,"remaining_time":19.80735235},
{"learn":[1.785862084],"iteration":702,"passed_time":46.7218098,"remaining_time":19.73880158},
{"learn":[1.785698153],"iteration":703,"passed_time":46.81840758,"remaining_time":19.68501228},
{"learn":[1.785547524],"iteration":704,"passed_time":46.89063552,"remaining_time":19.62090423},
{"learn":[1.785351462],"iteration":705,"passed_time":46.93044911,"remaining_time":19.54327484},
{"learn":[1.785040247],"iteration":706,"passed_time":47.02571661,"remaining_time":19.48873404},
{"learn":[1.784383683],"iteration":707,"passed_time":47.11086055,"remaining_time":19.42990294},
{"learn":[1.784232811],"iteration":708,"passed_time":47.19324468,"remaining_time":19.36986488},
{"learn":[1.783947891],"iteration":709,"passed_time":47.276401,"remaining_time":19.31007928},
{"learn":[1.783751896],"iteration":710,"passed_time":47.36530774,"remaining_time":19.25256531},
{"learn":[1.783683511],"iteration":711,"passed_time":47.43435579,"remaining_time":19.18693043},
{"learn":[1.781099475],"iteration":712,"passed_time":47.49527134,"remaining_time":19.11801245},
{"learn":[1.781075768],"iteration":713,"passed_time":47.57287739,"remaining_time":19.05580243},
{"learn":[1.780658776],"iteration":714,"passed_time":47.68478431,"remaining_time":19.00722172},
{"learn":[1.780608807],"iteration":715,"passed_time":47.76354947,"remaining_time":18.94531851},
{"learn":[1.780116839],"iteration":716,"passed_time":47.842387,"remaining_time":18.88339682},
{"learn":[1.779788984],"iteration":717,"passed_time":47.90800755,"remaining_time":18.81623695},
{"learn":[1.779350992],"iteration":718,"passed_time":47.94776591,"remaining_time":18.73897388},
{"learn":[1.777111005],"iteration":719,"passed_time":48.00733613,"remaining_time":18.6695196},
{"learn":[1.776898351],"iteration":720,"passed_time":48.10604013,"remaining_time":18.61523605},
{"learn":[1.776375862],"iteration":721,"passed_time":48.2031886,"remaining_time":18.56023052},
{"learn":[1.776358203],"iteration":722,"passed_time":48.2635281,"remaining_time":18.49100592},
{"learn":[1.775766691],"iteration":723,"passed_time":48.30698718,"remaining_time":18.41537081},
{"learn":[1.775406973],"iteration":724,"passed_time":48.38678863,"remaining_time":18.35360948},
{"learn":[1.77531181],"iteration":725,"passed_time":48.46058303,"remaining_time":18.28953134},
{"learn":[1.77490951],"iteration":726,"passed_time":48.52513725,"remaining_time":18.22195663},
{"learn":[1.77485665],"iteration":727,"passed_time":48.61029121,"remaining_time":18.16208683},
{"learn":[1.77479718],"iteration":728,"passed_time":48.66618748,"remaining_time":18.09127134},
{"learn":[1.774784099],"iteration":729,"passed_time":48.7595346,"remaining_time":18.03434841},
{"learn":[1.77338414],"iteration":730,"passed_time":48.85828523,"remaining_time":17.97931426},
{"learn":[1.773027498],"iteration":731,"passed_time":48.92265387,"remaining_time":17.91157273},
{"learn":[1.772810111],"iteration":732,"passed_time":48.98040956,"remaining_time":17.84143158},
{"learn":[1.772658383],"iteration":733,"passed_time":49.05770466,"remaining_time":17.77840523},
{"learn":[1.772501436],"iteration":734,"passed_time":49.13807626,"remaining_time":17.71644927},
{"learn":[1.772368565],"iteration":735,"passed_time":49.27386727,"remaining_time":17.67432196},
{"learn":[1.772168465],"iteration":736,"passed_time":49.38495166,"remaining_time":17.62312386},
{"learn":[1.771780155],"iteration":737,"passed_time":49.52318213,"remaining_time":17.5814007},
{"learn":[1.771688442],"iteration":738,"passed_time":49.68868302,"remaining_time":17.54904773},
{"learn":[1.77163967],"iteration":739,"passed_time":49.77115071,"remaining_time":17.48716106},
{"learn":[1.771515338],"iteration":740,"passed_time":49.84313656,"remaining_time":17.42155515},
{"learn":[1.771509574],"iteration":741,"passed_time":49.95768145,"remaining_time":17.37073021},
{"learn":[1.77118158],"iteration":742,"passed_time":50.01914717,"remaining_time":17.30137392},
{"learn":[1.770878184],"iteration":743,"passed_time":50.08354735,"remaining_time":17.23304855},
{"learn":[1.770727407],"iteration":744,"passed_time":50.18234571,"remaining_time":17.17650759},
{"learn":[1.770608052],"iteration":745,"passed_time":50.24547384,"remaining_time":17.10770825},
{"learn":[1.770486093],"iteration":746,"passed_time":50.32742976,"remaining_time":17.04530084},
{"learn":[1.770433956],"iteration":747,"passed_time":50.40221985,"remaining_time":16.98042701},
{"learn":[1.77013051],"iteration":748,"passed_time":50.47168456,"remaining_time":16.91374209},
{"learn":[1.769967286],"iteration":749,"passed_time":50.54035537,"remaining_time":16.84678512},
{"learn":[1.768719292],"iteration":750,"passed_time":50.6091298,"remaining_time":16.77985795},
{"learn":[1.767858891],"iteration":751,"passed_time":50.70941587,"remaining_time":16.723318},
{"learn":[1.767814186],"iteration":752,"passed_time":50.79244707,"remaining_time":16.66100189},
{"learn":[1.767675576],"iteration":753,"passed_time":50.85675061,"remaining_time":16.59252076},
{"learn":[1.76743684],"iteration":754,"passed_time":50.95642941,"remaining_time":16.53553007},
{"learn":[1.766733106],"iteration":755,"passed_time":51.06067528,"remaining_time":16.47990049},
{"learn":[1.766655103],"iteration":756,"passed_time":51.12055658,"remaining_time":16.40990125},
{"learn":[1.766580798],"iteration":757,"passed_time":51.18727663,"remaining_time":16.34211206},
{"learn":[1.765948624],"iteration":758,"passed_time":51.27447325,"remaining_time":16.28082747},
{"learn":[1.765466752],"iteration":759,"passed_time":51.34336804,"remaining_time":16.21369517},
{"learn":[1.76533713],"iteration":760,"passed_time":51.43151269,"remaining_time":16.15260385},
{"learn":[1.764878028],"iteration":761,"passed_time":51.49487075,"remaining_time":16.08369979},
{"learn":[1.764805813],"iteration":762,"passed_time":51.58852822,"remaining_time":16.02422174},
{"learn":[1.764126313],"iteration":763,"passed_time":51.64701609,"remaining_time":15.95379031},
{"learn":[1.763802504],"iteration":764,"passed_time":51.72859747,"remaining_time":15.89048419},
{"learn":[1.763399068],"iteration":765,"passed_time":51.80733293,"remaining_time":15.82626097},
{"learn":[1.763380127],"iteration":766,"passed_time":51.87837213,"remaining_time":15.75966194},
{"learn":[1.763257266],"iteration":767,"passed_time":51.95813442,"remaining_time":15.69568644},
{"learn":[1.761828366],"iteration":768,"passed_time":52.03080325,"remaining_time":15.62953908},
{"learn":[1.761435472],"iteration":769,"passed_time":52.1087778,"remaining_time":15.5649596},
{"learn":[1.76108307],"iteration":770,"passed_time":52.18962967,"remaining_time":15.50119999},
{"learn":[1.760984505],"iteration":771,"passed_time":52.25963782,"remaining_time":15.43419355},
{"learn":[1.760953316],"iteration":772,"passed_time":52.33006966,"remaining_time":15.36730377},
{"learn":[1.760325613],"iteration":773,"passed_time":52.40478406,"remaining_time":15.30165529},
{"learn":[1.760084013],"iteration":774,"passed_time":52.52272598,"remaining_time":15.24853335},
{"learn":[1.759962795],"iteration":775,"passed_time":52.58071618,"remaining_time":15.17793869},
{"learn":[1.759401376],"iteration":776,"passed_time":52.6713356,"remaining_time":15.11674111},
{"learn":[1.759086315],"iteration":777,"passed_time":52.75092191,"remaining_time":15.05231962},
{"learn":[1.757321676],"iteration":778,"passed_time":52.83215347,"remaining_time":14.98832595},
{"learn":[1.756352253],"iteration":779,"passed_time":52.91500635,"remaining_time":14.92474538},
{"learn":[1.756145631],"iteration":780,"passed_time":53.00424707,"remaining_time":14.86290667},
{"learn":[1.756058126],"iteration":781,"passed_time":53.10933297,"remaining_time":14.80541507},
{"learn":[1.755938094],"iteration":782,"passed_time":53.16601338,"remaining_time":14.73438685},
{"learn":[1.75513869],"iteration":783,"passed_time":53.25156763,"remaining_time":14.67135027},
{"learn":[1.754774038],"iteration":784,"passed_time":53.38267274,"remaining_time":14.62073202},
{"learn":[1.754746651],"iteration":785,"passed_time":53.49076796,"remaining_time":14.5636442},
{"learn":[1.754514387],"iteration":786,"passed_time":53.56931494,"remaining_time":14.49842958},
{"learn":[1.754499753],"iteration":787,"passed_time":53.62692837,"remaining_time":14.42754926},
{"learn":[1.754396187],"iteration":788,"passed_time":53.68708181,"remaining_time":14.35738183},
{"learn":[1.753941624],"iteration":789,"passed_time":53.72697969,"remaining_time":14.28185536},
{"learn":[1.753582809],"iteration":790,"passed_time":53.81553606,"remaining_time":14.21927565},
{"learn":[1.753062601],"iteration":791,"passed_time":53.8787329,"remaining_time":14.14997026},
{"learn":[1.752912587],"iteration":792,"passed_time":53.93288116,"remaining_time":14.07831828},
{"learn":[1.752735254],"iteration":793,"passed_time":53.99808706,"remaining_time":14.00957926},
{"learn":[1.752677763],"iteration":794,"passed_time":54.04376316,"remaining_time":13.93581314},
{"learn":[1.752414011],"iteration":795,"passed_time":54.12497537,"remaining_time":13.87122484},
{"learn":[1.75232946],"iteration":796,"passed_time":54.19561563,"remaining_time":13.8039021},
{"learn":[1.751498153],"iteration":797,"passed_time":54.28591433,"remaining_time":13.74154724},
{"learn":[1.751427091],"iteration":798,"passed_time":54.36512134,"remaining_time":13.67633215},
{"learn":[1.751227448],"iteration":799,"passed_time":54.43311792,"remaining_time":13.60827948},
{"learn":[1.750730825],"iteration":800,"passed_time":54.4761754,"remaining_time":13.53403109},
{"learn":[1.750533054],"iteration":801,"passed_time":54.59157339,"remaining_time":13.47772011},
{"learn":[1.750524076],"iteration":802,"passed_time":54.66617326,"remaining_time":13.41125297},
{"learn":[1.750162447],"iteration":803,"passed_time":54.70774584,"remaining_time":13.33671416},
{"learn":[1.749600385],"iteration":804,"passed_time":54.7670928,"remaining_time":13.26656285},
{"learn":[1.747777296],"iteration":805,"passed_time":54.80700559,"remaining_time":13.19176065},
{"learn":[1.747654793],"iteration":806,"passed_time":54.89074169,"remaining_time":13.12752558},
{"learn":[1.746423203],"iteration":807,"passed_time":54.94659058,"remaining_time":13.05661558},
{"learn":[1.746382587],"iteration":808,"passed_time":55.04467597,"remaining_time":12.9957146},
{"learn":[1.746229021],"iteration":809,"passed_time":55.10183768,"remaining_time":12.92512242},
{"learn":[1.745913594],"iteration":810,"passed_time":55.18987606,"remaining_time":12.86175903},
{"learn":[1.745844516],"iteration":811,"passed_time":55.26857376,"remaining_time":12.79617225},
{"learn":[1.745817167],"iteration":812,"passed_time":55.33710368,"remaining_time":12.7282145},
{"learn":[1.745424049],"iteration":813,"passed_time":55.38252429,"remaining_time":12.65497484},
{"learn":[1.745279566],"iteration":814,"passed_time":55.47389939,"remaining_time":12.59223483},
{"learn":[1.745134357],"iteration":815,"passed_time":55.56836691,"remaining_time":12.53012195},
{"learn":[1.74494476],"iteration":816,"passed_time":55.64877843,"remaining_time":12.46478146},
{"learn":[1.744927075],"iteration":817,"passed_time":55.71996872,"remaining_time":12.39735245},
{"learn":[1.744838142],"iteration":818,"passed_time":55.79095897,"remaining_time":12.32987005},
{"learn":[1.744611385],"iteration":819,"passed_time":55.85113675,"remaining_time":12.26000563},
{"learn":[1.744136958],"iteration":820,"passed_time":55.91166949,"remaining_time":12.19024219},
{"learn":[1.744075667],"iteration":821,"passed_time":55.99305878,"remaining_time":12.12501759},
{"learn":[1.743746204],"iteration":822,"passed_time":56.0547014,"remaining_time":12.05550686},
{"learn":[1.743602517],"iteration":823,"passed_time":56.13415937,"remaining_time":11.98982045},
{"learn":[1.742962271],"iteration":824,"passed_time":56.18447934,"remaining_time":11.91791986},
{"learn":[1.742672745],"iteration":825,"passed_time":56.24776565,"remaining_time":11.84880293},
{"learn":[1.742583623],"iteration":826,"passed_time":56.30736888,"remaining_time":11.77892965},
{"learn":[1.742471375],"iteration":827,"passed_time":56.38305251,"remaining_time":11.71242153},
{"learn":[1.741873906],"iteration":828,"passed_time":56.4498629,"remaining_time":11.64406098},
{"learn":[1.741670838],"iteration":829,"passed_time":56.52707236,"remaining_time":11.5778341},
{"learn":[1.741242564],"iteration":830,"passed_time":56.58818799,"remaining_time":11.50830779},
{"learn":[1.740820924],"iteration":831,"passed_time":56.63118346,"remaining_time":11.43514281},
{"learn":[1.740637202],"iteration":832,"passed_time":56.72696551,"remaining_time":11.37263294},
{"learn":[1.740477967],"iteration":833,"passed_time":56.80085659,"remaining_time":11.30568608},
{"learn":[1.739843584],"iteration":834,"passed_time":56.8711748,"remaining_time":11.23801658},
{"learn":[1.73907666],"iteration":835,"passed_time":56.98082674,"remaining_time":11.17805692},
{"learn":[1.738686722],"iteration":836,"passed_time":57.04808051,"remaining_time":11.10972177},
{"learn":[1.738673636],"iteration":837,"passed_time":57.14385242,"remaining_time":11.04690226},
{"learn":[1.73864043],"iteration":838,"passed_time":57.18595506,"remaining_time":10.97370532},
{"learn":[1.738579345],"iteration":839,"passed_time":57.28327873,"remaining_time":10.91110071},
{"learn":[1.738269556],"iteration":840,"passed_time":57.35958907,"remaining_time":10.84444074},
{"learn":[1.738173641],"iteration":841,"passed_time":57.43896086,"remaining_time":10.77833232},
{"learn":[1.738166109],"iteration":842,"passed_time":57.52172829,"remaining_time":10.71282484},
{"learn":[1.7371505],"iteration":843,"passed_time":57.56090765,"remaining_time":10.6392199},
{"learn":[1.737073127],"iteration":844,"passed_time":57.63788081,"remaining_time":10.57262902},
{"learn":[1.736959914],"iteration":845,"passed_time":57.7657773,"remaining_time":10.51528334},
{"learn":[1.736750584],"iteration":846,"passed_time":57.8586381,"remaining_time":10.4514423},
{"learn":[1.736411441],"iteration":847,"passed_time":57.925732,"remaining_time":10.38291423},
{"learn":[1.736384601],"iteration":848,"passed_time":57.97158276,"remaining_time":10.3106113},
{"learn":[1.735523404],"iteration":849,"passed_time":58.05715897,"remaining_time":10.24538099},
{"learn":[1.735448583],"iteration":850,"passed_time":58.12948944,"remaining_time":10.1777837},
{"learn":[1.735243651],"iteration":851,"passed_time":58.20842423,"remaining_time":10.11132252},
{"learn":[1.735219121],"iteration":852,"passed_time":58.28698928,"remaining_time":10.04476837},
{"learn":[1.734798787],"iteration":853,"passed_time":58.37113608,"remaining_time":9.97914036},
{"learn":[1.734735352],"iteration":854,"passed_time":58.43513088,"remaining_time":9.910051435},
{"learn":[1.7345299],"iteration":855,"passed_time":58.53535877,"remaining_time":9.8470697},
{"learn":[1.734082728],"iteration":856,"passed_time":58.61334751,"remaining_time":9.780290191},
{"learn":[1.733945379],"iteration":857,"passed_time":58.69309505,"remaining_time":9.713775638},
{"learn":[1.733886878],"iteration":858,"passed_time":58.79278925,"remaining_time":9.650504405},
{"learn":[1.733758945],"iteration":859,"passed_time":58.87239204,"remaining_time":9.583877773},
{"learn":[1.732738669],"iteration":860,"passed_time":58.93744977,"remaining_time":9.514872844},
{"learn":[1.732700701],"iteration":861,"passed_time":59.02111032,"remaining_time":9.448855248},
{"learn":[1.732530421],"iteration":862,"passed_time":59.11107843,"remaining_time":9.383798082},
{"learn":[1.732312521],"iteration":863,"passed_time":59.1926851,"remaining_time":9.317367099},
{"learn":[1.732134438],"iteration":864,"passed_time":59.25971562,"remaining_time":9.248626138},
{"learn":[1.731992433],"iteration":865,"passed_time":59.32365533,"remaining_time":9.179410871},
{"learn":[1.731768911],"iteration":866,"passed_time":59.40835908,"remaining_time":9.11339303},
{"learn":[1.731365075],"iteration":867,"passed_time":59.47778682,"remaining_time":9.045009056},
{"learn":[1.7311398],"iteration":868,"passed_time":59.54527564,"remaining_time":8.976330391},
{"learn":[1.731022083],"iteration":869,"passed_time":59.66628924,"remaining_time":8.915652415},
{"learn":[1.730648966],"iteration":870,"passed_time":59.76255165,"remaining_time":8.851170106},
{"learn":[1.730503551],"iteration":871,"passed_time":59.85942929,"remaining_time":8.786705216},
{"learn":[1.73018733],"iteration":872,"passed_time":59.90709613,"remaining_time":8.715007111},
{"learn":[1.729895499],"iteration":873,"passed_time":60.00461199,"remaining_time":8.65055047},
{"learn":[1.728960765],"iteration":874,"passed_time":60.08468916,"remaining_time":8.583527023},
{"learn":[1.72880081],"iteration":875,"passed_time":60.17341738,"remaining_time":8.51769835},
{"learn":[1.728766287],"iteration":876,"passed_time":60.24536542,"remaining_time":8.449464021},
{"learn":[1.728412124],"iteration":877,"passed_time":60.33891695,"remaining_time":8.384223084},
{"learn":[1.728361858],"iteration":878,"passed_time":60.44482396,"remaining_time":8.320618543},
{"learn":[1.728335113],"iteration":879,"passed_time":60.51396817,"remaining_time":8.251904751},
{"learn":[1.728046227],"iteration":880,"passed_time":60.57927329,"remaining_time":8.18267142},
{"learn":[1.727990898],"iteration":881,"passed_time":60.64702455,"remaining_time":8.11377426},
{"learn":[1.727250304],"iteration":882,"passed_time":60.71283395,"remaining_time":8.044622391},
{"learn":[1.727144438],"iteration":883,"passed_time":60.79857611,"remaining_time":7.978093698},
{"learn":[1.727020767],"iteration":884,"passed_time":60.91182343,"remaining_time":7.9150957},
{"learn":[1.726856506],"iteration":885,"passed_time":60.98129281,"remaining_time":7.846351446},
{"learn":[1.726703098],"iteration":886,"passed_time":61.05715673,"remaining_time":7.778420192},
{"learn":[1.726419681],"iteration":887,"passed_time":61.13356601,"remaining_time":7.710539857},
{"learn":[1.725902559],"iteration":888,"passed_time":61.21133311,"remaining_time":7.642809871},
{"learn":[1.725731608],"iteration":889,"passed_time":61.28620437,"remaining_time":7.574699417},
{"learn":[1.725665555],"iteration":890,"passed_time":61.35437097,"remaining_time":7.505753576},
{"learn":[1.725605248],"iteration":891,"passed_time":61.42842766,"remaining_time":7.437522631},
{"learn":[1.72547599],"iteration":892,"passed_time":61.51094704,"remaining_time":7.370292647},
{"learn":[1.725463278],"iteration":893,"passed_time":61.57875717,"remaining_time":7.301284408},
{"learn":[1.724983444],"iteration":894,"passed_time":61.6718752,"remaining_time":7.235247928},
{"learn":[1.724877143],"iteration":895,"passed_time":61.75097324,"remaining_time":7.16752368},
{"learn":[1.724749929],"iteration":896,"passed_time":61.82670432,"remaining_time":7.099387453},
{"learn":[1.724689101],"iteration":897,"passed_time":61.88992477,"remaining_time":7.029813281},
{"learn":[1.724582872],"iteration":898,"passed_time":62.0027108,"remaining_time":6.965821792},
{"learn":[1.724546587],"iteration":899,"passed_time":62.06963941,"remaining_time":6.896626602},
{"learn":[1.72437991],"iteration":900,"passed_time":62.15193803,"remaining_time":6.829125266},
{"learn":[1.724090523],"iteration":901,"passed_time":62.23882569,"remaining_time":6.762089709},
{"learn":[1.723977251],"iteration":902,"passed_time":62.31296785,"remaining_time":6.693641065},
{"learn":[1.723577362],"iteration":903,"passed_time":62.37106324,"remaining_time":6.623475743},
{"learn":[1.723309886],"iteration":904,"passed_time":62.53282663,"remaining_time":6.56421937},
{"learn":[1.723217039],"iteration":905,"passed_time":62.62920449,"remaining_time":6.497952784},
{"learn":[1.723095473],"iteration":906,"passed_time":62.74988898,"remaining_time":6.4341121},
{"learn":[1.722374348],"iteration":907,"passed_time":62.82025128,"remaining_time":6.365047486},
{"learn":[1.722277801],"iteration":908,"passed_time":62.90416782,"remaining_time":6.297336933},
{"learn":[1.722051283],"iteration":909,"passed_time":63.05395077,"remaining_time":6.236105021},
{"learn":[1.721915864],"iteration":910,"passed_time":63.1359444,"remaining_time":6.168056039},
{"learn":[1.721589149],"iteration":911,"passed_time":63.30032398,"remaining_time":6.107925998},
{"learn":[1.721512481],"iteration":912,"passed_time":63.42491361,"remaining_time":6.043775996},
{"learn":[1.721431693],"iteration":913,"passed_time":63.50777833,"remaining_time":5.975567764},
{"learn":[1.721385339],"iteration":914,"passed_time":63.63310174,"remaining_time":5.911271746},
{"learn":[1.721331012],"iteration":915,"passed_time":63.70921756,"remaining_time":5.842329995},
{"learn":[1.721279133],"iteration":916,"passed_time":63.79470543,"remaining_time":5.774220884},
{"learn":[1.721223742],"iteration":917,"passed_time":63.85618419,"remaining_time":5.703929307},
{"learn":[1.720883222],"iteration":918,"passed_time":63.93202603,"remaining_time":5.634922861},
{"learn":[1.720596579],"iteration":919,"passed_time":64.00134034,"remaining_time":5.565333943},
{"learn":[1.720438518],"iteration":920,"passed_time":64.15001644,"remaining_time":5.502552985},
{"learn":[1.720420028],"iteration":921,"passed_time":64.25175995,"remaining_time":5.435615267},
{"learn":[1.720181717],"iteration":922,"passed_time":64.32447497,"remaining_time":5.366180469},
{"learn":[1.720048071],"iteration":923,"passed_time":64.41799893,"remaining_time":5.298450128},
{"learn":[1.719260248],"iteration":924,"passed_time":64.50954688,"remaining_time":5.230503801},
{"learn":[1.719129675],"iteration":925,"passed_time":64.63257948,"remaining_time":5.16502255},
{"learn":[1.719118925],"iteration":926,"passed_time":64.72638318,"remaining_time":5.097115396},
{"learn":[1.719028722],"iteration":927,"passed_time":64.78747827,"remaining_time":5.026614693},
{"learn":[1.718169048],"iteration":928,"passed_time":64.87581163,"remaining_time":4.958215959},
{"learn":[1.718114263],"iteration":929,"passed_time":64.96352957,"remaining_time":4.889728032},
{"learn":[1.718069083],"iteration":930,"passed_time":65.03596808,"remaining_time":4.820066377},
{"learn":[1.717828696],"iteration":931,"passed_time":65.11792031,"remaining_time":4.751092898},
{"learn":[1.717793393],"iteration":932,"passed_time":65.17501567,"remaining_time":4.680306591},
{"learn":[1.717725614],"iteration":933,"passed_time":65.27143225,"remaining_time":4.612328189},
{"learn":[1.717673767],"iteration":934,"passed_time":65.39463393,"remaining_time":4.546151022},
{"learn":[1.717340183],"iteration":935,"passed_time":65.48582101,"remaining_time":4.477662975},
{"learn":[1.717182928],"iteration":936,"passed_time":65.57516055,"remaining_time":4.409002257},
{"learn":[1.71682735],"iteration":937,"passed_time":65.66336712,"remaining_time":4.34022256},
{"learn":[1.716725523],"iteration":938,"passed_time":65.78176286,"remaining_time":4.273362657},
{"learn":[1.71563149],"iteration":939,"passed_time":65.86498849,"remaining_time":4.204148201},
{"learn":[1.715581714],"iteration":940,"passed_time":65.94581586,"remaining_time":4.134753598},
{"learn":[1.715375995],"iteration":941,"passed_time":66.01736332,"remaining_time":4.064763347},
{"learn":[1.715361222],"iteration":942,"passed_time":66.10176163,"remaining_time":3.995546567},
{"learn":[1.715330118],"iteration":943,"passed_time":66.19770706,"remaining_time":3.926982622},
{"learn":[1.715296589],"iteration":944,"passed_time":66.30670766,"remaining_time":3.859120551},
{"learn":[1.715226293],"iteration":945,"passed_time":66.4243835,"remaining_time":3.791666712},
{"learn":[1.715090953],"iteration":946,"passed_time":66.48463723,"remaining_time":3.720893108},
{"learn":[1.715037468],"iteration":947,"passed_time":66.55433984,"remaining_time":3.650659991},
{"learn":[1.714898465],"iteration":948,"passed_time":66.63307369,"remaining_time":3.580913339},
{"learn":[1.714825538],"iteration":949,"passed_time":66.74875323,"remaining_time":3.513092276},
{"learn":[1.714649109],"iteration":950,"passed_time":66.85811364,"remaining_time":3.444844972},
{"learn":[1.714633875],"iteration":951,"passed_time":66.94137796,"remaining_time":3.375195528},
{"learn":[1.714502486],"iteration":952,"passed_time":67.02673653,"remaining_time":3.305620794},
{"learn":[1.714421304],"iteration":953,"passed_time":67.08616048,"remaining_time":3.234762455},
{"learn":[1.714001276],"iteration":954,"passed_time":67.14152917,"remaining_time":3.163736977},
{"learn":[1.713935424],"iteration":955,"passed_time":67.23058173,"remaining_time":3.094294556},
{"learn":[1.713788367],"iteration":956,"passed_time":67.30833199,"remaining_time":3.024303318},
{"learn":[1.7132779],"iteration":957,"passed_time":67.3762301,"remaining_time":2.95386395},
{"learn":[1.712748339],"iteration":958,"passed_time":67.44276533,"remaining_time":2.883371615},
{"learn":[1.712674549],"iteration":959,"passed_time":67.50446333,"remaining_time":2.812685972},
{"learn":[1.712426829],"iteration":960,"passed_time":67.57274317,"remaining_time":2.742286143},
{"learn":[1.711905748],"iteration":961,"passed_time":67.62680331,"remaining_time":2.671329029},
{"learn":[1.711826157],"iteration":962,"passed_time":67.72614716,"remaining_time":2.602146879},
{"learn":[1.71171992],"iteration":963,"passed_time":67.80742884,"remaining_time":2.532227633},
{"learn":[1.711582235],"iteration":964,"passed_time":67.88560276,"remaining_time":2.462172121},
{"learn":[1.710869866],"iteration":965,"passed_time":67.97755821,"remaining_time":2.392584865},
{"learn":[1.710768379],"iteration":966,"passed_time":68.06926389,"remaining_time":2.322942822},
{"learn":[1.71024927],"iteration":967,"passed_time":68.14049658,"remaining_time":2.252578399},
{"learn":[1.709252935],"iteration":968,"passed_time":68.20761298,"remaining_time":2.182080498},
{"learn":[1.70841839],"iteration":969,"passed_time":68.28812998,"remaining_time":2.11200402},
{"learn":[1.7079988],"iteration":970,"passed_time":68.39331536,"remaining_time":2.042642786},
{"learn":[1.707782893],"iteration":971,"passed_time":68.48738633,"remaining_time":1.972887672},
{"learn":[1.70771036],"iteration":972,"passed_time":68.5629231,"remaining_time":1.902568267},
{"learn":[1.70736635],"iteration":973,"passed_time":68.64597139,"remaining_time":1.832438661},
{"learn":[1.706766402],"iteration":974,"passed_time":68.70537622,"remaining_time":1.761676313},
{"learn":[1.70666678],"iteration":975,"passed_time":68.77661569,"remaining_time":1.691228255},
{"learn":[1.706653152],"iteration":976,"passed_time":68.85842079,"remaining_time":1.621027306},
{"learn":[1.706336531],"iteration":977,"passed_time":68.93484552,"remaining_time":1.550681597},
{"learn":[1.705851117],"iteration":978,"passed_time":69.02807432,"remaining_time":1.480683923},
{"learn":[1.705838178],"iteration":979,"passed_time":69.10390118,"remaining_time":1.410283698},
{"learn":[1.705731347],"iteration":980,"passed_time":69.21677947,"remaining_time":1.34059002},
{"learn":[1.705584554],"iteration":981,"passed_time":69.26996796,"remaining_time":1.26971428},
{"learn":[1.705381808],"iteration":982,"passed_time":69.35296366,"remaining_time":1.199390012},
{"learn":[1.705370749],"iteration":983,"passed_time":69.44384407,"remaining_time":1.129168196},
{"learn":[1.705307191],"iteration":984,"passed_time":69.53039111,"remaining_time":1.058838443},
{"learn":[1.705174776],"iteration":985,"passed_time":69.58611519,"remaining_time":0.9880381467},
{"learn":[1.705165251],"iteration":986,"passed_time":69.6808302,"remaining_time":0.9177819581},
{"learn":[1.70449587],"iteration":987,"passed_time":69.80142726,"remaining_time":0.8477906145},
{"learn":[1.704191244],"iteration":988,"passed_time":69.92007843,"remaining_time":0.7776752909},
{"learn":[1.704071436],"iteration":989,"passed_time":70.06207052,"remaining_time":0.707697682},
{"learn":[1.704056119],"iteration":990,"passed_time":70.17974473,"remaining_time":0.6373538876},
{"learn":[1.703994402],"iteration":991,"passed_time":70.27552009,"remaining_time":0.5667380653},
{"learn":[1.703983652],"iteration":992,"passed_time":70.38467478,"remaining_time":0.4961658846},
{"learn":[1.703860219],"iteration":993,"passed_time":70.50506371,"remaining_time":0.4255838856},
{"learn":[1.703843185],"iteration":994,"passed_time":70.56519389,"remaining_time":0.3545989643},
{"learn":[1.70362749],"iteration":995,"passed_time":70.64636828,"remaining_time":0.2837203545},
{"learn":[1.703583248],"iteration":996,"passed_time":70.74942534,"remaining_time":0.2128869368},
{"learn":[1.70357589],"iteration":997,"passed_time":70.81449805,"remaining_time":0.1419128217},
{"learn":[1.703364922],"iteration":998,"passed_time":70.87806453,"remaining_time":0.07094901354},
{"learn":[1.703334053],"iteration":999,"passed_time":70.96488191,"remaining_time":0}
]}