{
"meta":{"launch_mode":"Train","name":"experiment","iteration_count":1000,"learn_metrics":[{"best_value":"Min","name":"RMSE"}],"test_sets":[],"test_metrics":[],"learn_sets":["learn"]},
"iterations":[
{"learn":[15.78884228],"iteration":0,"passed_time":0.08372582016,"remaining_time":83.64209434},
{"learn":[15.33400343],"iteration":1,"passed_time":0.1221896975,"remaining_time":60.97265907},
{"learn":[14.89730121],"iteration":2,"passed_time":0.1897001326,"remaining_time":63.04367739},
{"learn":[14.46860683],"iteration":3,"passed_time":0.2050622886,"remaining_time":51.06050986},
{"learn":[14.05478748],"iteration":4,"passed_time":0.2409077199,"remaining_time":47.94063625},
{"learn":[13.65596472],"iteration":5,"passed_time":0.3412458434,"remaining_time":56.53306139},
{"learn":[13.27173834],"iteration":6,"passed_time":0.4254821636,"remaining_time":60.35768406},
{"learn":[12.89651979],"iteration":7,"passed_time":0.4489708854,"remaining_time":55.67238979},
{"learn":[12.53242505],"iteration":8,"passed_time":0.5417744994,"remaining_time":59.6553921},
{"learn":[12.18136402],"iteration":9,"passed_time":0.6076429945,"remaining_time":60.15665646},
{"learn":[11.83910465],"iteration":10,"passed_time":0.6669437604,"remaining_time":59.96430718},
{"learn":[11.51019587],"iteration":11,"passed_time":0.7217122539,"remaining_time":59.42097557},
{"learn":[11.1873057],"iteration":12,"passed_time":0.782889291,"remaining_time":59.43936386},
{"learn":[10.87769007],"iteration":13,"passed_time":0.8420908084,"remaining_time":59.30725265},
{"learn":[10.57580111],"iteration":14,"passed_time":0.8829881432,"remaining_time":57.98288807},
{"learn":[10.28499726],"iteration":15,"passed_time":0.9789188838,"remaining_time":60.20351135},
{"learn":[10.0010459],"iteration":16,"passed_time":1.038112901,"remaining_time":60.02735184},
{"learn":[9.727830529],"iteration":17,"passed_time":1.09532954,"remaining_time":59.75631155},
{"learn":[9.462876204],"iteration":18,"passed_time":1.117240734,"remaining_time":57.68490316},
{"learn":[9.203952582],"iteration":19,"passed_time":1.197156612,"remaining_time":58.660674},
{"learn":[8.956105633],"iteration":20,"passed_time":1.276903638,"remaining_time":59.52803152},
{"learn":[8.716604964],"iteration":21,"passed_time":1.339464911,"remaining_time":59.54530379},
{"learn":[8.478829143],"iteration":22,"passed_time":1.403973087,"remaining_time":59.63833506},
{"learn":[8.2518154],"iteration":23,"passed_time":1.439082603,"remaining_time":58.52269252},
{"learn":[8.036684023],"iteration":24,"passed_time":1.502704827,"remaining_time":58.60548824},
{"learn":[7.824436513],"iteration":25,"passed_time":1.595680416,"remaining_time":59.77664329},
{"learn":[7.617858538],"iteration":26,"passed_time":1.676509673,"remaining_time":60.41644116},
{"learn":[7.422126876],"iteration":27,"passed_time":1.731304866,"remaining_time":60.10101178},
{"learn":[7.225451561],"iteration":28,"passed_time":1.760619694,"remaining_time":58.95040425},
{"learn":[7.041430259],"iteration":29,"passed_time":1.813384676,"remaining_time":58.63277118},
{"learn":[6.861074669],"iteration":30,"passed_time":1.878189792,"remaining_time":58.70857769},
{"learn":[6.68959057],"iteration":31,"passed_time":1.917150672,"remaining_time":57.99380783},
{"learn":[6.518538413],"iteration":32,"passed_time":1.994050993,"remaining_time":58.43173666},
{"learn":[6.353247023],"iteration":33,"passed_time":2.060330677,"remaining_time":58.5376304},
{"learn":[6.196420576],"iteration":34,"passed_time":2.111951847,"remaining_time":58.2295295},
{"learn":[6.040997524],"iteration":35,"passed_time":2.197717098,"remaining_time":58.84998007},
{"learn":[5.89661621],"iteration":36,"passed_time":2.256605869,"remaining_time":58.73274194},
{"learn":[5.750987355],"iteration":37,"passed_time":2.332556809,"remaining_time":59.05051712},
{"learn":[5.61484432],"iteration":38,"passed_time":2.398340521,"remaining_time":59.09757028},
{"learn":[5.479526078],"iteration":39,"passed_time":2.473069027,"remaining_time":59.35365664},
{"learn":[5.350113465],"iteration":40,"passed_time":2.550841607,"remaining_time":59.66480734},
{"learn":[5.228973529],"iteration":41,"passed_time":2.631377163,"remaining_time":60.02046005},
{"learn":[5.108825395],"iteration":42,"passed_time":2.680888407,"remaining_time":59.66535361},
{"learn":[4.992989123],"iteration":43,"passed_time":2.742418162,"remaining_time":59.58526733},
{"learn":[4.882995125],"iteration":44,"passed_time":2.818414708,"remaining_time":59.81302325},
{"learn":[4.773524109],"iteration":45,"passed_time":2.913373166,"remaining_time":60.42082609},
{"learn":[4.671541966],"iteration":46,"passed_time":2.948859814,"remaining_time":59.79283836},
{"learn":[4.572920125],"iteration":47,"passed_time":3.00447947,"remaining_time":59.58884282},
{"learn":[4.474625379],"iteration":48,"passed_time":3.055027809,"remaining_time":59.29247849},
{"learn":[4.384590865],"iteration":49,"passed_time":3.123999685,"remaining_time":59.35599402},
{"learn":[4.294429802],"iteration":50,"passed_time":3.198131658,"remaining_time":59.51033223},
{"learn":[4.206270274],"iteration":51,"passed_time":3.258595079,"remaining_time":59.4066949},
{"learn":[4.123148352],"iteration":52,"passed_time":3.298007211,"remaining_time":58.92854395},
{"learn":[4.044546076],"iteration":53,"passed_time":3.342122367,"remaining_time":58.54903257},
{"learn":[3.969364948],"iteration":54,"passed_time":3.408744573,"remaining_time":58.56842948},
{"learn":[3.893557612],"iteration":55,"passed_time":3.499700545,"remaining_time":58.99495204},
{"learn":[3.823348598],"iteration":56,"passed_time":3.576523224,"remaining_time":59.16949824},
{"learn":[3.758995527],"iteration":57,"passed_time":3.596406423,"remaining_time":58.41060087},
{"learn":[3.69110961],"iteration":58,"passed_time":3.667675441,"remaining_time":58.49631509},
{"learn":[3.62737399],"iteration":59,"passed_time":3.743432706,"remaining_time":58.6471124},
{"learn":[3.565934885],"iteration":60,"passed_time":3.821225677,"remaining_time":58.82181821},
{"learn":[3.506820875],"iteration":61,"passed_time":3.899784568,"remaining_time":58.99996653},
{"learn":[3.452985476],"iteration":62,"passed_time":3.961525273,"remaining_time":58.91982826},
{"learn":[3.39982638],"iteration":63,"passed_time":4.075098038,"remaining_time":59.59830881},
{"learn":[3.347083111],"iteration":64,"passed_time":4.118443684,"remaining_time":59.24222838},
{"learn":[3.294452498],"iteration":65,"passed_time":4.17115781,"remaining_time":59.02820295},
{"learn":[3.246214408],"iteration":66,"passed_time":4.22288543,"remaining_time":58.80525532},
{"learn":[3.199921508],"iteration":67,"passed_time":4.28794049,"remaining_time":58.77000789},
{"learn":[3.155333975],"iteration":68,"passed_time":4.321749738,"remaining_time":58.31230444},
{"learn":[3.112008994],"iteration":69,"passed_time":4.36305712,"remaining_time":57.96633031},
{"learn":[3.07144721],"iteration":70,"passed_time":4.377509795,"remaining_time":57.27755774},
{"learn":[3.035392729],"iteration":71,"passed_time":4.436981178,"remaining_time":57.18775741},
{"learn":[2.997583304],"iteration":72,"passed_time":4.497953302,"remaining_time":57.11784536},
{"learn":[2.964862479],"iteration":73,"passed_time":4.561446243,"remaining_time":57.0797192},
{"learn":[2.933074661],"iteration":74,"passed_time":4.619275644,"remaining_time":56.97106627},
{"learn":[2.900626276],"iteration":75,"passed_time":4.698234441,"remaining_time":57.12063978},
{"learn":[2.868428931],"iteration":76,"passed_time":4.777342142,"remaining_time":57.2660623},
{"learn":[2.836706924],"iteration":77,"passed_time":4.840322706,"remaining_time":57.2150966},
{"learn":[2.807129215],"iteration":78,"passed_time":4.855720633,"remaining_time":56.60909751},
{"learn":[2.779947785],"iteration":79,"passed_time":4.900850137,"remaining_time":56.35977658},
{"learn":[2.751528183],"iteration":80,"passed_time":4.93770519,"remaining_time":56.02161814},
{"learn":[2.725894947],"iteration":81,"passed_time":5.037464472,"remaining_time":56.39502909},
{"learn":[2.701390643],"iteration":82,"passed_time":5.097143453,"remaining_time":56.31422346},
{"learn":[2.677729095],"iteration":83,"passed_time":5.178464451,"remaining_time":56.46992187},
{"learn":[2.656369981],"iteration":84,"passed_time":5.214923594,"remaining_time":56.13711869},
{"learn":[2.634976832],"iteration":85,"passed_time":5.290631848,"remaining_time":56.22834313},
{"learn":[2.615086252],"iteration":86,"passed_time":5.358595663,"remaining_time":56.23445794},
{"learn":[2.595813305],"iteration":87,"passed_time":5.392607236,"remaining_time":55.88702045},
{"learn":[2.577766691],"iteration":88,"passed_time":5.470146549,"remaining_time":55.99217422},
{"learn":[2.559572002],"iteration":89,"passed_time":5.549010024,"remaining_time":56.10665691},
{"learn":[2.54075243],"iteration":90,"passed_time":5.628766802,"remaining_time":56.22581344},
{"learn":[2.524226006],"iteration":91,"passed_time":5.691956801,"remaining_time":56.17713886},
{"learn":[2.509677748],"iteration":92,"passed_time":5.767032271,"remaining_time":56.24406742},
{"learn":[2.494726079],"iteration":93,"passed_time":5.831042306,"remaining_time":56.20132265},
{"learn":[2.480477959],"iteration":94,"passed_time":5.910329274,"remaining_time":56.30366309},
{"learn":[2.467291405],"iteration":95,"passed_time":6.02612765,"remaining_time":56.74603537},
{"learn":[2.453262349],"iteration":96,"passed_time":6.084089661,"remaining_time":56.63848416},
{"learn":[2.441235233],"iteration":97,"passed_time":6.13416715,"remaining_time":56.4593752},
{"learn":[2.429561833],"iteration":98,"passed_time":6.211264222,"remaining_time":56.52877843},
{"learn":[2.418198912],"iteration":99,"passed_time":6.304905631,"remaining_time":56.74415068},
{"learn":[2.409526745],"iteration":100,"passed_time":6.349826248,"remaining_time":56.51974057},
{"learn":[2.399093978],"iteration":101,"passed_time":6.425255798,"remaining_time":56.5674481},
{"learn":[2.391127604],"iteration":102,"passed_time":6.493866417,"remaining_time":56.55338035},
{"learn":[2.38037399],"iteration":103,"passed_time":6.585378986,"remaining_time":56.7355728},
{"learn":[2.370435535],"iteration":104,"passed_time":6.632512131,"remaining_time":56.53427007},
{"learn":[2.361284123],"iteration":105,"passed_time":6.689654994,"remaining_time":56.42029778},
{"learn":[2.351969547],"iteration":106,"passed_time":6.763353008,"remaining_time":56.44555361},
{"learn":[2.344187325],"iteration":107,"passed_time":6.828434182,"remaining_time":56.39780824},
{"learn":[2.336528933],"iteration":108,"passed_time":6.899899862,"remaining_time":56.40193373},
{"learn":[2.331872035],"iteration":109,"passed_time":6.929013667,"remaining_time":56.06201967},
{"learn":[2.324725069],"iteration":110,"passed_time":6.987975476,"remaining_time":55.96675854},
{"learn":[2.319056417],"iteration":111,"passed_time":7.030334144,"remaining_time":55.74050643},
{"learn":[2.313352358],"iteration":112,"passed_time":7.065426485,"remaining_time":55.46047162},
{"learn":[2.306939934],"iteration":113,"passed_time":7.123853339,"remaining_time":55.36608823},
{"learn":[2.30203872],"iteration":114,"passed_time":7.17568041,"remaining_time":55.22154054},
{"learn":[2.2972521],"iteration":115,"passed_time":7.230110917,"remaining_time":55.09843147},
{"learn":[2.293556392],"iteration":116,"passed_time":7.285737187,"remaining_time":54.98552082},
{"learn":[2.288513665],"iteration":117,"passed_time":7.381490178,"remaining_time":55.17351133},
{"learn":[2.283936899],"iteration":118,"passed_time":7.445537996,"remaining_time":55.12200819},
{"learn":[2.277257769],"iteration":119,"passed_time":7.521234685,"remaining_time":55.15572102},
{"learn":[2.272728814],"iteration":120,"passed_time":7.587109254,"remaining_time":55.11627301},
{"learn":[2.267892192],"iteration":121,"passed_time":7.624815145,"remaining_time":54.87366965},
{"learn":[2.26246078],"iteration":122,"passed_time":7.725027904,"remaining_time":55.08007701},
{"learn":[2.257522755],"iteration":123,"passed_time":7.794345444,"remaining_time":55.06327911},
{"learn":[2.254334907],"iteration":124,"passed_time":7.84864717,"remaining_time":54.94053019},
{"learn":[2.251572246],"iteration":125,"passed_time":7.940244287,"remaining_time":55.07756751},
{"learn":[2.246129141],"iteration":126,"passed_time":7.990533618,"remaining_time":54.92705393},
{"learn":[2.243487747],"iteration":127,"passed_time":8.041641933,"remaining_time":54.78368567},
{"learn":[2.240465354],"iteration":128,"passed_time":8.106269095,"remaining_time":54.73302622},
{"learn":[2.237368488],"iteration":129,"passed_time":8.198926307,"remaining_time":54.86973759},
{"learn":[2.235508093],"iteration":130,"passed_time":8.241589233,"remaining_time":54.67130568},
{"learn":[2.232193082],"iteration":131,"passed_time":8.317949243,"remaining_time":54.69681775},
{"learn":[2.228614371],"iteration":132,"passed_time":8.396873677,"remaining_time":54.73751487},
{"learn":[2.224453346],"iteration":133,"passed_time":8.477359335,"remaining_time":54.7865163},
{"learn":[2.221576332],"iteration":134,"passed_time":8.549664087,"remaining_time":54.781181},
{"learn":[2.219812766],"iteration":135,"passed_time":8.633334031,"remaining_time":54.84706325},
{"learn":[2.217065463],"iteration":136,"passed_time":8.709486439,"remaining_time":54.86340728},
{"learn":[2.214925957],"iteration":137,"passed_time":8.755801279,"remaining_time":54.69203408},
{"learn":[2.212682537],"iteration":138,"passed_time":8.801732544,"remaining_time":54.52008432},
{"learn":[2.20951968],"iteration":139,"passed_time":8.890767609,"remaining_time":54.61471531},
{"learn":[2.207647354],"iteration":140,"passed_time":8.964780931,"remaining_time":54.61522567},
{"learn":[2.203354432],"iteration":141,"passed_time":9.047006897,"remaining_time":54.66430928},
{"learn":[2.201676351],"iteration":142,"passed_time":9.125363996,"remaining_time":54.68837024},
{"learn":[2.200209916],"iteration":143,"passed_time":9.187695625,"remaining_time":54.61574622},
{"learn":[2.195951082],"iteration":144,"passed_time":9.240962983,"remaining_time":54.48981621},
{"learn":[2.193272502],"iteration":145,"passed_time":9.328063098,"remaining_time":54.56278004},
{"learn":[2.191637826],"iteration":146,"passed_time":9.37047993,"remaining_time":54.3742815},
{"learn":[2.18991341],"iteration":147,"passed_time":9.408173227,"remaining_time":54.16056479},
{"learn":[2.187483366],"iteration":148,"passed_time":9.485581528,"remaining_time":54.17603946},
{"learn":[2.184135271],"iteration":149,"passed_time":9.536448324,"remaining_time":54.03987384},
{"learn":[2.18129122],"iteration":150,"passed_time":9.5858553,"remaining_time":53.89663013},
{"learn":[2.177412323],"iteration":151,"passed_time":9.65155396,"remaining_time":53.84551157},
{"learn":[2.174669966],"iteration":152,"passed_time":9.742627867,"remaining_time":53.93467845},
{"learn":[2.171872701],"iteration":153,"passed_time":9.842899868,"remaining_time":54.07203434},
{"learn":[2.170019085],"iteration":154,"passed_time":9.897270047,"remaining_time":53.95608509},
{"learn":[2.166931457],"iteration":155,"passed_time":9.945015283,"remaining_time":53.80508268},
{"learn":[2.164306377],"iteration":156,"passed_time":10.04150833,"remaining_time":53.91714346},
{"learn":[2.162731419],"iteration":157,"passed_time":10.10638802,"remaining_time":53.85809313},
{"learn":[2.159856922],"iteration":158,"passed_time":10.18589936,"remaining_time":53.87636075},
{"learn":[2.156179773],"iteration":159,"passed_time":10.29989273,"remaining_time":54.07443682},
{"learn":[2.155022391],"iteration":160,"passed_time":10.37737432,"remaining_time":54.07836681},
{"learn":[2.153760242],"iteration":161,"passed_time":10.41730813,"remaining_time":53.88706305},
{"learn":[2.151775715],"iteration":162,"passed_time":10.47502341,"remaining_time":53.78892388},
{"learn":[2.149992666],"iteration":163,"passed_time":10.54548104,"remaining_time":53.75623264},
{"learn":[2.147946721],"iteration":164,"passed_time":10.61612009,"remaining_time":53.72400168},
{"learn":[2.146537645],"iteration":165,"passed_time":10.68116801,"remaining_time":53.66321762},
{"learn":[2.14597415],"iteration":166,"passed_time":10.72403587,"remaining_time":53.49174777},
{"learn":[2.142907006],"iteration":167,"passed_time":10.76045105,"remaining_time":53.28985279},
{"learn":[2.140736955],"iteration":168,"passed_time":10.81136547,"remaining_time":53.16121126},
{"learn":[2.138871194],"iteration":169,"passed_time":10.86298314,"remaining_time":53.03691768},
{"learn":[2.138261466],"iteration":170,"passed_time":10.92331032,"remaining_time":52.95569741},
{"learn":[2.136824918],"iteration":171,"passed_time":10.96079865,"remaining_time":52.76477487},
{"learn":[2.13519017],"iteration":172,"passed_time":11.04130856,"remaining_time":52.78128428},
{"learn":[2.132720841],"iteration":173,"passed_time":11.12091441,"remaining_time":52.79238679},
{"learn":[2.131895088],"iteration":174,"passed_time":11.22020729,"remaining_time":52.89526296},
{"learn":[2.130461602],"iteration":175,"passed_time":11.26137204,"remaining_time":52.72369635},
{"learn":[2.129596099],"iteration":176,"passed_time":11.32276975,"remaining_time":52.64768081},
{"learn":[2.129294562],"iteration":177,"passed_time":11.38034729,"remaining_time":52.55418804},
{"learn":[2.128487296],"iteration":178,"passed_time":11.442941,"remaining_time":52.4841037},
{"learn":[2.127945421],"iteration":179,"passed_time":11.47879595,"remaining_time":52.29229265},
{"learn":[2.127483351],"iteration":180,"passed_time":11.51214711,"remaining_time":52.09087561},
{"learn":[2.126240147],"iteration":181,"passed_time":11.59485752,"remaining_time":52.11315081},
{"learn":[2.125481641],"iteration":182,"passed_time":11.65257712,"remaining_time":52.02270768},
{"learn":[2.124289435],"iteration":183,"passed_time":11.69944136,"remaining_time":51.88447906},
{"learn":[2.121995547],"iteration":184,"passed_time":11.77748719,"remaining_time":51.88460572},
{"learn":[2.121227503],"iteration":185,"passed_time":11.87274048,"remaining_time":51.9591976},
{"learn":[2.120263317],"iteration":186,"passed_time":11.92756666,"remaining_time":51.85621228},
{"learn":[2.119503197],"iteration":187,"passed_time":11.97823751,"remaining_time":51.7357918},
{"learn":[2.118702886],"iteration":188,"passed_time":12.05791339,"remaining_time":51.74057016},
{"learn":[2.117775366],"iteration":189,"passed_time":12.12309365,"remaining_time":51.68266241},
{"learn":[2.11768754],"iteration":190,"passed_time":12.13587203,"remaining_time":51.402725},
{"learn":[2.116000407],"iteration":191,"passed_time":12.23175364,"remaining_time":51.47529655},
{"learn":[2.115341097],"iteration":192,"passed_time":12.30962368,"remaining_time":51.47080989},
{"learn":[2.114616158],"iteration":193,"passed_time":12.37334977,"remaining_time":51.40680367},
{"learn":[2.113182426],"iteration":194,"passed_time":12.4333267,"remaining_time":51.32732305},
{"learn":[2.11253792],"iteration":195,"passed_time":12.49526789,"remaining_time":51.2560989},
{"learn":[2.11125939],"iteration":196,"passed_time":12.59181358,"remaining_time":51.32602187},
{"learn":[2.110814429],"iteration":197,"passed_time":12.70762018,"remaining_time":51.47227972},
{"learn":[2.109684897],"iteration":198,"passed_time":12.78846026,"remaining_time":51.47515913},
{"learn":[2.106190217],"iteration":199,"passed_time":12.87084734,"remaining_time":51.48338937},
{"learn":[2.10436753],"iteration":200,"passed_time":12.93420774,"remaining_time":51.41508451},
{"learn":[2.103480516],"iteration":201,"passed_time":12.99054203,"remaining_time":51.31907198},
{"learn":[2.103082669],"iteration":202,"passed_time":13.04598901,"remaining_time":51.2199667},
{"learn":[2.10145032],"iteration":203,"passed_time":13.09298234,"remaining_time":51.08830366},
{"learn":[2.101313209],"iteration":204,"passed_time":13.13626094,"remaining_time":50.94306073},
{"learn":[2.100968505],"iteration":205,"passed_time":13.17576363,"remaining_time":50.784254},
{"learn":[2.099685161],"iteration":206,"passed_time":13.2325929,"remaining_time":50.69297668},
{"learn":[2.099200675],"iteration":207,"passed_time":13.29453937,"remaining_time":50.62151528},
{"learn":[2.098361585],"iteration":208,"passed_time":13.35172742,"remaining_time":50.53213582},
{"learn":[2.09796549],"iteration":209,"passed_time":13.39333127,"remaining_time":50.3844367},
{"learn":[2.097059363],"iteration":210,"passed_time":13.47034933,"remaining_time":50.37016881},
{"learn":[2.094610956],"iteration":211,"passed_time":13.56589151,"remaining_time":50.42416279},
{"learn":[2.09365197],"iteration":212,"passed_time":13.63374944,"remaining_time":50.37446388},
{"learn":[2.092469687],"iteration":213,"passed_time":13.71043344,"remaining_time":50.35701254},
{"learn":[2.089406622],"iteration":214,"passed_time":13.78900996,"remaining_time":50.34592009},
{"learn":[2.088770726],"iteration":215,"passed_time":13.88378328,"remaining_time":50.39299116},
{"learn":[2.087868655],"iteration":216,"passed_time":13.9688593,"remaining_time":50.40376419},
{"learn":[2.086355598],"iteration":217,"passed_time":14.04793716,"remaining_time":50.39214155},
{"learn":[2.084621499],"iteration":218,"passed_time":14.12350727,"remaining_time":50.36739352},
{"learn":[2.083048774],"iteration":219,"passed_time":14.21462253,"remaining_time":50.39729805},
{"learn":[2.082182515],"iteration":220,"passed_time":14.28799018,"remaining_time":50.36354911},
{"learn":[2.081791312],"iteration":221,"passed_time":14.39661449,"remaining_time":50.45300034},
{"learn":[2.08146653],"iteration":222,"passed_time":14.43254707,"remaining_time":50.28739496},
{"learn":[2.079745023],"iteration":223,"passed_time":14.52024363,"remaining_time":50.30227259},
{"learn":[2.078628494],"iteration":224,"passed_time":14.58728605,"remaining_time":50.2450964},
{"learn":[2.078344182],"iteration":225,"passed_time":14.64744867,"remaining_time":50.1642711},
{"learn":[2.0773582],"iteration":226,"passed_time":14.68778284,"remaining_time":50.01610631},
{"learn":[2.076524899],"iteration":227,"passed_time":14.72624261,"remaining_time":49.86254076},
{"learn":[2.076067379],"iteration":228,"passed_time":14.80720731,"remaining_time":49.85308661},
{"learn":[2.0749211],"iteration":229,"passed_time":14.83383568,"remaining_time":49.66110205},
{"learn":[2.074672906],"iteration":230,"passed_time":14.90288635,"remaining_time":49.61177318},
{"learn":[2.073385679],"iteration":231,"passed_time":15.00462242,"remaining_time":49.67047422},
{"learn":[2.072349312],"iteration":232,"passed_time":15.09683089,"remaining_time":49.69643474},
{"learn":[2.070228418],"iteration":233,"passed_time":15.16064908,"remaining_time":49.62844957},
{"learn":[2.069720451],"iteration":234,"passed_time":15.25644828,"remaining_time":49.66460822},
{"learn":[2.068840167],"iteration":235,"passed_time":15.30491414,"remaining_time":49.54641695},
{"learn":[2.068376973],"iteration":236,"passed_time":15.34197012,"remaining_time":49.39208101},
{"learn":[2.067279197],"iteration":237,"passed_time":15.44171072,"remaining_time":49.43942676},
{"learn":[2.06680747],"iteration":238,"passed_time":15.53552107,"remaining_time":49.46665914},
{"learn":[2.065774805],"iteration":239,"passed_time":15.59972432,"remaining_time":49.39912701},
{"learn":[2.065563763],"iteration":240,"passed_time":15.66839846,"remaining_time":49.34570304},
{"learn":[2.063332193],"iteration":241,"passed_time":15.71230244,"remaining_time":49.21456715},
{"learn":[2.062740245],"iteration":242,"passed_time":15.77863794,"remaining_time":49.15402849},
{"learn":[2.061526925],"iteration":243,"passed_time":15.86028762,"remaining_time":49.14089116},
{"learn":[2.061374015],"iteration":244,"passed_time":15.97255134,"remaining_time":49.22153577},
{"learn":[2.060138123],"iteration":245,"passed_time":16.05848577,"remaining_time":49.21991168},
{"learn":[2.059176715],"iteration":246,"passed_time":16.0990467,"remaining_time":49.07928002},
{"learn":[2.058445459],"iteration":247,"passed_time":16.17665519,"remaining_time":49.05179314},
{"learn":[2.057342211],"iteration":248,"passed_time":16.21953214,"remaining_time":48.91915116},
{"learn":[2.057323112],"iteration":249,"passed_time":16.31134175,"remaining_time":48.93402526},
{"learn":[2.053062673],"iteration":250,"passed_time":16.36349132,"remaining_time":48.82970118},
{"learn":[2.052032606],"iteration":251,"passed_time":16.44160613,"remaining_time":48.80286264},
{"learn":[2.051752436],"iteration":252,"passed_time":16.48941367,"remaining_time":48.68613443},
{"learn":[2.050041744],"iteration":253,"passed_time":16.54273511,"remaining_time":48.58614329},
{"learn":[2.049523196],"iteration":254,"passed_time":16.59682527,"remaining_time":48.48876403},
{"learn":[2.049401313],"iteration":255,"passed_time":16.62715187,"remaining_time":48.32266012},
{"learn":[2.049193805],"iteration":256,"passed_time":16.69120721,"remaining_time":48.25512435},
{"learn":[2.049192973],"iteration":257,"passed_time":16.71893341,"remaining_time":48.08313406},
{"learn":[2.048868061],"iteration":258,"passed_time":16.78411106,"remaining_time":48.01940653},
{"learn":[2.04835518],"iteration":259,"passed_time":16.843965,"remaining_time":47.94051576},
{"learn":[2.047845175],"iteration":260,"passed_time":16.8901398,"remaining_time":47.82303952},
{"learn":[2.046473052],"iteration":261,"passed_time":16.97820259,"remaining_time":47.82409737},
{"learn":[2.045911338],"iteration":262,"passed_time":17.04492548,"remaining_time":47.7646771},
{"learn":[2.045456415],"iteration":263,"passed_time":17.12381807,"remaining_time":47.73912917},
{"learn":[2.044511804],"iteration":264,"passed_time":17.20214878,"remaining_time":47.71162019},
{"learn":[2.041907195],"iteration":265,"passed_time":17.29539482,"remaining_time":47.72488647},
{"learn":[2.040547299],"iteration":266,"passed_time":17.37670979,"remaining_time":47.70460028},
{"learn":[2.040054583],"iteration":267,"passed_time":17.45684836,"remaining_time":47.68064552},
{"learn":[2.038406857],"iteration":268,"passed_time":17.51906102,"remaining_time":47.60755988},
{"learn":[2.038027231],"iteration":269,"passed_time":17.55881402,"remaining_time":47.4738305},
{"learn":[2.037727456],"iteration":270,"passed_time":17.6024695,"remaining_time":47.35129251},
{"learn":[2.034996134],"iteration":271,"passed_time":17.66963613,"remaining_time":47.29226141},
{"learn":[2.03400279],"iteration":272,"passed_time":17.75430247,"remaining_time":47.27977251},
{"learn":[2.033022795],"iteration":273,"passed_time":17.8172031,"remaining_time":47.20908558},
{"learn":[2.032665751],"iteration":274,"passed_time":17.85939636,"remaining_time":47.08386312},
{"learn":[2.032355436],"iteration":275,"passed_time":17.92939089,"remaining_time":47.03217032},
{"learn":[2.032143291],"iteration":276,"passed_time":17.96242289,"remaining_time":46.88386913},
{"learn":[2.028001658],"iteration":277,"passed_time":18.05307763,"remaining_time":46.88605053},
{"learn":[2.027445325],"iteration":278,"passed_time":18.15339019,"remaining_time":46.91252447},
{"learn":[2.022189858],"iteration":279,"passed_time":18.21448878,"remaining_time":46.83725686},
{"learn":[2.021956542],"iteration":280,"passed_time":18.31245639,"remaining_time":46.85642755},
{"learn":[2.021955706],"iteration":281,"passed_time":18.35117887,"remaining_time":46.72392352},
{"learn":[2.021739611],"iteration":282,"passed_time":18.40549606,"remaining_time":46.63159249},
{"learn":[2.020778144],"iteration":283,"passed_time":18.47959767,"remaining_time":46.58940821},
{"learn":[2.016750194],"iteration":284,"passed_time":18.57551318,"remaining_time":46.60172606},
{"learn":[2.013594357],"iteration":285,"passed_time":18.65571588,"remaining_time":46.57405993},
{"learn":[2.013059594],"iteration":286,"passed_time":18.74352054,"remaining_time":46.56491339},
{"learn":[2.012421741],"iteration":287,"passed_time":18.82855108,"remaining_time":46.54836239},
{"learn":[2.012260285],"iteration":288,"passed_time":18.87298027,"remaining_time":46.43144972},
{"learn":[2.012098907],"iteration":289,"passed_time":18.93862745,"remaining_time":46.36698445},
{"learn":[2.011480304],"iteration":290,"passed_time":18.96867139,"remaining_time":46.21576639},
{"learn":[2.011352218],"iteration":291,"passed_time":19.04609752,"remaining_time":46.18026385},
{"learn":[2.009012575],"iteration":292,"passed_time":19.10361864,"remaining_time":46.09644497},
{"learn":[2.008520926],"iteration":293,"passed_time":19.17757448,"remaining_time":46.05227068},
{"learn":[2.007088433],"iteration":294,"passed_time":19.24254637,"remaining_time":45.98642439},
{"learn":[2.006537216],"iteration":295,"passed_time":19.33614178,"remaining_time":45.98866152},
{"learn":[2.006400748],"iteration":296,"passed_time":19.41800456,"remaining_time":45.96248217},
{"learn":[2.006227729],"iteration":297,"passed_time":19.46463856,"remaining_time":45.8529405},
{"learn":[2.005511666],"iteration":298,"passed_time":19.52365073,"remaining_time":45.77284001},
{"learn":[2.004235402],"iteration":299,"passed_time":19.64189026,"remaining_time":45.83107727},
{"learn":[2.004201846],"iteration":300,"passed_time":19.70077237,"remaining_time":45.75029863},
{"learn":[2.003875608],"iteration":301,"passed_time":19.76214215,"remaining_time":45.67541463},
{"learn":[2.00324121],"iteration":302,"passed_time":19.85433802,"remaining_time":45.67153003},
{"learn":[2.002292905],"iteration":303,"passed_time":19.9203258,"remaining_time":45.60706169},
{"learn":[2.001202796],"iteration":304,"passed_time":20.01995915,"remaining_time":45.61925118},
{"learn":[2.000620329],"iteration":305,"passed_time":20.09831869,"remaining_time":45.58246133},
{"learn":[1.999671018],"iteration":306,"passed_time":20.13946264,"remaining_time":45.46139287},
{"learn":[1.998445316],"iteration":307,"passed_time":20.21707983,"remaining_time":45.42278974},
{"learn":[1.997909391],"iteration":308,"passed_time":20.29913643,"remaining_time":45.39386172},
{"learn":[1.997523559],"iteration":309,"passed_time":20.33367746,"remaining_time":45.25883048},
{"learn":[1.997402335],"iteration":310,"passed_time":20.3907965,"remaining_time":45.17446557},
{"learn":[1.996912126],"iteration":311,"passed_time":20.48526321,"remaining_time":45.17263169},
{"learn":[1.996698458],"iteration":312,"passed_time":20.56637071,"remaining_time":45.14088396},
{"learn":[1.995516375],"iteration":313,"passed_time":20.64553936,"remaining_time":45.10458599},
{"learn":[1.995161518],"iteration":314,"passed_time":20.7472994,"remaining_time":45.11714314},
{"learn":[1.994523693],"iteration":315,"passed_time":20.84098433,"remaining_time":45.11149772},
{"learn":[1.989549974],"iteration":316,"passed_time":20.91876231,"remaining_time":45.07102416},
{"learn":[1.988370438],"iteration":317,"passed_time":20.98265356,"remaining_time":45.00053374},
{"learn":[1.988064894],"iteration":318,"passed_time":21.05930001,"remaining_time":44.95731443},
{"learn":[1.9874933],"iteration":319,"passed_time":21.14200221,"remaining_time":44.92675469},
{"learn":[1.987034628],"iteration":320,"passed_time":21.21778442,"remaining_time":44.88123246},
{"learn":[1.986805416],"iteration":321,"passed_time":21.30462234,"remaining_time":44.85880107},
{"learn":[1.986494258],"iteration":322,"passed_time":21.3939661,"remaining_time":44.84122307},
{"learn":[1.985731417],"iteration":323,"passed_time":21.46387082,"remaining_time":44.78264406},
{"learn":[1.985149374],"iteration":324,"passed_time":21.56452017,"remaining_time":44.78784959},
{"learn":[1.984411948],"iteration":325,"passed_time":21.64095496,"remaining_time":44.74234246},
{"learn":[1.984166992],"iteration":326,"passed_time":21.71548803,"remaining_time":44.69273224},
{"learn":[1.983590924],"iteration":327,"passed_time":21.79829768,"remaining_time":44.65992696},
{"learn":[1.983053815],"iteration":328,"passed_time":21.87544689,"remaining_time":44.61527314},
{"learn":[1.98172666],"iteration":329,"passed_time":21.97442074,"remaining_time":44.61473302},
{"learn":[1.981155663],"iteration":330,"passed_time":22.04216202,"remaining_time":44.55047249},
{"learn":[1.979733316],"iteration":331,"passed_time":22.12483091,"remaining_time":44.51622605},
{"learn":[1.979244886],"iteration":332,"passed_time":22.18689215,"remaining_time":44.4404116},
{"learn":[1.978597824],"iteration":333,"passed_time":22.24900708,"remaining_time":44.36478657},
{"learn":[1.977747222],"iteration":334,"passed_time":22.32963887,"remaining_time":44.32599955},
{"learn":[1.977310799],"iteration":335,"passed_time":22.42404832,"remaining_time":44.31419074},
{"learn":[1.976290115],"iteration":336,"passed_time":22.52283392,"remaining_time":44.31050115},
{"learn":[1.976028732],"iteration":337,"passed_time":22.60316811,"remaining_time":44.27011032},
{"learn":[1.972614039],"iteration":338,"passed_time":22.66622434,"remaining_time":44.19579436},
{"learn":[1.970406513],"iteration":339,"passed_time":22.7460892,"remaining_time":44.15417315},
{"learn":[1.967908929],"iteration":340,"passed_time":22.82740131,"remaining_time":44.11512453},
{"learn":[1.967311512],"iteration":341,"passed_time":22.90107269,"remaining_time":44.06112816},
{"learn":[1.966180632],"iteration":342,"passed_time":22.97827559,"remaining_time":44.01378153},
{"learn":[1.965543293],"iteration":343,"passed_time":23.06463064,"remaining_time":43.98371425},
{"learn":[1.965105233],"iteration":344,"passed_time":23.14313376,"remaining_time":43.93841337},
{"learn":[1.963967054],"iteration":345,"passed_time":23.18468209,"remaining_time":43.82306962},
{"learn":[1.963719037],"iteration":346,"passed_time":23.27632837,"remaining_time":43.80242774},
{"learn":[1.963512212],"iteration":347,"passed_time":23.3585893,"remaining_time":43.76379375},
{"learn":[1.959541917],"iteration":348,"passed_time":23.43954523,"remaining_time":43.7224755},
{"learn":[1.95915873],"iteration":349,"passed_time":23.51796859,"remaining_time":43.67622738},
{"learn":[1.958790961],"iteration":350,"passed_time":23.61694661,"remaining_time":43.66780156},
{"learn":[1.958400126],"iteration":351,"passed_time":23.69746045,"remaining_time":43.62487037},
{"learn":[1.955974722],"iteration":352,"passed_time":23.75846222,"remaining_time":43.54596333},
{"learn":[1.955116768],"iteration":353,"passed_time":23.83052522,"remaining_time":43.48734263},
{"learn":[1.954573217],"iteration":354,"passed_time":23.90494363,"remaining_time":43.43292575},
{"learn":[1.953949791],"iteration":355,"passed_time":23.9721057,"remaining_time":43.36526985},
{"learn":[1.953664875],"iteration":356,"passed_time":24.05225603,"remaining_time":43.32101017},
{"learn":[1.952763386],"iteration":357,"passed_time":24.1277916,"remaining_time":43.26827433},
{"learn":[1.952673979],"iteration":358,"passed_time":24.1806827,"remaining_time":43.17497943},
{"learn":[1.952127219],"iteration":359,"passed_time":24.23069194,"remaining_time":43.07678568},
{"learn":[1.951361914],"iteration":360,"passed_time":24.32385251,"remaining_time":43.05524032},
{"learn":[1.951298472],"iteration":361,"passed_time":24.38702036,"remaining_time":42.98043919},
{"learn":[1.950994704],"iteration":362,"passed_time":24.46133891,"remaining_time":42.92526965},
{"learn":[1.950093157],"iteration":363,"passed_time":24.53743531,"remaining_time":42.87310126},
{"learn":[1.949682509],"iteration":364,"passed_time":24.59938527,"remaining_time":42.79619081},
{"learn":[1.947717087],"iteration":365,"passed_time":24.67473429,"remaining_time":42.74257251},
{"learn":[1.947321375],"iteration":366,"passed_time":24.75148661,"remaining_time":42.6912562},
{"learn":[1.946540618],"iteration":367,"passed_time":24.84002442,"remaining_time":42.66004194},
{"learn":[1.946404002],"iteration":368,"passed_time":24.93177869,"remaining_time":42.63401723},
{"learn":[1.942215896],"iteration":369,"passed_time":24.99442126,"remaining_time":42.55806863},
{"learn":[1.938922871],"iteration":370,"passed_time":25.09031406,"remaining_time":42.5385648},
{"learn":[1.938153716],"iteration":371,"passed_time":25.16911422,"remaining_time":42.48979498},
{"learn":[1.937725367],"iteration":372,"passed_time":25.23433358,"remaining_time":42.41803527},
{"learn":[1.937338594],"iteration":373,"passed_time":25.31430666,"remaining_time":42.37100526},
{"learn":[1.936878655],"iteration":374,"passed_time":25.39268125,"remaining_time":42.32113542},
{"learn":[1.93566295],"iteration":375,"passed_time":25.45326176,"remaining_time":42.24158334},
{"learn":[1.935475594],"iteration":376,"passed_time":25.53317833,"remaining_time":42.19408515},
{"learn":[1.934504278],"iteration":377,"passed_time":25.60746943,"remaining_time":42.13715869},
{"learn":[1.933850289],"iteration":378,"passed_time":25.67177832,"remaining_time":42.06378453},
{"learn":[1.931267356],"iteration":379,"passed_time":25.75183535,"remaining_time":42.01615241},
{"learn":[1.931054009],"iteration":380,"passed_time":25.8461954,"remaining_time":41.99158781},
{"learn":[1.930278414],"iteration":381,"passed_time":25.91513399,"remaining_time":41.9255309},
{"learn":[1.929666168],"iteration":382,"passed_time":26.00650877,"remaining_time":41.8956029},
{"learn":[1.929384454],"iteration":383,"passed_time":26.08367822,"remaining_time":41.84256715},
{"learn":[1.928694704],"iteration":384,"passed_time":26.17859539,"remaining_time":41.81775628},
{"learn":[1.927498441],"iteration":385,"passed_time":26.23800551,"remaining_time":41.73610203},
{"learn":[1.925523041],"iteration":386,"passed_time":26.3044221,"remaining_time":41.66566084},
{"learn":[1.925186554],"iteration":387,"passed_time":26.39050613,"remaining_time":41.62626224},
{"learn":[1.924895005],"iteration":388,"passed_time":26.46886646,"remaining_time":41.57449206},
{"learn":[1.924768666],"iteration":389,"passed_time":26.54808234,"remaining_time":41.52392367},
{"learn":[1.924196998],"iteration":390,"passed_time":26.62800159,"remaining_time":41.47430426},
{"learn":[1.923413215],"iteration":391,"passed_time":26.68779954,"remaining_time":41.39332174},
{"learn":[1.923345884],"iteration":392,"passed_time":26.75428403,"remaining_time":41.32277457},
{"learn":[1.922711931],"iteration":393,"passed_time":26.80877253,"remaining_time":41.23379734},
{"learn":[1.922238384],"iteration":394,"passed_time":26.85531128,"remaining_time":41.13281854},
{"learn":[1.921609473],"iteration":395,"passed_time":26.92042162,"remaining_time":41.06044106},
{"learn":[1.92080833],"iteration":396,"passed_time":26.99376493,"remaining_time":41.00060518},
{"learn":[1.920637933],"iteration":397,"passed_time":27.05550449,"remaining_time":40.92315001},
{"learn":[1.920549562],"iteration":398,"passed_time":27.14620442,"remaining_time":40.88939563},
{"learn":[1.919450631],"iteration":399,"passed_time":27.24509321,"remaining_time":40.86763982},
{"learn":[1.915889023],"iteration":400,"passed_time":27.29369132,"remaining_time":40.77037681},
{"learn":[1.915389608],"iteration":401,"passed_time":27.35281075,"remaining_time":40.68900704},
{"learn":[1.915283938],"iteration":402,"passed_time":27.39196056,"remaining_time":40.5781649},
{"learn":[1.912254842],"iteration":403,"passed_time":27.46999937,"remaining_time":40.52504857},
{"learn":[1.911708833],"iteration":404,"passed_time":27.54861982,"remaining_time":40.47266368},
{"learn":[1.911142094],"iteration":405,"passed_time":27.61270895,"remaining_time":40.39888945},
{"learn":[1.910620054],"iteration":406,"passed_time":27.69317997,"remaining_time":40.34903126},
{"learn":[1.907988904],"iteration":407,"passed_time":27.78656405,"remaining_time":40.3177596},
{"learn":[1.907688003],"iteration":408,"passed_time":27.86586188,"remaining_time":40.26582975},
{"learn":[1.907424921],"iteration":409,"passed_time":27.94281649,"remaining_time":40.21039446},
{"learn":[1.906723564],"iteration":410,"passed_time":27.98789747,"remaining_time":40.10917667},
{"learn":[1.906021629],"iteration":411,"passed_time":28.05658243,"remaining_time":40.04191861},
{"learn":[1.904719904],"iteration":412,"passed_time":28.14530497,"remaining_time":40.00313321},
{"learn":[1.903612159],"iteration":413,"passed_time":28.2515182,"remaining_time":39.98886393},
{"learn":[1.902665735],"iteration":414,"passed_time":28.3449721,"remaining_time":39.95616549},
{"learn":[1.901467291],"iteration":415,"passed_time":28.42412986,"remaining_time":39.90310539},
{"learn":[1.901176332],"iteration":416,"passed_time":28.48833317,"remaining_time":39.82901256},
{"learn":[1.900293444],"iteration":417,"passed_time":28.56339917,"remaining_time":39.77009167},
{"learn":[1.896841235],"iteration":418,"passed_time":28.62753662,"remaining_time":39.69593979},
{"learn":[1.896728759],"iteration":419,"passed_time":28.70492025,"remaining_time":39.64012797},
{"learn":[1.895909467],"iteration":420,"passed_time":28.75843825,"remaining_time":39.55139133},
{"learn":[1.895669601],"iteration":421,"passed_time":28.81134901,"remaining_time":39.46198988},
{"learn":[1.894953736],"iteration":422,"passed_time":28.86701163,"remaining_time":39.37651468},
{"learn":[1.893302123],"iteration":423,"passed_time":28.94541029,"remaining_time":39.32206681},
{"learn":[1.892304382],"iteration":424,"passed_time":29.03970044,"remaining_time":39.28900648},
{"learn":[1.891316349],"iteration":425,"passed_time":29.10407107,"remaining_time":39.21534458},
{"learn":[1.889349803],"iteration":426,"passed_time":29.17965556,"remaining_time":39.15677433},
{"learn":[1.889095667],"iteration":427,"passed_time":29.27898896,"remaining_time":39.12986375},
{"learn":[1.888719225],"iteration":428,"passed_time":29.35729869,"remaining_time":39.07463299},
{"learn":[1.887839166],"iteration":429,"passed_time":29.45634894,"remaining_time":39.04678813},
{"learn":[1.887214018],"iteration":430,"passed_time":29.57791077,"remaining_time":39.04833232},
{"learn":[1.886838519],"iteration":431,"passed_time":29.64587964,"remaining_time":38.97884175},
{"learn":[1.886561931],"iteration":432,"passed_time":29.73710995,"remaining_time":38.93981834},
{"learn":[1.886115584],"iteration":433,"passed_time":29.81665518,"remaining_time":38.88531529},
{"learn":[1.885340083],"iteration":434,"passed_time":29.89642118,"remaining_time":38.83098383},
{"learn":[1.885139046],"iteration":435,"passed_time":29.97602846,"remaining_time":38.7763304},
{"learn":[1.883722482],"iteration":436,"passed_time":30.05466385,"remaining_time":38.72031063},
{"learn":[1.883575213],"iteration":437,"passed_time":30.11879869,"remaining_time":38.64558188},
{"learn":[1.88315997],"iteration":438,"passed_time":30.1795667,"remaining_time":38.56659891},
{"learn":[1.882905662],"iteration":439,"passed_time":30.26056902,"remaining_time":38.51345148},
{"learn":[1.882376537],"iteration":440,"passed_time":30.34023793,"remaining_time":38.45848753},
{"learn":[1.88193989],"iteration":441,"passed_time":30.43411693,"remaining_time":38.42135124},
{"learn":[1.881057071],"iteration":442,"passed_time":30.49799944,"remaining_time":38.34624309},
{"learn":[1.880225345],"iteration":443,"passed_time":30.57627966,"remaining_time":38.28921507},
{"learn":[1.879468052],"iteration":444,"passed_time":30.65436857,"remaining_time":38.23185294},
{"learn":[1.87927677],"iteration":445,"passed_time":30.71607876,"remaining_time":38.15405299},
{"learn":[1.876225064],"iteration":446,"passed_time":30.79183677,"remaining_time":38.0937041},
{"learn":[1.876021852],"iteration":447,"passed_time":30.85587584,"remaining_time":38.01884702},
{"learn":[1.875811826],"iteration":448,"passed_time":30.91578714,"remaining_time":37.93897264},
{"learn":[1.875005793],"iteration":449,"passed_time":30.99476023,"remaining_time":37.88248472},
{"learn":[1.871991712],"iteration":450,"passed_time":31.05951713,"remaining_time":37.8085918},
{"learn":[1.871062229],"iteration":451,"passed_time":31.13372497,"remaining_time":37.74619753},
{"learn":[1.870702037],"iteration":452,"passed_time":31.19568638,"remaining_time":37.66896347},
{"learn":[1.870307187],"iteration":453,"passed_time":31.28021027,"remaining_time":37.61893129},
{"learn":[1.869630484],"iteration":454,"passed_time":31.34390683,"remaining_time":37.54380049},
{"learn":[1.869481504],"iteration":455,"passed_time":31.42188061,"remaining_time":37.48575231},
{"learn":[1.869295919],"iteration":456,"passed_time":31.49817388,"remaining_time":37.42562017},
{"learn":[1.868876378],"iteration":457,"passed_time":31.56383696,"remaining_time":37.35283762},
{"learn":[1.86862251],"iteration":458,"passed_time":31.64547663,"remaining_time":37.2989169},
{"learn":[1.868420452],"iteration":459,"passed_time":31.72744288,"remaining_time":37.24525904},
{"learn":[1.867883144],"iteration":460,"passed_time":31.83721889,"remaining_time":37.22399345},
{"learn":[1.867467585],"iteration":461,"passed_time":31.91587253,"remaining_time":37.16610264},
{"learn":[1.867186169],"iteration":462,"passed_time":31.97820796,"remaining_time":37.08919584},
{"learn":[1.867090433],"iteration":463,"passed_time":32.05945477,"remaining_time":37.03419775},
{"learn":[1.865531605],"iteration":464,"passed_time":32.10269559,"remaining_time":36.93535944},
{"learn":[1.865177341],"iteration":465,"passed_time":32.19395962,"remaining_time":36.89179064},
{"learn":[1.864992642],"iteration":466,"passed_time":32.27387498,"remaining_time":36.83506502},
{"learn":[1.86442673],"iteration":467,"passed_time":32.33671056,"remaining_time":36.75882482},
{"learn":[1.863112824],"iteration":468,"passed_time":32.39656686,"remaining_time":36.67926866},
{"learn":[1.862865207],"iteration":469,"passed_time":32.47290305,"remaining_time":36.61838004},
{"learn":[1.862777119],"iteration":470,"passed_time":32.53613977,"remaining_time":36.54271324},
{"learn":[1.86264368],"iteration":471,"passed_time":32.64918446,"remaining_time":36.52281651},
{"learn":[1.862165676],"iteration":472,"passed_time":32.72513929,"remaining_time":36.4612017},
{"learn":[1.860866525],"iteration":473,"passed_time":32.80051556,"remaining_time":36.39888436},
{"learn":[1.860539453],"iteration":474,"passed_time":32.88446456,"remaining_time":36.34598714},
{"learn":[1.860148031],"iteration":475,"passed_time":32.94974771,"remaining_time":36.27241135},
{"learn":[1.860007449],"iteration":476,"passed_time":33.02582071,"remaining_time":36.2107007},
{"learn":[1.859778726],"iteration":477,"passed_time":33.12902192,"remaining_time":36.17855532},
{"learn":[1.85924898],"iteration":478,"passed_time":33.20131777,"remaining_time":36.11249803},
{"learn":[1.858191622],"iteration":479,"passed_time":33.26649365,"remaining_time":36.03870145},
{"learn":[1.855958135],"iteration":480,"passed_time":33.31830959,"remaining_time":35.95052531},
{"learn":[1.855755512],"iteration":481,"passed_time":33.41762298,"remaining_time":35.91354503},
{"learn":[1.855610868],"iteration":482,"passed_time":33.4836385,"remaining_time":35.84066481},
{"learn":[1.854684939],"iteration":483,"passed_time":33.56295789,"remaining_time":35.78199643},
{"learn":[1.852871041],"iteration":484,"passed_time":33.65984982,"remaining_time":35.74190239},
{"learn":[1.852643712],"iteration":485,"passed_time":33.76814779,"remaining_time":35.71363779},
{"learn":[1.852550597],"iteration":486,"passed_time":33.83235731,"remaining_time":35.63860226},
{"learn":[1.852206465],"iteration":487,"passed_time":33.88421138,"remaining_time":35.550648},
{"learn":[1.852116973],"iteration":488,"passed_time":33.94397747,"remaining_time":35.47110938},
{"learn":[1.851540685],"iteration":489,"passed_time":34.00765987,"remaining_time":35.39572762},
{"learn":[1.851269962],"iteration":490,"passed_time":34.0698631,"remaining_time":35.31886012},
{"learn":[1.851007195],"iteration":491,"passed_time":34.14922992,"remaining_time":35.25977399},
{"learn":[1.850807295],"iteration":492,"passed_time":34.21092515,"remaining_time":35.18243215},
{"learn":[1.850514023],"iteration":493,"passed_time":34.28931244,"remaining_time":35.1222512},
{"learn":[1.850275685],"iteration":494,"passed_time":34.350129,"remaining_time":35.044071},
{"learn":[1.849997176],"iteration":495,"passed_time":34.39797665,"remaining_time":34.95278273},
{"learn":[1.849283969],"iteration":496,"passed_time":34.4542551,"remaining_time":34.87020185},
{"learn":[1.84909708],"iteration":497,"passed_time":34.55142646,"remaining_time":34.82894796},
{"learn":[1.848157627],"iteration":498,"passed_time":34.63052135,"remaining_time":34.76932104},
{"learn":[1.847274277],"iteration":499,"passed_time":34.69483628,"remaining_time":34.69483628},
{"learn":[1.847054187],"iteration":500,"passed_time":34.75423104,"remaining_time":34.61549159},
{"learn":[1.846293948],"iteration":501,"passed_time":34.81912626,"remaining_time":34.54168302},
{"learn":[1.846071821],"iteration":502,"passed_time":34.87603794,"remaining_time":34.46002158},
{"learn":[1.844676769],"iteration":503,"passed_time":34.95110928,"remaining_time":34.39632977},
{"learn":[1.843942011],"iteration":504,"passed_time":35.01651767,"remaining_time":34.32312128},
{"learn":[1.843271427],"iteration":505,"passed_time":35.11459625,"remaining_time":34.28183903},
{"learn":[1.842300268],"iteration":506,"passed_time":35.20907082,"remaining_time":34.23682823},
{"learn":[1.842183417],"iteration":507,"passed_time":35.26241876,"remaining_time":34.1517914},
{"learn":[1.842073093],"iteration":508,"passed_time":35.34051624,"remaining_time":34.09075338},
{"learn":[1.841511802],"iteration":509,"passed_time":35.39340407,"remaining_time":34.00542744},
{"learn":[1.840909094],"iteration":510,"passed_time":35.45611035,"remaining_time":33.92962419},
{"learn":[1.840783975],"iteration":511,"passed_time":35.54194065,"remaining_time":33.87591218},
{"learn":[1.839629165],"iteration":512,"passed_time":35.62236927,"remaining_time":33.81694705},
{"learn":[1.838797166],"iteration":513,"passed_time":35.72367746,"remaining_time":33.77764056},
{"learn":[1.838515429],"iteration":514,"passed_time":35.81492701,"remaining_time":33.72862059},
{"learn":[1.838359496],"iteration":515,"passed_time":35.88052635,"remaining_time":33.65537743},
{"learn":[1.838269022],"iteration":516,"passed_time":35.97413333,"remaining_time":33.60832959},
{"learn":[1.837823521],"iteration":517,"passed_time":36.05685469,"remaining_time":33.55097289},
{"learn":[1.837187291],"iteration":518,"passed_time":36.11315563,"remaining_time":33.46903249},
{"learn":[1.836993194],"iteration":519,"passed_time":36.20583738,"remaining_time":33.42077296},
{"learn":[1.8368162],"iteration":520,"passed_time":36.29183444,"remaining_time":33.36619711},
{"learn":[1.836057604],"iteration":521,"passed_time":36.37715363,"remaining_time":33.31088015},
{"learn":[1.833309331],"iteration":522,"passed_time":36.47623949,"remaining_time":33.26800428},
{"learn":[1.832701114],"iteration":523,"passed_time":36.5772186,"remaining_time":33.22663369},
{"learn":[1.83240944],"iteration":524,"passed_time":36.67064137,"remaining_time":33.17819934},
{"learn":[1.832303885],"iteration":525,"passed_time":36.73586323,"remaining_time":33.10418093},
{"learn":[1.830210227],"iteration":526,"passed_time":36.80091097,"remaining_time":33.03003964},
{"learn":[1.829497815],"iteration":527,"passed_time":36.8738241,"remaining_time":32.96296397},
{"learn":[1.828970972],"iteration":528,"passed_time":36.96909311,"remaining_time":32.91577099},
{"learn":[1.828686059],"iteration":529,"passed_time":37.03530387,"remaining_time":32.84262796},
{"learn":[1.828247653],"iteration":530,"passed_time":37.11224744,"remaining_time":32.77899068},
{"learn":[1.828121892],"iteration":531,"passed_time":37.15323865,"remaining_time":32.68367611},
{"learn":[1.82803321],"iteration":532,"passed_time":37.24130333,"remaining_time":32.62980986},
{"learn":[1.827114606],"iteration":533,"passed_time":37.3274683,"remaining_time":32.57415773},
{"learn":[1.826480069],"iteration":534,"passed_time":37.39198627,"remaining_time":32.49957685},
{"learn":[1.826033704],"iteration":535,"passed_time":37.49095525,"remaining_time":32.45485679},
{"learn":[1.825630713],"iteration":536,"passed_time":37.55128173,"remaining_time":32.37661721},
{"learn":[1.82488099],"iteration":537,"passed_time":37.62933629,"remaining_time":32.31366797},
{"learn":[1.823688101],"iteration":538,"passed_time":37.72745444,"remaining_time":32.26782282},
{"learn":[1.823617027],"iteration":539,"passed_time":37.80339453,"remaining_time":32.20289164},
{"learn":[1.823192912],"iteration":540,"passed_time":37.86871955,"remaining_time":32.12891363},
{"learn":[1.823081209],"iteration":541,"passed_time":37.94286171,"remaining_time":32.0624182},
{"learn":[1.822962136],"iteration":542,"passed_time":38.02275901,"remaining_time":32.00073824},
{"learn":[1.822339502],"iteration":543,"passed_time":38.10230289,"remaining_time":31.93869507},
{"learn":[1.821710144],"iteration":544,"passed_time":38.16631507,"remaining_time":31.86362084},
{"learn":[1.820963357],"iteration":545,"passed_time":38.25214304,"remaining_time":31.80672699},
{"learn":[1.819903594],"iteration":546,"passed_time":38.34372684,"remaining_time":31.75449407},
{"learn":[1.819429675],"iteration":547,"passed_time":38.40522145,"remaining_time":31.67729944},
{"learn":[1.81923038],"iteration":548,"passed_time":38.46699091,"remaining_time":31.60038779},
{"learn":[1.818878043],"iteration":549,"passed_time":38.54532168,"remaining_time":31.53708137},
{"learn":[1.818563588],"iteration":550,"passed_time":38.60517389,"remaining_time":31.45866257},
{"learn":[1.818397805],"iteration":551,"passed_time":38.70163352,"remaining_time":31.41002141},
{"learn":[1.817514267],"iteration":552,"passed_time":38.76275753,"remaining_time":31.33264487},
{"learn":[1.817035116],"iteration":553,"passed_time":38.83935992,"remaining_time":31.26778795},
{"learn":[1.816581623],"iteration":554,"passed_time":38.90273072,"remaining_time":31.19227959},
{"learn":[1.816482967],"iteration":555,"passed_time":38.98707544,"remaining_time":31.13356384},
{"learn":[1.816077538],"iteration":556,"passed_time":39.06228234,"remaining_time":31.06748847},
{"learn":[1.81564559],"iteration":557,"passed_time":39.15987506,"remaining_time":31.0191125},
{"learn":[1.815622707],"iteration":558,"passed_time":39.23557689,"remaining_time":30.95329053},
{"learn":[1.814951494],"iteration":559,"passed_time":39.30807028,"remaining_time":30.88491237},
{"learn":[1.814019746],"iteration":560,"passed_time":39.38018905,"remaining_time":30.81622637},
{"learn":[1.813915847],"iteration":561,"passed_time":39.47611984,"remaining_time":30.76608628},
{"learn":[1.813738725],"iteration":562,"passed_time":39.56073545,"remaining_time":30.70700069},
{"learn":[1.813647209],"iteration":563,"passed_time":39.63966846,"remaining_time":30.64343165},
{"learn":[1.813549765],"iteration":564,"passed_time":39.70681185,"remaining_time":30.57073125},
{"learn":[1.812208077],"iteration":565,"passed_time":39.79082597,"remaining_time":30.5109867},
{"learn":[1.810184458],"iteration":566,"passed_time":39.8602789,"remaining_time":30.44003662},
{"learn":[1.808367675],"iteration":567,"passed_time":39.95871493,"remaining_time":30.3911353},
{"learn":[1.807978409],"iteration":568,"passed_time":40.03612904,"remaining_time":30.32613641},
{"learn":[1.80755583],"iteration":569,"passed_time":40.1214157,"remaining_time":30.26703289},
{"learn":[1.807452452],"iteration":570,"passed_time":40.20493872,"remaining_time":30.20651263},
{"learn":[1.807212322],"iteration":571,"passed_time":40.27409602,"remaining_time":30.13516276},
{"learn":[1.806925203],"iteration":572,"passed_time":40.36092987,"remaining_time":30.07699312},
{"learn":[1.80601968],"iteration":573,"passed_time":40.43524435,"remaining_time":30.00943222},
{"learn":[1.80576157],"iteration":574,"passed_time":40.50498342,"remaining_time":29.938466},
{"learn":[1.805618165],"iteration":575,"passed_time":40.58823616,"remaining_time":29.87745162},
{"learn":[1.805468396],"iteration":576,"passed_time":40.65721928,"remaining_time":29.80589906},
{"learn":[1.803988274],"iteration":577,"passed_time":40.71947083,"remaining_time":29.72944064},
{"learn":[1.803799295],"iteration":578,"passed_time":40.78932746,"remaining_time":29.65856107},
{"learn":[1.803689135],"iteration":579,"passed_time":40.85660822,"remaining_time":29.58581975},
{"learn":[1.803222701],"iteration":580,"passed_time":40.93376392,"remaining_time":29.52021873},
{"learn":[1.802779315],"iteration":581,"passed_time":41.00225009,"remaining_time":29.44835144},
{"learn":[1.802153421],"iteration":582,"passed_time":41.05838965,"remaining_time":29.36766464},
{"learn":[1.801763724],"iteration":583,"passed_time":41.13392147,"remaining_time":29.30087556},
{"learn":[1.801690345],"iteration":584,"passed_time":41.20161577,"remaining_time":29.22849665},
{"learn":[1.801438744],"iteration":585,"passed_time":41.2710814,"remaining_time":29.15738516},
{"learn":[1.801354058],"iteration":586,"passed_time":41.3364553,"remaining_time":29.0834004},
{"learn":[1.801214188],"iteration":587,"passed_time":41.40087024,"remaining_time":29.00877303},
{"learn":[1.801090184],"iteration":588,"passed_time":41.45737044,"remaining_time":28.92865747},
{"learn":[1.800875034],"iteration":589,"passed_time":41.52345892,"remaining_time":28.85528501},
{"learn":[1.800461299],"iteration":590,"passed_time":41.57734688,"remaining_time":28.77349387},
{"learn":[1.800300831],"iteration":591,"passed_time":41.65412658,"remaining_time":28.70757373},
{"learn":[1.800189471],"iteration":592,"passed_time":41.73888116,"remaining_time":28.64709045},
{"learn":[1.798983902],"iteration":593,"passed_time":41.80241023,"remaining_time":28.57201777},
{"learn":[1.798595337],"iteration":594,"passed_time":41.88583799,"remaining_time":28.51052838},
{"learn":[1.796825126],"iteration":595,"passed_time":41.95213293,"remaining_time":28.43735185},
{"learn":[1.79626979],"iteration":596,"passed_time":42.01598258,"remaining_time":28.3625477},
{"learn":[1.796212401],"iteration":597,"passed_time":42.08657967,"remaining_time":28.2923161},
{"learn":[1.79526392],"iteration":598,"passed_time":42.15818464,"remaining_time":28.222758},
{"learn":[1.795072655],"iteration":599,"passed_time":42.23082501,"remaining_time":28.15388334},
{"learn":[1.794802896],"iteration":600,"passed_time":42.29954391,"remaining_time":28.08239272},
{"learn":[1.793907055],"iteration":601,"passed_time":42.3980773,"remaining_time":28.03062253},
{"learn":[1.79385214],"iteration":602,"passed_time":42.45192376,"remaining_time":27.9492765},
{"learn":[1.791374013],"iteration":603,"passed_time":42.48850633,"remaining_time":27.85670283},
{"learn":[1.79063636],"iteration":604,"passed_time":42.56838194,"remaining_time":27.79257995},
{"learn":[1.788860195],"iteration":605,"passed_time":42.65044075,"remaining_time":27.72982451},
{"learn":[1.78875589],"iteration":606,"passed_time":42.71275282,"remaining_time":27.65422053},
{"learn":[1.788695632],"iteration":607,"passed_time":42.78266183,"remaining_time":27.58355828},
{"learn":[1.788450161],"iteration":608,"passed_time":42.85034477,"remaining_time":27.5114693},
{"learn":[1.788289609],"iteration":609,"passed_time":42.91395227,"remaining_time":27.43678916},
{"learn":[1.787864735],"iteration":610,"passed_time":42.98005853,"remaining_time":27.36373612},
{"learn":[1.787629037],"iteration":611,"passed_time":43.05009177,"remaining_time":27.29319544},
{"learn":[1.787024988],"iteration":612,"passed_time":43.13348778,"remaining_time":27.23109261},
{"learn":[1.786917139],"iteration":613,"passed_time":43.19062358,"remaining_time":27.15241157},
{"learn":[1.786252124],"iteration":614,"passed_time":43.26428794,"remaining_time":27.08414773},
{"learn":[1.785959963],"iteration":615,"passed_time":43.34273753,"remaining_time":27.01884937},
{"learn":[1.785528596],"iteration":616,"passed_time":43.42249391,"remaining_time":26.95431956},
{"learn":[1.785448199],"iteration":617,"passed_time":43.50388126,"remaining_time":26.89074861},
{"learn":[1.783306715],"iteration":618,"passed_time":43.57127674,"remaining_time":26.81850798},
{"learn":[1.783254728],"iteration":619,"passed_time":43.6632594,"remaining_time":26.76135254},
{"learn":[1.782523414],"iteration":620,"passed_time":43.74442619,"remaining_time":26.69748394},
{"learn":[1.782342531],"iteration":621,"passed_time":43.80994086,"remaining_time":26.62404766},
{"learn":[1.781755885],"iteration":622,"passed_time":43.8930612,"remaining_time":26.56129065},
{"learn":[1.781425615],"iteration":623,"passed_time":44.00189258,"remaining_time":26.51396092},
{"learn":[1.781316439],"iteration":624,"passed_time":44.06675227,"remaining_time":26.44005136},
{"learn":[1.780603852],"iteration":625,"passed_time":44.14915197,"remaining_time":26.3766499},
{"learn":[1.780536831],"iteration":626,"passed_time":44.24807397,"remaining_time":26.32301689},
{"learn":[1.780497601],"iteration":627,"passed_time":44.31048658,"remaining_time":26.24761307},
{"learn":[1.780161632],"iteration":628,"passed_time":44.37913742,"remaining_time":26.17593002},
{"learn":[1.780071457],"iteration":629,"passed_time":44.44841139,"remaining_time":26.10462256},
{"learn":[1.779807128],"iteration":630,"passed_time":44.52481897,"remaining_time":26.03749318},
{"learn":[1.779661382],"iteration":631,"passed_time":44.59366038,"remaining_time":25.96592883},
{"learn":[1.7792047],"iteration":632,"passed_time":44.66245142,"remaining_time":25.89434387},
{"learn":[1.779043505],"iteration":633,"passed_time":44.7244917,"remaining_time":25.8188706},
{"learn":[1.778986268],"iteration":634,"passed_time":44.79267472,"remaining_time":25.74697051},
{"learn":[1.778882673],"iteration":635,"passed_time":44.848974,"remaining_time":25.66828072},
{"learn":[1.777870155],"iteration":636,"passed_time":44.923292,"remaining_time":25.59992935},
{"learn":[1.77733234],"iteration":637,"passed_time":45.02322277,"remaining_time":25.54609192},
{"learn":[1.776247891],"iteration":638,"passed_time":45.09437237,"remaining_time":25.47585043},
{"learn":[1.775024425],"iteration":639,"passed_time":45.17809001,"remaining_time":25.41267563},
{"learn":[1.774961943],"iteration":640,"passed_time":45.24552555,"remaining_time":25.34031774},
{"learn":[1.774284451],"iteration":641,"passed_time":45.32210084,"remaining_time":25.27307181},
{"learn":[1.77360537],"iteration":642,"passed_time":45.38311781,"remaining_time":25.19715872},
{"learn":[1.773516431],"iteration":643,"passed_time":45.4358851,"remaining_time":25.11673151},
{"learn":[1.773358622],"iteration":644,"passed_time":45.50734307,"remaining_time":25.04667719},
{"learn":[1.772702323],"iteration":645,"passed_time":45.60552358,"remaining_time":24.99126215},
{"learn":[1.772557293],"iteration":646,"passed_time":45.67438257,"remaining_time":24.91971723},
{"learn":[1.772343141],"iteration":647,"passed_time":45.74359389,"remaining_time":24.84837199},
{"learn":[1.771745978],"iteration":648,"passed_time":45.80601825,"remaining_time":24.77336272},
{"learn":[1.771635422],"iteration":649,"passed_time":45.90466208,"remaining_time":24.71789497},
{"learn":[1.771535049],"iteration":650,"passed_time":45.97429217,"remaining_time":24.64674035},
{"learn":[1.771243953],"iteration":651,"passed_time":46.05908352,"remaining_time":24.58368262},
{"learn":[1.770940609],"iteration":652,"passed_time":46.14207922,"remaining_time":24.51960412},
{"learn":[1.770763694],"iteration":653,"passed_time":46.20718043,"remaining_time":24.44600066},
{"learn":[1.770578191],"iteration":654,"passed_time":46.27299248,"remaining_time":24.37279756},
{"learn":[1.76911137],"iteration":655,"passed_time":46.34126592,"remaining_time":24.30090774},
{"learn":[1.768954476],"iteration":656,"passed_time":46.4031849,"remaining_time":24.22571145},
{"learn":[1.768016717],"iteration":657,"passed_time":46.47373717,"remaining_time":24.15504272},
{"learn":[1.767820776],"iteration":658,"passed_time":46.55559222,"remaining_time":24.09022298},
{"learn":[1.767756496],"iteration":659,"passed_time":46.64196015,"remaining_time":24.02767644},
{"learn":[1.767283322],"iteration":660,"passed_time":46.72048642,"remaining_time":23.96103615},
{"learn":[1.767027109],"iteration":661,"passed_time":46.78598033,"remaining_time":23.88770597},
{"learn":[1.76691315],"iteration":662,"passed_time":46.83945977,"remaining_time":23.80829252},
{"learn":[1.766837916],"iteration":663,"passed_time":46.90155652,"remaining_time":23.73331776},
{"learn":[1.766332429],"iteration":664,"passed_time":46.96968404,"remaining_time":23.66141978},
{"learn":[1.765853478],"iteration":665,"passed_time":47.04028235,"remaining_time":23.59077223},
{"learn":[1.765482351],"iteration":666,"passed_time":47.11583918,"remaining_time":23.52260037},
{"learn":[1.764347101],"iteration":667,"passed_time":47.18436972,"remaining_time":23.45091429},
{"learn":[1.76430045],"iteration":668,"passed_time":47.2533196,"remaining_time":23.37944512},
{"learn":[1.764236735],"iteration":669,"passed_time":47.31489117,"remaining_time":23.30434938},
{"learn":[1.764155196],"iteration":670,"passed_time":47.38494557,"remaining_time":23.23345319},
{"learn":[1.763953307],"iteration":671,"passed_time":47.48688791,"remaining_time":23.17812386},
{"learn":[1.763320117],"iteration":672,"passed_time":47.5844428,"remaining_time":23.12052421},
{"learn":[1.763012521],"iteration":673,"passed_time":47.66863869,"remaining_time":23.05634453},
{"learn":[1.762880556],"iteration":674,"passed_time":47.75476957,"remaining_time":22.9930372},
{"learn":[1.762297625],"iteration":675,"passed_time":47.81590883,"remaining_time":22.91768412},
{"learn":[1.762116362],"iteration":676,"passed_time":47.88873764,"remaining_time":22.84795016},
{"learn":[1.762078829],"iteration":677,"passed_time":47.965789,"remaining_time":22.78021247},
{"learn":[1.761943777],"iteration":678,"passed_time":48.03552982,"remaining_time":22.70899127},
{"learn":[1.761776644],"iteration":679,"passed_time":48.13469129,"remaining_time":22.65161943},
{"learn":[1.761262494],"iteration":680,"passed_time":48.21169744,"remaining_time":22.58374667},
{"learn":[1.760509444],"iteration":681,"passed_time":48.28264055,"remaining_time":22.51302008},
{"learn":[1.76015742],"iteration":682,"passed_time":48.350671,"remaining_time":22.440941},
{"learn":[1.759485133],"iteration":683,"passed_time":48.43458873,"remaining_time":22.37621351},
{"learn":[1.757991603],"iteration":684,"passed_time":48.54818336,"remaining_time":22.32507702},
{"learn":[1.757674753],"iteration":685,"passed_time":48.61162341,"remaining_time":22.25080139},
{"learn":[1.757549461],"iteration":686,"passed_time":48.67847373,"remaining_time":22.17811103},
{"learn":[1.757477771],"iteration":687,"passed_time":48.76508225,"remaining_time":22.11439776},
{"learn":[1.757424974],"iteration":688,"passed_time":48.85962561,"remaining_time":22.05419966},
{"learn":[1.757369616],"iteration":689,"passed_time":48.93274648,"remaining_time":21.9842774},
{"learn":[1.756187011],"iteration":690,"passed_time":49.0127378,"remaining_time":21.91741821},
{"learn":[1.756103664],"iteration":691,"passed_time":49.07715841,"remaining_time":21.84359074},
{"learn":[1.755906057],"iteration":692,"passed_time":49.16079667,"remaining_time":21.77830386},
{"learn":[1.755715321],"iteration":693,"passed_time":49.22882932,"remaining_time":21.70608324},
{"learn":[1.755603566],"iteration":694,"passed_time":49.28327324,"remaining_time":21.62791128},
{"learn":[1.75549478],"iteration":695,"passed_time":49.36929136,"remaining_time":21.56359853},
{"learn":[1.75540378],"iteration":696,"passed_time":49.43086962,"remaining_time":21.48859899},
{"learn":[1.754817483],"iteration":697,"passed_time":49.53026482,"remaining_time":21.42999997},
{"learn":[1.754717623],"iteration":698,"passed_time":49.59211426,"remaining_time":21.35511644},
{"learn":[1.753774292],"iteration":699,"passed_time":49.65874894,"remaining_time":21.28232098},
{"learn":[1.753562401],"iteration":700,"passed_time":49.72750196,"remaining_time":21.21044663},
{"learn":[1.753527218],"iteration":701,"passed_time":49.80549439,"remaining_time":21.14250332},
{"learn":[1.753248857],"iteration":702,"passed_time":49.87740452,"remaining_time":21.0719618},
{"learn":[1.753174775],"iteration":703,"passed_time":49.9582474,"remaining_time":21.0051722},
{"learn":[1.752880151],"iteration":704,"passed_time":50.02691038,"remaining_time":20.93324619},
{"learn":[1.75260393],"iteration":705,"passed_time":50.08892138,"remaining_time":20.85855933},
{"learn":[1.75196433],"iteration":706,"passed_time":50.15949993,"remaining_time":20.78745895},
{"learn":[1.751554822],"iteration":707,"passed_time":50.22769213,"remaining_time":20.71537585},
{"learn":[1.751412855],"iteration":708,"passed_time":50.29578033,"remaining_time":20.64326104},
{"learn":[1.751089714],"iteration":709,"passed_time":50.36445603,"remaining_time":20.57139753},
{"learn":[1.750963407],"iteration":710,"passed_time":50.42677254,"remaining_time":20.49695818},
{"learn":[1.750749529],"iteration":711,"passed_time":50.52577641,"remaining_time":20.4373927},
{"learn":[1.750731941],"iteration":712,"passed_time":50.6056916,"remaining_time":20.37003294},
{"learn":[1.750275821],"iteration":713,"passed_time":50.67027294,"remaining_time":20.29649589},
{"learn":[1.750141699],"iteration":714,"passed_time":50.73928432,"remaining_time":20.22474969},
{"learn":[1.7498107],"iteration":715,"passed_time":50.80166791,"remaining_time":20.15038225},
{"learn":[1.749761902],"iteration":716,"passed_time":50.86970148,"remaining_time":20.07827827},
{"learn":[1.748426089],"iteration":717,"passed_time":50.92432204,"remaining_time":20.00091757},
{"learn":[1.748022128],"iteration":718,"passed_time":50.98475978,"remaining_time":19.9258936},
{"learn":[1.747927262],"iteration":719,"passed_time":51.05366667,"remaining_time":19.8542037},
{"learn":[1.747670799],"iteration":720,"passed_time":51.12257707,"remaining_time":19.78252289},
{"learn":[1.74761596],"iteration":721,"passed_time":51.19996906,"remaining_time":19.71411551},
{"learn":[1.747483948],"iteration":722,"passed_time":51.26853394,"remaining_time":19.64230138},
{"learn":[1.747283819],"iteration":723,"passed_time":51.32467982,"remaining_time":19.56576192},
{"learn":[1.747232056],"iteration":724,"passed_time":51.39875297,"remaining_time":19.49607871},
{"learn":[1.746839736],"iteration":725,"passed_time":51.46713103,"remaining_time":19.42423403},
{"learn":[1.746776243],"iteration":726,"passed_time":51.53623923,"remaining_time":19.35267305},
{"learn":[1.74668858],"iteration":727,"passed_time":51.60195423,"remaining_time":19.27985103},
{"learn":[1.746234261],"iteration":728,"passed_time":51.66643115,"remaining_time":19.20658826},
{"learn":[1.746083558],"iteration":729,"passed_time":51.73555819,"remaining_time":19.13506947},
{"learn":[1.745463316],"iteration":730,"passed_time":51.79785645,"remaining_time":19.0610443},
{"learn":[1.745332598],"iteration":731,"passed_time":51.86625321,"remaining_time":18.98928396},
{"learn":[1.745097547],"iteration":732,"passed_time":51.92117623,"remaining_time":18.9126249},
{"learn":[1.744852915],"iteration":733,"passed_time":51.98097731,"remaining_time":18.83779287},
{"learn":[1.744779233],"iteration":734,"passed_time":52.04951058,"remaining_time":18.76615007},
{"learn":[1.744627174],"iteration":735,"passed_time":52.13552251,"remaining_time":18.70078525},
{"learn":[1.74424437],"iteration":736,"passed_time":52.23465882,"remaining_time":18.64004785},
{"learn":[1.744186047],"iteration":737,"passed_time":52.31904969,"remaining_time":18.57397157},
{"learn":[1.743469773],"iteration":738,"passed_time":52.39554054,"remaining_time":18.50505559},
{"learn":[1.743204517],"iteration":739,"passed_time":52.46412206,"remaining_time":18.43334018},
{"learn":[1.743122491],"iteration":740,"passed_time":52.56364099,"remaining_time":18.37244672},
{"learn":[1.74308346],"iteration":741,"passed_time":52.63224563,"remaining_time":18.30069996},
{"learn":[1.742452176],"iteration":742,"passed_time":52.69437984,"remaining_time":18.22672358},
{"learn":[1.741891086],"iteration":743,"passed_time":52.76256229,"remaining_time":18.15486014},
{"learn":[1.741242182],"iteration":744,"passed_time":52.86720639,"remaining_time":18.09548675},
{"learn":[1.741045807],"iteration":745,"passed_time":52.93248095,"remaining_time":18.02258735},
{"learn":[1.740811104],"iteration":746,"passed_time":53.04884917,"remaining_time":17.96701317},
{"learn":[1.740591817],"iteration":747,"passed_time":53.13034207,"remaining_time":17.89952701},
{"learn":[1.740533297],"iteration":748,"passed_time":53.22035103,"remaining_time":17.83485729},
{"learn":[1.740502274],"iteration":749,"passed_time":53.29416914,"remaining_time":17.76472305},
{"learn":[1.74024201],"iteration":750,"passed_time":53.37284093,"remaining_time":17.69618827},
{"learn":[1.739947793],"iteration":751,"passed_time":53.45070065,"remaining_time":17.62735873},
{"learn":[1.739723514],"iteration":752,"passed_time":53.51720699,"remaining_time":17.55478105},
{"learn":[1.7394433],"iteration":753,"passed_time":53.60646357,"remaining_time":17.48964196},
{"learn":[1.739376385],"iteration":754,"passed_time":53.72497296,"remaining_time":17.43393162},
{"learn":[1.738895061],"iteration":755,"passed_time":53.78818458,"remaining_time":17.36020772},
{"learn":[1.738835619],"iteration":756,"passed_time":53.87241043,"remaining_time":17.29325724},
{"learn":[1.738709189],"iteration":757,"passed_time":53.96912713,"remaining_time":17.23024903},
{"learn":[1.738521444],"iteration":758,"passed_time":54.02838762,"remaining_time":17.15525878},
{"learn":[1.738490702],"iteration":759,"passed_time":54.10426442,"remaining_time":17.08555718},
{"learn":[1.738424024],"iteration":760,"passed_time":54.15978835,"remaining_time":17.00944733},
{"learn":[1.738394668],"iteration":761,"passed_time":54.21666716,"remaining_time":16.93381468},
{"learn":[1.737883086],"iteration":762,"passed_time":54.31130086,"remaining_time":16.86995846},
{"learn":[1.737826057],"iteration":763,"passed_time":54.39306476,"remaining_time":16.80204618},
{"learn":[1.737706418],"iteration":764,"passed_time":54.44947523,"remaining_time":16.72630938},
{"learn":[1.737094297],"iteration":765,"passed_time":54.532309,"remaining_time":16.65869492},
{"learn":[1.736362451],"iteration":766,"passed_time":54.61343356,"remaining_time":16.59052154},
{"learn":[1.73623987],"iteration":767,"passed_time":54.69041242,"remaining_time":16.52106208},
{"learn":[1.736148091],"iteration":768,"passed_time":54.75071803,"remaining_time":16.4465746},
{"learn":[1.735973978],"iteration":769,"passed_time":54.79800829,"remaining_time":16.36823624},
{"learn":[1.735904943],"iteration":770,"passed_time":54.89506376,"remaining_time":16.30475954},
{"learn":[1.73575458],"iteration":771,"passed_time":54.99028108,"remaining_time":16.24065296},
{"learn":[1.735537257],"iteration":772,"passed_time":55.07732568,"remaining_time":16.17406588},
{"learn":[1.735368896],"iteration":773,"passed_time":55.15049113,"remaining_time":16.10337338},
{"learn":[1.735292743],"iteration":774,"passed_time":55.24327546,"remaining_time":16.0383703},
{"learn":[1.735085401],"iteration":775,"passed_time":55.32176072,"remaining_time":15.96916804},
{"learn":[1.735024556],"iteration":776,"passed_time":55.39422426,"remaining_time":15.89821366},
{"learn":[1.73473273],"iteration":777,"passed_time":55.45478449,"remaining_time":15.82385881},
{"learn":[1.734629603],"iteration":778,"passed_time":55.54406243,"remaining_time":15.75768652},
{"learn":[1.734538549],"iteration":779,"passed_time":55.63838606,"remaining_time":15.69287812},
{"learn":[1.734195772],"iteration":780,"passed_time":55.73333856,"remaining_time":15.62817048},
{"learn":[1.733501607],"iteration":781,"passed_time":55.81174712,"remaining_time":15.55877349},
{"learn":[1.733036301],"iteration":782,"passed_time":55.89108933,"remaining_time":15.48961224},
{"learn":[1.73282575],"iteration":783,"passed_time":55.95618359,"remaining_time":15.41649956},
{"learn":[1.732566842],"iteration":784,"passed_time":56.02028026,"remaining_time":15.34313409},
{"learn":[1.732512009],"iteration":785,"passed_time":56.09350281,"remaining_time":15.27227685},
{"learn":[1.732127126],"iteration":786,"passed_time":56.17726806,"remaining_time":15.20426696},
{"learn":[1.731846613],"iteration":787,"passed_time":56.26767859,"remaining_time":15.1380049},
{"learn":[1.731742928],"iteration":788,"passed_time":56.329836,"remaining_time":15.06412598},
{"learn":[1.7314196],"iteration":789,"passed_time":56.43114576,"remaining_time":15.00068432},
{"learn":[1.730651241],"iteration":790,"passed_time":56.54456386,"remaining_time":14.9403462},
{"learn":[1.730126557],"iteration":791,"passed_time":56.66229931,"remaining_time":14.8810079},
{"learn":[1.729920397],"iteration":792,"passed_time":56.74036455,"remaining_time":14.81116704},
{"learn":[1.729838451],"iteration":793,"passed_time":56.82616266,"remaining_time":14.74331172},
{"learn":[1.729790243],"iteration":794,"passed_time":56.89233603,"remaining_time":14.6703508},
{"learn":[1.729301519],"iteration":795,"passed_time":56.95476422,"remaining_time":14.59644711},
{"learn":[1.729090114],"iteration":796,"passed_time":57.00743418,"remaining_time":14.52008675},
{"learn":[1.728994683],"iteration":797,"passed_time":57.06969797,"remaining_time":14.44621427},
{"learn":[1.728953791],"iteration":798,"passed_time":57.13861106,"remaining_time":14.37404358},
{"learn":[1.728941743],"iteration":799,"passed_time":57.19766309,"remaining_time":14.29941577},
{"learn":[1.728725614],"iteration":800,"passed_time":57.27039397,"remaining_time":14.22822522},
{"learn":[1.728581191],"iteration":801,"passed_time":57.33821841,"remaining_time":14.15581951},
{"learn":[1.728480344],"iteration":802,"passed_time":57.41960611,"remaining_time":14.08675268},
{"learn":[1.728461573],"iteration":803,"passed_time":57.45837405,"remaining_time":14.00726531},
{"learn":[1.728115196],"iteration":804,"passed_time":57.5420651,"remaining_time":13.93876111},
{"learn":[1.728011971],"iteration":805,"passed_time":57.61712113,"remaining_time":13.86814082},
{"learn":[1.72792732],"iteration":806,"passed_time":57.68935574,"remaining_time":13.79683477},
{"learn":[1.727485129],"iteration":807,"passed_time":57.7687931,"remaining_time":13.72723796},
{"learn":[1.727195368],"iteration":808,"passed_time":57.8265801,"remaining_time":13.65250531},
{"learn":[1.726873097],"iteration":809,"passed_time":57.89616537,"remaining_time":13.580582},
{"learn":[1.726802129],"iteration":810,"passed_time":57.96473282,"remaining_time":13.50842725},
{"learn":[1.726775638],"iteration":811,"passed_time":58.04999579,"remaining_time":13.44014681},
{"learn":[1.726383554],"iteration":812,"passed_time":58.13434059,"remaining_time":13.37161339},
{"learn":[1.726257991],"iteration":813,"passed_time":58.2180233,"remaining_time":13.30288984},
{"learn":[1.725845155],"iteration":814,"passed_time":58.28548502,"remaining_time":13.23044752},
{"learn":[1.725812628],"iteration":815,"passed_time":58.34868765,"remaining_time":13.15705702},
{"learn":[1.725465478],"iteration":816,"passed_time":58.45074536,"remaining_time":13.09239462},
{"learn":[1.725188424],"iteration":817,"passed_time":58.53231649,"remaining_time":13.02308264},
{"learn":[1.724673242],"iteration":818,"passed_time":58.63218119,"remaining_time":12.95778363},
{"learn":[1.724499839],"iteration":819,"passed_time":58.7168591,"remaining_time":12.88906663},
{"learn":[1.723641701],"iteration":820,"passed_time":58.78559167,"remaining_time":12.81683424},
{"learn":[1.723466324],"iteration":821,"passed_time":58.86312692,"remaining_time":12.74651653},
{"learn":[1.723390597],"iteration":822,"passed_time":58.93278303,"remaining_time":12.67448675},
{"learn":[1.722951244],"iteration":823,"passed_time":59.02996476,"remaining_time":12.60834199},
{"learn":[1.722604946],"iteration":824,"passed_time":59.11416802,"remaining_time":12.53936897},
{"learn":[1.722423595],"iteration":825,"passed_time":59.18383729,"remaining_time":12.46729744},
{"learn":[1.722353133],"iteration":826,"passed_time":59.26038386,"remaining_time":12.39667039},
{"learn":[1.722130185],"iteration":827,"passed_time":59.32960136,"remaining_time":12.32450656},
{"learn":[1.721934407],"iteration":828,"passed_time":59.40396491,"remaining_time":12.25341134},
{"learn":[1.721563339],"iteration":829,"passed_time":59.52532731,"remaining_time":12.19193451},
{"learn":[1.721418561],"iteration":830,"passed_time":59.59636636,"remaining_time":12.12007932},
{"learn":[1.721340522],"iteration":831,"passed_time":59.65851506,"remaining_time":12.04643093},
{"learn":[1.721044519],"iteration":832,"passed_time":59.74340328,"remaining_time":11.97736897},
{"learn":[1.720894821],"iteration":833,"passed_time":59.82785955,"remaining_time":11.90818308},
{"learn":[1.720780462],"iteration":834,"passed_time":59.91174522,"remaining_time":11.83884786},
{"learn":[1.720312858],"iteration":835,"passed_time":59.99536739,"remaining_time":11.76942614},
{"learn":[1.720154262],"iteration":836,"passed_time":60.09546394,"remaining_time":11.70317876},
{"learn":[1.720090358],"iteration":837,"passed_time":60.17952527,"remaining_time":11.63375071},
{"learn":[1.719549259],"iteration":838,"passed_time":60.28311572,"remaining_time":11.56803532},
{"learn":[1.718919212],"iteration":839,"passed_time":60.36010317,"remaining_time":11.49716251},
{"learn":[1.718847768],"iteration":840,"passed_time":60.43256027,"remaining_time":11.42541865},
{"learn":[1.718789861],"iteration":841,"passed_time":60.51000311,"remaining_time":11.35460866},
{"learn":[1.718643971],"iteration":842,"passed_time":60.59299164,"remaining_time":11.28481576},
{"learn":[1.718306508],"iteration":843,"passed_time":60.6765724,"remaining_time":11.21510106},
{"learn":[1.718030526],"iteration":844,"passed_time":60.75470663,"remaining_time":11.14435447},
{"learn":[1.717937978],"iteration":845,"passed_time":60.81687379,"remaining_time":11.07068388},
{"learn":[1.717786442],"iteration":846,"passed_time":60.87986908,"remaining_time":10.99719005},
{"learn":[1.717405932],"iteration":847,"passed_time":60.9939538,"remaining_time":10.93287851},
{"learn":[1.717357188],"iteration":848,"passed_time":61.08825107,"remaining_time":10.8649304},
{"learn":[1.717094129],"iteration":849,"passed_time":61.15403757,"remaining_time":10.79188898},
{"learn":[1.716743637],"iteration":850,"passed_time":61.22984851,"remaining_time":10.72061978},
{"learn":[1.716523337],"iteration":851,"passed_time":61.33617269,"remaining_time":10.65464033},
{"learn":[1.716357966],"iteration":852,"passed_time":61.41649869,"remaining_time":10.58408594},
{"learn":[1.716332279],"iteration":853,"passed_time":61.50514496,"remaining_time":10.51493111},
{"learn":[1.716071341],"iteration":854,"passed_time":61.61946626,"remaining_time":10.45008492},
{"learn":[1.716014124],"iteration":855,"passed_time":61.69620118,"remaining_time":10.3788002},
{"learn":[1.715971619],"iteration":856,"passed_time":61.76130816,"remaining_time":10.3055625},
{"learn":[1.715726724],"iteration":857,"passed_time":61.84949122,"remaining_time":10.23616288},
{"learn":[1.715562172],"iteration":858,"passed_time":61.91811382,"remaining_time":10.16350879},
{"learn":[1.715458531],"iteration":859,"passed_time":61.98839127,"remaining_time":10.09113346},
{"learn":[1.715230236],"iteration":860,"passed_time":62.08579683,"remaining_time":10.02314258},
{"learn":[1.714869723],"iteration":861,"passed_time":62.15480608,"remaining_time":9.950537401},
{"learn":[1.714637327],"iteration":862,"passed_time":62.24672101,"remaining_time":9.881576799},
{"learn":[1.714568738],"iteration":863,"passed_time":62.32033871,"remaining_time":9.809682945},
{"learn":[1.714470666],"iteration":864,"passed_time":62.38474688,"remaining_time":9.736347779},
{"learn":[1.714449248],"iteration":865,"passed_time":62.44690198,"remaining_time":9.662684602},
{"learn":[1.714246534],"iteration":866,"passed_time":62.51479028,"remaining_time":9.589927459},
{"learn":[1.714168575],"iteration":867,"passed_time":62.61422255,"remaining_time":9.521978544},
{"learn":[1.713223442],"iteration":868,"passed_time":62.68551624,"remaining_time":9.449715337},
{"learn":[1.712521898],"iteration":869,"passed_time":62.76819329,"remaining_time":9.379155319},
{"learn":[1.712370256],"iteration":870,"passed_time":62.84735736,"remaining_time":9.308047187},
{"learn":[1.712161358],"iteration":871,"passed_time":62.91307911,"remaining_time":9.234947392},
{"learn":[1.712065006],"iteration":872,"passed_time":62.96884114,"remaining_time":9.160415607},
{"learn":[1.711347286],"iteration":873,"passed_time":63.06569565,"remaining_time":9.09185086},
{"learn":[1.711294502],"iteration":874,"passed_time":63.14374006,"remaining_time":9.020534294},
{"learn":[1.711120713],"iteration":875,"passed_time":63.21294517,"remaining_time":8.947951142},
{"learn":[1.710838588],"iteration":876,"passed_time":63.2961543,"remaining_time":8.877339771},
{"learn":[1.710566272],"iteration":877,"passed_time":63.36531122,"remaining_time":8.804747117},
{"learn":[1.710403904],"iteration":878,"passed_time":63.44217936,"remaining_time":8.733223781},
{"learn":[1.710200126],"iteration":879,"passed_time":63.51033588,"remaining_time":8.660500347},
{"learn":[1.710167827],"iteration":880,"passed_time":63.56776844,"remaining_time":8.586338756},
{"learn":[1.71013909],"iteration":881,"passed_time":63.67842073,"remaining_time":8.5193352},
{"learn":[1.709913628],"iteration":882,"passed_time":63.74104057,"remaining_time":8.445868343},
{"learn":[1.709780949],"iteration":883,"passed_time":63.82544459,"remaining_time":8.375284584},
{"learn":[1.709568197],"iteration":884,"passed_time":63.90093015,"remaining_time":8.303510698},
{"learn":[1.709293175],"iteration":885,"passed_time":63.95013897,"remaining_time":8.228347452},
{"learn":[1.708816916],"iteration":886,"passed_time":64.03471574,"remaining_time":8.157748454},
{"learn":[1.708131903],"iteration":887,"passed_time":64.11177428,"remaining_time":8.086169729},
{"learn":[1.70801326],"iteration":888,"passed_time":64.19240943,"remaining_time":8.01502525},
{"learn":[1.70799781],"iteration":889,"passed_time":64.29128739,"remaining_time":7.946114172},
{"learn":[1.707666822],"iteration":890,"passed_time":64.37745305,"remaining_time":7.875580677},
{"learn":[1.707591054],"iteration":891,"passed_time":64.46214229,"remaining_time":7.804833371},
{"learn":[1.706830673],"iteration":892,"passed_time":64.53891435,"remaining_time":7.733106198},
{"learn":[1.706359884],"iteration":893,"passed_time":64.60583287,"remaining_time":7.660199423},
{"learn":[1.705738982],"iteration":894,"passed_time":64.69035736,"remaining_time":7.589371534},
{"learn":[1.705689088],"iteration":895,"passed_time":64.760129,"remaining_time":7.516800687},
{"learn":[1.705582049],"iteration":896,"passed_time":64.83596719,"remaining_time":7.444932688},
{"learn":[1.705532518],"iteration":897,"passed_time":64.90402486,"remaining_time":7.372172089},
{"learn":[1.705481653],"iteration":898,"passed_time":64.98296402,"remaining_time":7.300644456},
{"learn":[1.705369495],"iteration":899,"passed_time":65.02745477,"remaining_time":7.225272752},
{"learn":[1.705275791],"iteration":900,"passed_time":65.10737287,"remaining_time":7.15386228},
{"learn":[1.705169325],"iteration":901,"passed_time":65.18735265,"remaining_time":7.082439645},
{"learn":[1.704706853],"iteration":902,"passed_time":65.25528988,"remaining_time":7.00970445},
{"learn":[1.703540653],"iteration":903,"passed_time":65.31792499,"remaining_time":6.936416813},
{"learn":[1.703516985],"iteration":904,"passed_time":65.38879409,"remaining_time":6.864017059},
{"learn":[1.703177624],"iteration":905,"passed_time":65.46227728,"remaining_time":6.791891904},
{"learn":[1.70309246],"iteration":906,"passed_time":65.52558738,"remaining_time":6.718720646},
{"learn":[1.702898182],"iteration":907,"passed_time":65.60006937,"remaining_time":6.646703064},
{"learn":[1.702817559],"iteration":908,"passed_time":65.65501842,"remaining_time":6.572724617},
{"learn":[1.702104993],"iteration":909,"passed_time":65.7544321,"remaining_time":6.503185593},
{"learn":[1.701937732],"iteration":910,"passed_time":65.82713985,"remaining_time":6.43097195},
{"learn":[1.701613959],"iteration":911,"passed_time":65.88163447,"remaining_time":6.356999817},
{"learn":[1.701538703],"iteration":912,"passed_time":65.95259681,"remaining_time":6.284639565},
{"learn":[1.700911321],"iteration":913,"passed_time":66.01957439,"remaining_time":6.211907437},
{"learn":[1.700863587],"iteration":914,"passed_time":66.09818003,"remaining_time":6.14026809},
{"learn":[1.700833922],"iteration":915,"passed_time":66.17699078,"remaining_time":6.068632342},
{"learn":[1.700756456],"iteration":916,"passed_time":66.24019495,"remaining_time":5.995568354},
{"learn":[1.700694309],"iteration":917,"passed_time":66.31318597,"remaining_time":5.923400054},
{"learn":[1.700243589],"iteration":918,"passed_time":66.41312046,"remaining_time":5.853604741},
{"learn":[1.69890904],"iteration":919,"passed_time":66.49646512,"remaining_time":5.782301315},
{"learn":[1.698681656],"iteration":920,"passed_time":66.551709,"remaining_time":5.708561359},
{"learn":[1.698640325],"iteration":921,"passed_time":66.63956968,"remaining_time":5.637620863},
{"learn":[1.698572732],"iteration":922,"passed_time":66.73914138,"remaining_time":5.567620679},
{"learn":[1.698515264],"iteration":923,"passed_time":66.81135899,"remaining_time":5.495306584},
{"learn":[1.698508167],"iteration":924,"passed_time":66.89440376,"remaining_time":5.423870575},
{"learn":[1.698083321],"iteration":925,"passed_time":66.94836293,"remaining_time":5.350085159},
{"learn":[1.698069594],"iteration":926,"passed_time":66.98778627,"remaining_time":5.27519784},
{"learn":[1.69799519],"iteration":927,"passed_time":67.0787265,"remaining_time":5.204383953},
{"learn":[1.697979601],"iteration":928,"passed_time":67.150183,"remaining_time":5.132037667},
{"learn":[1.697663894],"iteration":929,"passed_time":67.24592847,"remaining_time":5.061521498},
{"learn":[1.697529461],"iteration":930,"passed_time":67.30762812,"remaining_time":4.988427863},
{"learn":[1.697496181],"iteration":931,"passed_time":67.37870218,"remaining_time":4.916042648},
{"learn":[1.697478899],"iteration":932,"passed_time":67.44945514,"remaining_time":4.843637186},
{"learn":[1.697457132],"iteration":933,"passed_time":67.5174454,"remaining_time":4.771040039},
{"learn":[1.697180922],"iteration":934,"passed_time":67.59199843,"remaining_time":4.698908982},
{"learn":[1.697133267],"iteration":935,"passed_time":67.67532543,"remaining_time":4.627372679},
{"learn":[1.696856354],"iteration":936,"passed_time":67.74643699,"remaining_time":4.554989894},
{"learn":[1.696477954],"iteration":937,"passed_time":67.84375045,"remaining_time":4.484341714},
{"learn":[1.695877423],"iteration":938,"passed_time":67.92184569,"remaining_time":4.412388272},
{"learn":[1.695144913],"iteration":939,"passed_time":68.0201598,"remaining_time":4.341712328},
{"learn":[1.695135785],"iteration":940,"passed_time":68.09038467,"remaining_time":4.269216467},
{"learn":[1.694683991],"iteration":941,"passed_time":68.17244214,"remaining_time":4.197453975},
{"learn":[1.694551902],"iteration":942,"passed_time":68.24324535,"remaining_time":4.12498938},
{"learn":[1.693480161],"iteration":943,"passed_time":68.30331691,"remaining_time":4.051891681},
{"learn":[1.693393466],"iteration":944,"passed_time":68.38791129,"remaining_time":3.980248805},
{"learn":[1.693149194],"iteration":945,"passed_time":68.47634178,"remaining_time":3.908797523},
{"learn":[1.692655451],"iteration":946,"passed_time":68.54818758,"remaining_time":3.836382198},
{"learn":[1.692578781],"iteration":947,"passed_time":68.58313882,"remaining_time":3.761944324},
{"learn":[1.691860421],"iteration":948,"passed_time":68.65482179,"remaining_time":3.689563658},
{"learn":[1.691386559],"iteration":949,"passed_time":68.7167364,"remaining_time":3.616670337},
{"learn":[1.69126633],"iteration":950,"passed_time":68.81770752,"remaining_time":3.54581248},
{"learn":[1.69092329],"iteration":951,"passed_time":68.90031484,"remaining_time":3.473965454},
{"learn":[1.690231678],"iteration":952,"passed_time":68.98437167,"remaining_time":3.402167333},
{"learn":[1.690213676],"iteration":953,"passed_time":69.03968851,"remaining_time":3.328957727},
{"learn":[1.690203822],"iteration":954,"passed_time":69.11521645,"remaining_time":3.256737948},
{"learn":[1.690179809],"iteration":955,"passed_time":69.18473082,"remaining_time":3.184234473},
{"learn":[1.689838017],"iteration":956,"passed_time":69.2840941,"remaining_time":3.113078418},
{"learn":[1.68958977],"iteration":957,"passed_time":69.32803055,"remaining_time":3.03943349},
{"learn":[1.689351975],"iteration":958,"passed_time":69.38336701,"remaining_time":2.966337901},
{"learn":[1.689269812],"iteration":959,"passed_time":69.48315639,"remaining_time":2.895131516},
{"learn":[1.689233954],"iteration":960,"passed_time":69.5670442,"remaining_time":2.823220316},
{"learn":[1.689086309],"iteration":961,"passed_time":69.63872837,"remaining_time":2.75080216},
{"learn":[1.689061998],"iteration":962,"passed_time":69.69685217,"remaining_time":2.677864517},
{"learn":[1.688800068],"iteration":963,"passed_time":69.77358778,"remaining_time":2.605652656},
{"learn":[1.687531828],"iteration":964,"passed_time":69.85914297,"remaining_time":2.533751299},
{"learn":[1.687194005],"iteration":965,"passed_time":69.92033862,"remaining_time":2.460964299},
{"learn":[1.687165462],"iteration":966,"passed_time":69.97486871,"remaining_time":2.387973803},
{"learn":[1.687003782],"iteration":967,"passed_time":70.03547009,"remaining_time":2.315222152},
{"learn":[1.686384862],"iteration":968,"passed_time":70.07296547,"remaining_time":2.241756377},
{"learn":[1.686082315],"iteration":969,"passed_time":70.1640345,"remaining_time":2.170021686},
{"learn":[1.685832769],"iteration":970,"passed_time":70.23527452,"remaining_time":2.097654955},
{"learn":[1.685648559],"iteration":971,"passed_time":70.31094064,"remaining_time":2.025418043},
{"learn":[1.685393249],"iteration":972,"passed_time":70.37805669,"remaining_time":1.952936825},
{"learn":[1.685302416],"iteration":973,"passed_time":70.46297064,"remaining_time":1.880941721},
{"learn":[1.68505343],"iteration":974,"passed_time":70.53669393,"remaining_time":1.808633178},
{"learn":[1.684517357],"iteration":975,"passed_time":70.58655697,"remaining_time":1.735735007},
{"learn":[1.684198217],"iteration":976,"passed_time":70.65602852,"remaining_time":1.663345605},
{"learn":[1.683963703],"iteration":977,"passed_time":70.70680128,"remaining_time":1.590541542},
{"learn":[1.68348753],"iteration":978,"passed_time":70.79011095,"remaining_time":1.518480419},
{"learn":[1.683332425],"iteration":979,"passed_time":70.89228055,"remaining_time":1.446781236},
{"learn":[1.683140019],"iteration":980,"passed_time":70.97554253,"remaining_time":1.374653729},
{"learn":[1.682995339],"iteration":981,"passed_time":71.05975171,"remaining_time":1.302520907},
{"learn":[1.682861994],"iteration":982,"passed_time":71.14244358,"remaining_time":1.230337275},
{"learn":[1.682809229],"iteration":983,"passed_time":71.22693811,"remaining_time":1.158161595},
{"learn":[1.682557988],"iteration":984,"passed_time":71.28114651,"remaining_time":1.085499693},
{"learn":[1.682282067],"iteration":985,"passed_time":71.32455152,"remaining_time":1.012721827},
{"learn":[1.682253881],"iteration":986,"passed_time":71.39619424,"remaining_time":0.9403754053},
{"learn":[1.682047269],"iteration":987,"passed_time":71.45093895,"remaining_time":0.8678251694},
{"learn":[1.681960898],"iteration":988,"passed_time":71.50385008,"remaining_time":0.7952905469},
{"learn":[1.681925877],"iteration":989,"passed_time":71.55613205,"remaining_time":0.7227892126},
{"learn":[1.68163131],"iteration":990,"passed_time":71.63766306,"remaining_time":0.6505943164},
{"learn":[1.681484553],"iteration":991,"passed_time":71.70146295,"remaining_time":0.5782376045},
{"learn":[1.681330663],"iteration":992,"passed_time":71.78455103,"remaining_time":0.5060340959},
{"learn":[1.680358549],"iteration":993,"passed_time":71.85401161,"remaining_time":0.4337264282},
{"learn":[1.680187873],"iteration":994,"passed_time":71.93773411,"remaining_time":0.3614961513},
{"learn":[1.679951021],"iteration":995,"passed_time":72.02026071,"remaining_time":0.2892379948},
{"learn":[1.679368552],"iteration":996,"passed_time":72.085503,"remaining_time":0.2169072307},
{"learn":[1.679174726],"iteration":997,"passed_time":72.18298787,"remaining_time":0.1446552863},
{"learn":[1.679031102],"iteration":998,"passed_time":72.2826206,"remaining_time":0.07235497558},
{"learn":[1.678891232],"iteration":999,"passed_time":72.36751025,"remaining_time":0}
]}